Workbook

Sheet README
A1: Novčić Pay — pricing model and calculations 2027
A2: Price Management, ZSEM MBA 2026/27 · individual pricing project · case 05 (Case Book p. 7) · model built 02.10.2026, audited and extended 05.10.2026
A4: What this file is
A5: The one place where every number of the project is produced. Type only on the Inputs sheet; every other sheet is live formulas. The website and the dashboard show the same figures (sheet 'Dashboard map').
A7: Read in this order
A8: 1 · KPIs — the 18 measures that judge the price list (definition, formula, result, criterion, met or not, interpretation) and the eight operating KPIs for 2027.
A9: 2 · Inputs — CASE FACTS (blue), ASSUMPTIONS not on the case sheet (orange), DECISIONS = the price list (green).
A10: 3 · Segment economics — contribution per customer per month for each segment under each offer (today, Basic, Plus, Travel).
A11: 4 · Model — the recommended structure: each segment followed through its choices (buys the plan / stays on Basic / leaves), contribution per offer and in total, profit.
A12: 5 · Bridge — from today's loss to the 2027 contribution, line by line.
A13: 6 · Alternatives — the same customers under five structures: everything free, fees per use only, one monthly fee, Basic + Travel only, the recommendation.
A14: 7 · Price grid — contribution of each segment at each surveyed price point.
... A29: The company is fictitious; all case figures were invented for the course.

Sheet KPIs
A1: KPI register — definition, formula, result, criterion, verdict, interpretation, source
A2: Part 1: the KPIs that judge the price list itself (all results are live formulas). Part 2: the eight operating KPIs Novčić would track in 2027 (Balanced Scorecard; Kaplan & Norton 1992). Criteria are the project's own unless marked 'case'.
A4: Part 1 · Does the price list do its job? (model results)
A5: # | B5: Objective | C5: KPI | D5: Definition / formula | E5: Result | F5: Criterion | G5: Met? | H5: Interpretation | I5: Workbook source | J5: Dashboard page
A6: 1 | B6: Pay for itself from 2027 (case) | C6: Profit after fixed costs | D6: Contribution − fixed costs of 700,000 | E6: =reco_profit -> 176182.4 | F6: ≥ 0 (case: the account has to pay for itself) | G6: =IF(E6>=0,"met","NOT MET") -> met | H6: The price list turns a loss of 1.28 million into a profit. This is the base case: the survey taken at face value. | I6: Model | J6: Overview · 3 Numbers
A7: 2 | B7: Pay for itself from 2027 (case) | C7: Contribution per year | D7: Σ income − Σ variable cost, all retained customers × 12 | E7: =reco_total -> 876182.4 | F7: ≥ fixed costs (700,000) | G7: =IF(E7>=fixed,"met","NOT MET") -> met | H7: Plans and per-use fees each deliver about half. | I7: Model | J7: 3 Numbers
A8: 3 | B8: Pay for itself from 2027 (case) | C8: Safety margin | D8: 1 − fixed costs ÷ contribution | E8: =1-fixed/reco_total -> 0.20107959 | F8: ≥ 10% | G8: =IF(E8>=0.1,"met","NOT MET") -> met | H8: Contribution may fall by a fifth before a loss. | I8: Break-even B10 | J8: 3 Numbers
A9: 4 | B9: Pay for itself from 2027 (case) | C9: Break-even customers | D9: Fixed costs ÷ (blended contribution per customer × 12) | E9: ='Break-even'!B9 -> 30231.148 | F9: ≤ customers retained | G9: =IF(E9<=Model!E13,"met","NOT MET") -> met | H9: 30,231 of the 37,840 retained customers are needed at the model's mix. | I9: Break-even B9 | J9: 3 Numbers
A10: 5 | B10: Pay for itself from 2027 (case) | C10: Gain over the best alternative structure | D10: Contribution ÷ highest contribution among A–D − 1 | E10: =reco_total/MAX(Alternatives!E5:E8)-1 -> 0.13720213 | F10: > 0 | G10: =IF(E10>0,"met","NOT MET") -> met | H10: Segmented pricing beats one price (handout 04). The flat fee is compared at the level set on Inputs (3.99). | I10: Alternatives | J10: Overview · 3 Numbers
A11: 6 | B11: Keep the generation | C11: Customers retained | D11: Retained customers ÷ 40,000 | E11: =Model!E13/Inputs!$B$10 -> 0.946 | F11: ≥ retention of per-use fees alone (B) | G11: =IF(E11>=Alternatives!G6/Inputs!$B$10,"met","NOT MET") -> met | H11: The plans do not only add income; they keep 2,200 customers that pure per-use fees would lose (mainly travellers). | I11: Model | J11: Overview
A12: 7 | B12: Keep the generation | C12: Students retained | D12: Students retained ÷ 24,000 | E12: =Model!B13/Inputs!$B$6 -> 0.954 | F12: ≥ 95% | G12: =IF(E12>=0.95,"met","NOT MET") -> met | H12: The pipeline segment stays almost intact; a monthly fee would keep 45%. | I12: Model | J12: 1 Customers
A13: 8 | B13: Charge for what costs us | C13: Cash cost coverage | D13: Withdrawal fee income ÷ cost of all withdrawals (incl. those in plans) | E13: =Model!E33/-Model!E39 -> 1.0134889 | F13: ≥ 100% | G13: =IF(E13>=1,"met","NOT MET") -> met | H13: The largest variable cost is now paid for by those who cause it — with one point to spare, so it is the first ratio to watch. | I13: Model (income and cost rows) | J13: 3 Numbers · KPIs
A14: 9 | B14: Charge for what costs us | C14: Lowest contribution per customer among the segments on Basic | D14: MIN of Basic contribution per month (students, employees, travellers) | E14: =MIN('Segment economics'!C15,'Segment economics'!G15,'Segment economics'!K15) -> 0.7 | F14: > 0 | G14: =IF(E14>0,"met","NOT MET") -> met | H14: Every segment covers its variable cost even without a plan; today none does. | I14: Segment economics | J14: 1 Customers
A15: 10 | B15: Plans customers choose | C15: Plan attach rate | D15: Plus + Travel subscribers ÷ customers retained | E15: =Model!E9/Model!E13 -> 0.25158562 | F15: ≥ 25% | G15: =IF(E15>=0.25,"met","NOT MET") -> met | H15: A quarter of the customers produce half of the contribution. | I15: Model | J15: 3 Numbers · KPIs
A16: 11 | B16: Price inside the value range | C16: Plus: price position | D16: (price − reference value) ÷ (proxy EVC − reference value) | E16: =EVE!B33 -> 0.49748744 | F16: between 0% and 100% | G16: =IF(AND(E16>=0,E16<=1),"met","NOT MET") -> met | H16: Plus captures half of the differentiation value (50:50 starting point, handout 07). | I16: EVE B29:B33 | J16: 2 Pricing
A17: 12 | B17: Price inside the value range | C17: Travel: price minus reference value | D17: Travel price − Fluxa bill for the same usage | E17: =EVE!B14 -> -1.01 | F17: reference value ≤ price ≤ EVC (value-based range) | G17: =IF(AND(EVE!B12>=EVE!B6,EVE!B12<=EVE!B9),"met","NOT MET") -> NOT MET | H17: NOT MET ON PURPOSE: 6.99 is below the value-based floor of 8.00 (penetration price). It is the contribution-maximising surveyed price and keeps 70% of the segment; stated willingness to pay centres on the reference value. Above the cost floor of 2.70. 7.99 is the price to test. | I17: EVE B6:B16 | J17: 2 Pricing
A18: 13 | B18: Price level holds | C18: Neighbouring surveyed prices that would raise total profit | D18: Count of 4 moves (Plus 2.99, Plus 4.99, Travel 5.99, Travel 8.99; Plus has one price for students and employees) with a higher profit than the price list | E18: =(Sensitivity!AG27>reco_profit)+(Sensitivity!AG23>reco_profit)+(Sensitivity!AG21>reco_profit)+(Sensitivity!AG24>reco_profit) -> 0 | F18: =0 -> 0 | G18: =IF(E18=0,"met","NOT MET") -> met | H18: No neighbouring surveyed price earns more in total. Closest: Travel 8.99 (−14,400) and Plus 4.99 (−19,700). For students alone 2.99 would pay (+7,700), but the employees lose 56,500 at that price. | I18: Sensitivity · Break-even rows 39–58 | J18: 2 Pricing · 3 Numbers
A19: 14 | B19: Structure fits the segments | C19: Self-selection holds | D19: Travel is the cheapest offer for travellers AND Plus is not cheaper than Basic for the typical employee | E19: =IF(AND(Arbitrage!E7="Travel",Arbitrage!C6>Arbitrage!B6),1,0) -> 1 | F19: =1 -> 1 | G19: =IF(E19=1,"met","NOT MET") -> met | H19: Travellers gain by choosing Travel; employees buy Plus for its features, not to avoid fees (no cannibalisation). | I19: Arbitrage | J19: 2 Pricing
A20: 15 | B20: Robust, not only optimal | C20: Probability of at least breaking even under joint uncertainty | D20: Share of 5,000 simulated draws with profit ≥ 0 | E20: =1-'Stress test'!H40 -> 0.8618 | F20: ≥ 80% and above every alternative | G20: =IF(AND(E20>=0.8,'Stress test'!H40<MIN('Stress test'!H41:H43)),"met","NOT MET") -> met | H20: The recommendation is the only structure that breaks even in most draws (one fee: about 30%). | I20: Stress test, block C | J20: Risk
A21: 16 | B21: Robust, not only optimal | C21: Median profit under joint uncertainty | D21: Median of 5,000 draws | E21: ='Stress test'!E40 -> 52915.517 | F21: > 0 | G21: =IF(E21>0,"met","NOT MET") -> met | H21: The honest expectation is about a third of the base case: the base case is close to the best case. | I21: Stress test, block C | J21: Overview · Risk
A22: 17 | B22: Robust, not only optimal | C22: Withdrawals Basic customers may avoid before a loss | D22: Switching value of the withdrawal reduction | E22: ='Stress test'!F6 -> 0.8233438 | F22: ≥ 50% | G22: =IF(E22>=0.5,"met","NOT MET") -> met | H22: Withdrawals would have to fall by more than four fifths. | I22: Stress test, block A | J22: Risk
A23: 18 | B23: Robust, not only optimal | C23: Profit in the combined downside scenario | D23: 50% fewer withdrawals, take-up −20%, features 0.25 | E23: =Sensitivity!AG26 -> 6245.12 | F23: ≥ 0 | G23: =IF(E23>=0,"met","NOT MET") -> met | H23: Three adverse moves at once still leave break-even. | I23: Sensitivity | J23: Risk
C24: KPIs met | E24: =COUNTIF(G6:G23,"met") -> 17 | F24: of 18
A26: Part 2 · Operating scorecard 2027: what Novčić measures from the first month (targets follow from the model; none can be 'met' before launch)
A27: # | B27: Perspective · objective | C27: Measure | D27: Definition | E27: Model baseline | F27: Target | G27: Lead / lag | H27: Why this KPI, and what triggers a review | I27: Data source | J27: Dashboard page
A28: 1 | B28: Financial · pay for itself | C28: Contribution per active customer per month | D28: Contribution ÷ active customers ÷ 12 | E28: ='Break-even'!B8 -> 1.9295772 | F28: ≥ 1.93 (break-even at 30,231 customers) | G28: lag | H28: One number that says whether the price list works; profit alone would hide a shrinking base. | I28: Novčić account data (from January 2027) | J28: KPIs and roll-out
A29: 2 | B29: Financial · charge for what costs us | C29: Cash cost coverage | D29: Withdrawal fee income ÷ withdrawal cost | E29: =Model!E33/-Model!E39 -> 1.0134889 | F29: ≥ 100% | G29: lead | H29: Moves months before profit does. Below 100% for a quarter → review the withdrawal fee. | I29: Novčić account data (from January 2027) | J29: KPIs and roll-out
A30: 3 | B30: Customer · keep the generation | C30: Customers retained after the price list | D30: Active customers ÷ 40,000 | E30: =Model!E13/Inputs!$B$10 -> 0.946 | F30: ≥ 94%; students ≥ 95% | G30: lag | H30: The reason for the €0 account. A monthly fee would have cut this to 58.5%. | I30: Novčić account data (from January 2027) | J30: KPIs and roll-out
A31: 4 | B31: Customer · plans customers choose | C31: Plan attach rate | D31: Subscribers ÷ active customers; Travel take-up among travellers | E31: =Model!E9/Model!E13 -> 0.25158562 | F31: ≥ 25%; Travel ≥ 70% of travellers | G31: lead | H31: Demand-side test of the value message. Travel take-up above 80% for two quarters → test 7.99. | I31: Novčić account data (from January 2027) | J31: KPIs and roll-out
A32: 5 | B32: Internal process · be the transparent one | C32: Mark-up shown before payment; fee complaints | D32: Share of currency payments with the ECB mark-up shown before confirmation; complaints per 1,000 customers | E32: n/a | F32: 100% · < 2 per 1,000 | G32: lead | H32: A legal constraint and the fairness lever (handout 05). | I32: Novčić account data (from January 2027) | J32: KPIs and roll-out
A33: 6 | B33: Internal process · keep cash use economic | C33: Withdrawals per Basic customer per month | D33: Withdrawals ÷ Basic customers | E33: =(Model!B12*Inputs!$E$6+Model!C12*Inputs!$E$7+Model!D12*Inputs!$E$8)/Model!E12 -> 1.259322 | F33: track; review below 0.9 | G33: lead | H33: Turns the biggest model uncertainty into a measured number (profit is zero at −82%). | I33: Novčić account data (from January 2027) | J33: KPIs and roll-out
A34: 7 | B34: Learning and growth · explain the price list | C34: Support staff certified on the fee information document | D34: Certified ÷ support staff | E34: n/a | F34: 100% before launch | G34: lead | H34: The fee document and the ECB rule are only as good as the people who explain them. | I34: Novčić account data (from January 2027) | J34: KPIs and roll-out
A35: 8 | B35: Learning and growth · price with evidence | C35: Monthly take-up and churn report by segment, with a named owner | D35: Report live yes/no; quarterly price review held | E35: n/a | F35: live in Q1 2027 | G35: lead | H35: The model's assumptions must be replaced by observed data within one quarter. | I35: Novčić account data (from January 2027) | J35: KPIs and roll-out

Sheet Inputs
A1: Inputs — case facts, assumptions, decisions
A2: Blue = fact from the case sheet · orange = assumption (not on the sheet) · green = decision. Only these cells are typed in; everything else is a formula.
A4: CASE FACTS — customers and what they told us (survey of 2,000 customers)
A5: Segment | B5: Customers | C5: Card payments / month | D5: of which other currencies | E5: Cash withdrawals / month | F5: Leave if the account itself has a monthly fee | G5: Leave if per-use fees (of those who pay them) | H5: Plan price 1 | I5: Share 1 | J5: Plan price 2 | K5: Share 2 | L5: Plan price 3 | M5: Share 3
A6: Students (18–22) | B6: 24000 | C6: 250 | D6: 25 | E6: 1 | F6: 0.55 | G6: 0.05 | H6: 2.99 | I6: 0.15 | J6: 3.99 | K6: 0.08 | L6: 4.99 | M6: 0.04
A7: Young employees (23–26) | B7: 12000 | C7: 900 | D7: 50 | E7: 2 | F7: 0.25 | G7: 0.03 | H7: 2.99 | I7: 0.5 | J7: 3.99 | K7: 0.4 | L7: 4.99 | M7: 0.2
A8: Travellers | B8: 4000 | C8: 800 | D8: 400 | E8: 2 | F8: 0.1 | G8: 0.7 | H8: 5.99 | I8: 0.8 | J8: 6.99 | K8: 0.7 | L8: 8.99 | M8: 0.3
A9: Plan asked about: students and employees — free cash withdrawals, shared accounts, virtual cards. Travellers — no currency fee, free withdrawals worldwide, travel insurance.
A10: Total customers | B10: =SUM(B6:B8) -> 40000
A12: CASE FACTS — income and costs
A13: Income from merchants' banks: share of all card payments (EU limit for debit cards) | B13: 0.002
A14: Cost per customer per month (card, processing, checks, support) | B14: 0.6
A15: Cost per cash withdrawal | B15: 1
A16: Cost of payments in other currencies (share of amount) | B16: 0.003
A17: Travel insurance per insured customer per month | B17: 0.5
A18: Fixed costs per year (licence, compliance, IT, staff) | B18: 700000
A20: CASE FACTS — survey fee scenario and competitors
A21: Survey scenario: fee per cash withdrawal | B21: 1.5
A22: Survey scenario: fee on other currencies, above the ECB rate | B22: 0.015
A23: Fluxa: fee on other currencies | B23: 0.01
A24: Fluxa: fee per withdrawal abroad | B24: 2
A25: Fluxa Premium per month (no currency fee) | B25: 9.99
A26: Travel insurance bought separately, per month (about) | B26: 4
A27: Banks: fee on other currencies | B27: 0.025
A28: Banks: fee per withdrawal, low / high | B28: 1 | C28: 2
A29: Banks: account package per month, low / high | B29: 3 | C29: 5
A31: ASSUMPTIONS — not on the case sheet (each one is tested on the Sensitivity sheet)
A32: Extra cost of Plus features (shared accounts, virtual cards) per subscriber per month | B32: 0 | C32: Software features; marginal cost close to zero. 0.25 and 0.50 tested.
A33: Share of withdrawals that Basic customers stop making once a withdrawal costs 1.50 | B33: 0 | C33: The case says nothing about behaviour; each avoided withdrawal costs Novčić 0.50 of margin. 25–75% tested.
A34: Withdrawals of a Plus subscriber relative to the segment average (1 = unchanged) | B34: 1 | C34: Withdrawals are included in Plus up to the cap below; the cap keeps this near 1. 1.5 and 2 tested.
A35: Plus: withdrawals included per month (cap, then the Basic fee applies) | B35: 3 | C35: Covers the typical employee (2) and student (1); protects against heavy cash users (handout 04).
A36: Per-use churn applies only to customers who actually pay the per-use fees (plan buyers do not leave) | B36: 1 | C36: Reading of the sheet: '… of the students/employees/travellers who pay these fees would leave'.
A37: Plan buyers: survey share at the chosen price buys; the rest stay on Basic (then the per-use churn applies) | B37: 1 | C37: Customers who do not buy a plan still do something: stay on Basic, or leave.
A39: DECISIONS — the price list (change these)
A40: Basic: fee per cash withdrawal | B40: 1.5 | C40: Survey level. Cost 1.00 → margin 0.50 per withdrawal. Fluxa charges 2.00 abroad, banks 1–2.
A41: Basic: fee on other currencies above the ECB rate | B41: 0.015 | C41: Survey level. Cost 0.3%. Fluxa 1.0%, banks 2.5%.
A42: Plus price per month — students (needs student verification if different) | B42: 3.99 | C42: Set equal to pE for one Plus price; 2.99 with a student fence adds about 7,700 a year.
A43: Plus price per month — young employees | B43: 3.99 | C43: Only 2.99 / 3.99 / 4.99 have survey shares.
A44: Travel price per month | B44: 6.99 | C44: Only 5.99 / 6.99 / 8.99 have survey shares.
A45: Alternative for comparison: one monthly fee for everyone (everything included) | B45: 3.99 | C45: Bank package range is 3–5.
A47: Leave a Plus or Travel price blank to model 'no such plan'.

Sheet Segment economics
A1: Contribution per customer per month, by segment and offer
A2: Income − variable cost for one typical member of the segment (usage as on the case sheet). A plan price is counted as income; services included in a plan show their cost but no fee income.
A4: Segment | B4: Students | C4: Students | D4: Students | E4: Students | F4: Employees | G4: Employees | H4: Employees | I4: Employees | J4: Travellers | K4: Travellers | L4: Travellers | M4: Travellers
A5: Offer | B5: Today (all free) | C5: Basic | D5: Plus | E5: Travel | F5: Today (all free) | G5: Basic | H5: Plus | I5: Travel | J5: Today (all free) | K5: Basic | L5: Plus | M5: Travel
A6: Card payments (interchange) | B6: =ic*Inputs!$C$6 -> 0.5 | C6: =ic*Inputs!$C$6 -> 0.5 | D6: =ic*Inputs!$C$6 -> 0.5 | E6: =ic*Inputs!$C$6 -> 0.5 | F6: =ic*Inputs!$C$7 -> 1.8 | G6: =ic*Inputs!$C$7 -> 1.8 | H6: =ic*Inputs!$C$7 -> 1.8 | I6: =ic*Inputs!$C$7 -> 1.8 | J6: =ic*Inputs!$C$8 -> 1.6 | K6: =ic*Inputs!$C$8 -> 1.6 | L6: =ic*Inputs!$C$8 -> 1.6 | M6: =ic*Inputs!$C$8 -> 1.6
A7: Plan fee | B7: 0 | C7: 0 | D7: =pS -> 3.99 | E7: =pT -> 6.99 | F7: 0 | G7: 0 | H7: =pE -> 3.99 | I7: =pT -> 6.99 | J7: 0 | K7: 0 | L7: =pE -> 3.99 | M7: =pT -> 6.99
A8: Cash withdrawal fees | B8: 0 | C8: =fee_wd*Inputs!$E$6*(1-wd_red) -> 1.5 | D8: 0 | E8: 0 | F8: 0 | G8: =fee_wd*Inputs!$E$7*(1-wd_red) -> 3 | H8: 0 | I8: 0 | J8: 0 | K8: =fee_wd*Inputs!$E$8*(1-wd_red) -> 3 | L8: 0 | M8: 0
A9: Currency fees | B9: 0 | C9: =fee_fx*Inputs!$D$6 -> 0.375 | D9: =fee_fx*Inputs!$D$6 -> 0.375 | E9: 0 | F9: 0 | G9: =fee_fx*Inputs!$D$7 -> 0.75 | H9: =fee_fx*Inputs!$D$7 -> 0.75 | I9: 0 | J9: 0 | K9: =fee_fx*Inputs!$D$8 -> 6 | L9: =fee_fx*Inputs!$D$8 -> 6 | M9: 0
A10: Account cost | B10: =-cost_acc -> -0.6 | C10: =-cost_acc -> -0.6 | D10: =-cost_acc -> -0.6 | E10: =-cost_acc -> -0.6 | F10: =-cost_acc -> -0.6 | G10: =-cost_acc -> -0.6 | H10: =-cost_acc -> -0.6 | I10: =-cost_acc -> -0.6 | ... M10: =-cost_acc -> -0.6
A11: Cash withdrawal cost | B11: =-cost_wd*Inputs!$E$6 -> -1 | C11: =-cost_wd*Inputs!$E$6*(1-wd_red) -> -1 | D11: =-cost_wd*Inputs!$E$6*plus_wdf -> -1 | E11: =-cost_wd*Inputs!$E$6 -> -1 | F11: =-cost_wd*Inputs!$E$7 -> -2 | G11: =-cost_wd*Inputs!$E$7*(1-wd_red) -> -2 | H11: =-cost_wd*Inputs!$E$7*plus_wdf -> -2 | I11: =-cost_wd*Inputs!$E$7 -> -2 | J11: =-cost_wd*Inputs!$E$8 -> -2 | K11: =-cost_wd*Inputs!$E$8*(1-wd_red) -> -2 | L11: =-cost_wd*Inputs!$E$8*plus_wdf -> -2 | M11: =-cost_wd*Inputs!$E$8 -> -2
A12: Currency cost | B12: =-cost_fx*Inputs!$D$6 -> -0.075 | C12: =-cost_fx*Inputs!$D$6 -> -0.075 | D12: =-cost_fx*Inputs!$D$6 -> -0.075 | E12: =-cost_fx*Inputs!$D$6 -> -0.075 | F12: =-cost_fx*Inputs!$D$7 -> -0.15 | G12: =-cost_fx*Inputs!$D$7 -> -0.15 | H12: =-cost_fx*Inputs!$D$7 -> -0.15 | I12: =-cost_fx*Inputs!$D$7 -> -0.15 | J12: =-cost_fx*Inputs!$D$8 -> -1.2 | K12: =-cost_fx*Inputs!$D$8 -> -1.2 | L12: =-cost_fx*Inputs!$D$8 -> -1.2 | M12: =-cost_fx*Inputs!$D$8 -> -1.2
A13: Insurance cost | B13: 0 | C13: 0 | D13: 0 | E13: =-cost_ins -> -0.5 | F13: 0 | G13: 0 | H13: 0 | I13: =-cost_ins -> -0.5 | J13: 0 | K13: 0 | L13: 0 | M13: =-cost_ins -> -0.5
A14: Plus feature cost | B14: 0 | C14: 0 | D14: =-feat_cost -> 0 | E14: 0 | F14: 0 | G14: 0 | H14: =-feat_cost -> 0 | I14: 0 | J14: 0 | K14: 0 | L14: =-feat_cost -> 0 | M14: 0
A15: Contribution per month | B15: =SUM(B6:B14) -> -1.175 | C15: =SUM(C6:C14) -> 0.7 | D15: =SUM(D6:D14) -> 3.19 | E15: =SUM(E6:E14) -> 5.315 | F15: =SUM(F6:F14) -> -0.95 | G15: =SUM(G6:G14) -> 2.8 | H15: =SUM(H6:H14) -> 3.79 | I15: =SUM(I6:I14) -> 5.54 | ... M15: =SUM(M6:M14) -> 4.29
A16: Contribution per year | B16: =B15*12 -> -14.1 | C16: =C15*12 -> 8.4 | D16: =D15*12 -> 38.28 | E16: =E15*12 -> 63.78 | F16: =F15*12 -> -11.4 | G16: =G15*12 -> 33.6 | H16: =H15*12 -> 45.48 | I16: =I15*12 -> 66.48 | ... M16: =M15*12 -> 51.48
A18: Reading: today every segment loses money; the cash withdrawal (cost 1.00, no fee) is the largest single leak. Basic turns each segment positive through per-use fees; Plus and Travel earn more per subscriber than Basic for employees and travellers, but a plan is worth offering only if its take-up × margin beats what the same customers would pay per use (see Model and Price grid).

Sheet Model
A1: Recommended structure — each segment followed through its choices (2027, per year)
A2: Basic account (no monthly fee, fees per use) for everyone · Plus for students and employees · Travel for travellers. Non-buyers stay on Basic or leave (survey churn).
B4: Students | C4: Employees | D4: Travellers | E4: Total
A5: Customers today | B5: =Inputs!$B$6 -> 24000 | C5: =Inputs!$B$7 -> 12000 | D5: =Inputs!$B$8 -> 4000 | E5: =SUM(B5:D5) -> 40000
A6: Plan offered | B6: Plus | C6: Plus | D6: Travel
A7: Plan price per month | B7: =pS -> 3.99 | C7: =pE -> 3.99 | D7: =pT -> 6.99
A8: Share who buy the plan (survey) | B8: =IF(pS="",0,MIN(1,1*IF(pS=Inputs!$H$6,Inputs!$I$6,IF(pS=Inputs!$J$6,Inputs!$K$6,IF(pS=Inputs!$L$6,Inputs!$M$6,NA()))))) -> 0.08 | C8: =IF(pE="",0,MIN(1,1*IF(pE=Inputs!$H$7,Inputs!$I$7,IF(pE=Inputs!$J$7,Inputs!$K$7,IF(pE=Inputs!$L$7,Inputs!$M$7,NA()))))) -> 0.4 | D8: =IF(pT="",0,MIN(1,1*IF(pT=Inputs!$H$8,Inputs!$I$8,IF(pT=Inputs!$J$8,Inputs!$K$8,IF(pT=Inputs!$L$8,Inputs!$M$8,NA()))))) -> 0.7
A9: Plan subscribers | B9: =B5*B8 -> 1920 | C9: =C5*C8 -> 4800 | D9: =D5*D8 -> 2800 | E9: =SUM(B9:D9) -> 9520
A10: Do not buy the plan | B10: =B5-B9 -> 22080 | C10: =C5-C9 -> 7200 | D10: =D5-D9 -> 1200 | E10: =SUM(B10:D10) -> 30480
A11: … of whom leave (per-use churn) | B11: =B10*Inputs!$G$6*churn_nonbuyers -> 1104 | C11: =C10*Inputs!$G$7*churn_nonbuyers -> 216 | D11: =D10*Inputs!$G$8*churn_nonbuyers -> 840 | E11: =SUM(B11:D11) -> 2160
A12: … of whom stay on Basic | B12: =B10-B11 -> 20976 | C12: =C10-C11 -> 6984 | D12: =D10-D11 -> 360 | E12: =SUM(B12:D12) -> 28320
A13: Customers retained | B13: =B9+B12 -> 22896 | C13: =C9+C12 -> 11784 | D13: =D9+D12 -> 3160 | E13: =SUM(B13:D13) -> 37840
A14: Contribution per plan subscriber per month | B14: ='Segment economics'!D15 -> 3.19 | C14: ='Segment economics'!H15 -> 3.79 | D14: ='Segment economics'!M15 -> 4.29
A15: Contribution per Basic customer per month | B15: ='Segment economics'!C15 -> 0.7 | C15: ='Segment economics'!G15 -> 2.8 | D15: ='Segment economics'!K15 -> 6.8
A16: Contribution from the plan per year | B16: =12*B9*B14 -> 73497.6 | C16: =12*C9*C14 -> 218304 | D16: =12*D9*D14 -> 144144 | E16: =SUM(B16:D16) -> 435945.6
A17: Contribution from Basic per year | B17: =12*B12*B15 -> 176198.4 | C17: =12*C12*C15 -> 234662.4 | D17: =12*D12*D15 -> 29376 | E17: =SUM(B17:D17) -> 440236.8
A18: Contribution per year | B18: =B16+B17 -> 249696 | C18: =C16+C17 -> 452966.4 | D18: =D16+D17 -> 173520 | E18: =SUM(B18:D18) -> 876182.4
A20: Total contribution per year | E20: =E18 -> 876182.4
A21: Fixed costs per year | E21: =-fixed -> -700000
A22: Profit per year | E22: =E20+E21 -> 176182.4
A23: Customers retained (share of 40,000) | E23: =E13/Inputs!$B$10 -> 0.946
A24: Customers lost | E24: =E11 -> 2160
A25: Blended contribution per retained customer per month | E25: =E20/E13/12 -> 1.9295772
A26: Break-even: customers needed at this blend | E26: =fixed/E25/12 -> 30231.148
A27: Safety margin: contribution may fall by … before a loss | E27: =1-fixed/E20 -> 0.20107959
A29: Where the money comes from and goes (per year, recommended structure)
A30: Income
A31: Interchange (0.2% of card payments) | B31: =12*(B9+B12)*ic*Inputs!$C$6 -> 137376 | C31: =12*(C9+C12)*ic*Inputs!$C$7 -> 254534.4 | D31: =12*(D9+D12)*ic*Inputs!$C$8 -> 60672 | E31: =SUM(B31:D31) -> 452582.4
A32: Plan fees (Plus + Travel) | B32: =12*B9*pS -> 91929.6 | C32: =12*C9*pE -> 229824 | D32: =12*D9*pT -> 234864 | E32: =SUM(B32:D32) -> 556617.6
A33: Cash withdrawal fees (Basic) | B33: =12*B12*fee_wd*Inputs!$E$6*(1-wd_red) -> 377568 | C33: =12*C12*fee_wd*Inputs!$E$7*(1-wd_red) -> 251424 | D33: =12*D12*fee_wd*Inputs!$E$8*(1-wd_red) -> 12960 | E33: =SUM(B33:D33) -> 641952
A34: Currency fees (Basic + Plus) | B34: =12*(B12+B9)*fee_fx*Inputs!$D$6 -> 103032 | C34: =12*(C12+C9)*fee_fx*Inputs!$D$7 -> 106056 | D34: =12*(D12)*fee_fx*Inputs!$D$8 -> 25920 | E34: =SUM(B34:D34) -> 235008
A35: Total income | B35: =SUM(B31:B34) -> 709905.6 | C35: =SUM(C31:C34) -> 841838.4 | D35: =SUM(D31:D34) -> 334416 | E35: =SUM(E31:E34) -> 1886160
A37: Variable costs
A38: Account cost | B38: =-12*(B9+B12)*cost_acc -> -164851.2 | C38: =-12*(C9+C12)*cost_acc -> -84844.8 | D38: =-12*(D9+D12)*cost_acc -> -22752 | E38: =SUM(B38:D38) -> -272448
A39: Cash withdrawal cost | B39: =-12*cost_wd*Inputs!$E$6*(B12*(1-wd_red)+B9*plus_wdf) -> -274752 | C39: =-12*cost_wd*Inputs!$E$7*(C12*(1-wd_red)+C9*plus_wdf) -> -282816 | D39: =-12*cost_wd*Inputs!$E$8*(D12*(1-wd_red)+D9) -> -75840 | E39: =SUM(B39:D39) -> -633408
A40: Currency cost | B40: =-12*(B9+B12)*cost_fx*Inputs!$D$6 -> -20606.4 | C40: =-12*(C9+C12)*cost_fx*Inputs!$D$7 -> -21211.2 | D40: =-12*(D9+D12)*cost_fx*Inputs!$D$8 -> -45504 | E40: =SUM(B40:D40) -> -87321.6
A41: Insurance (Travel) | B41: 0 | C41: 0 | D41: =-12*D9*cost_ins -> -16800 | E41: =SUM(B41:D41) -> -16800
A42: Plus feature cost | B42: =-12*B9*feat_cost -> 0 | C42: =-12*C9*feat_cost -> 0 | D42: 0 | E42: =SUM(B42:D42) -> 0
A43: Total variable costs | B43: =SUM(B38:B42) -> -460209.6 | C43: =SUM(C38:C42) -> -388872 | D43: =SUM(D38:D42) -> -160896 | E43: =SUM(E38:E42) -> -1009977.6
A44: Contribution (check = row above) | B44: =B35+B43 -> 249696 | C44: =C35+C43 -> 452966.4 | D44: =D35+D43 -> 173520 | E44: =E35+E43 -> 876182.4
A45: Difference to the segment table (should be 0) | B45: =B44-B18 -> 0 | C45: =C44-C18 -> 0 | D45: =D44-D18 -> 0 | E45: =E44-E18 -> 0

Sheet Bridge
A1: From today's loss to the 2027 contribution — line by line (per year)
A2: Each line is the change the price list causes. The sum reproduces the Model total; the last line checks it.
A4: Step | B4: Change | C4: Running total | D4: Where it comes from
A5: Today: everything free (contribution) | B5: =Alternatives!E5 -> -580800 | C5: =SUM(B$5:B5) -> -580800 | D5: Alternatives, row A. Interchange 480,000 − variable costs 1,060,800.
A6: + Cash withdrawal fees (Basic) | B6: =Model!E33 -> 641952 | C6: =SUM(B$5:B6) -> 61152 | D6: 1.50 × withdrawals of customers on Basic.
A7: + Currency fees (Basic and Plus) | B7: =Model!E34 -> 235008 | C7: =SUM(B$5:B7) -> 296160 | D7: 1.5% above ECB × payments in other currencies.
A8: + Plan fees (Plus and Travel) | B8: =Model!E32 -> 556617.6 | C8: =SUM(B$5:B8) -> 852777.6 | D8: 9,520 subscribers at 3.99 / 6.99.
A9: − Travel insurance for subscribers | B9: =Model!E41 -> -16800 | C9: =SUM(B$5:B9) -> 835977.6 | D9: 0.50 × Travel subscribers.
A10: + Customers who leave no longer cause a loss | B10: =-12*(Model!B11*'Segment economics'!B15+Model!C11*'Segment economics'!F15+Model!D11*'Segment economics'!J15) -> 40204.8 | C10: =SUM(B$5:B10) -> 876182.4 | D10: Each leaver had a negative contribution today (−1.18 / −0.95 / −2.20 a month).
A11: ± Behaviour assumptions (0 at default inputs: withdrawals avoided, Plus use, feature cost) | B11: =reco_total-SUM(B5:B10) -> 0 | C11: =SUM(B$5:B11) -> 876182.4
A12: → Contribution 2027, recommended price list | B12: =reco_total -> 876182.4
A13: − Fixed costs | B13: =-fixed -> -700000
A14: → Profit 2027 | B14: =B12+B13 -> 176182.4
A15: Profit today (contribution − fixed costs) | B15: =B5-fixed -> -1280800
A16: Swing in profit | B16: =B14-B15 -> 1456982.4
A18: Reading: the withdrawal fee alone closes the gap to zero contribution; currency and plan fees then build the 876,000. Half of the swing comes from charging for a service that costs 1.00 each time and was given away 56,000 times a month.

Sheet Alternatives
A1: The same 40,000 customers under five price structures (per year)
A2: Survey responses are applied as on the case sheet. The flat fee uses the churn for 'a monthly fee on the account itself'; that share was not asked per fee level, so the flat-fee result is only credible in the bank-package range (3–5) — see note.
A4: Structure | B4: Students | C4: Employees | D4: Travellers | E4: Contribution | F4: Profit after fixed | G4: Customers retained
A5: A · Today: everything free | B5: =12*Inputs!$B$6*(ic*Inputs!$C$6-cost_acc-cost_wd*Inputs!$E$6-cost_fx*Inputs!$D$6) -> -338400 | C5: =12*Inputs!$B$7*(ic*Inputs!$C$7-cost_acc-cost_wd*Inputs!$E$7-cost_fx*Inputs!$D$7) -> -136800 | D5: =12*Inputs!$B$8*(ic*Inputs!$C$8-cost_acc-cost_wd*Inputs!$E$8-cost_fx*Inputs!$D$8) -> -105600 | E5: =SUM(B5:D5) -> -580800 | F5: =E5-fixed -> -1280800 | G5: =Inputs!$B$10 -> 40000
A6: B · Fees per use only (1.50 per withdrawal, 1.5% above ECB), no plans | B6: =12*Inputs!$B$6*(1-Inputs!$G$6)*(ic*Inputs!$C$6+fee_wd*Inputs!$E$6*(1-wd_red)+fee_fx*Inputs!$D$6-cost_acc-cost_wd*Inputs!$E$6*(1-wd_red)-cost_fx*Inputs!$D$6) -> 191520 | C6: =12*Inputs!$B$7*(1-Inputs!$G$7)*(ic*Inputs!$C$7+fee_wd*Inputs!$E$7*(1-wd_red)+fee_fx*Inputs!$D$7-cost_acc-cost_wd*Inputs!$E$7*(1-wd_red)-cost_fx*Inputs!$D$7) -> 391104 | D6: =12*Inputs!$B$8*(1-Inputs!$G$8)*(ic*Inputs!$C$8+fee_wd*Inputs!$E$8*(1-wd_red)+fee_fx*Inputs!$D$8-cost_acc-cost_wd*Inputs!$E$8*(1-wd_red)-cost_fx*Inputs!$D$8) -> 97920 | E6: =SUM(B6:D6) -> 680544 | F6: =E6-fixed -> -19456 | G6: =Inputs!$B$6*(1-Inputs!$G$6)+Inputs!$B$7*(1-Inputs!$G$7)+Inputs!$B$8*(1-Inputs!$G$8) -> 35640
A7: C · One monthly fee for everyone, everything included (fee on Inputs) | B7: =12*Inputs!$B$6*(1-Inputs!$F$6)*(ic*Inputs!$C$6+flat_fee-cost_acc-cost_wd*Inputs!$E$6-cost_fx*Inputs!$D$6) -> 364824 | C7: =12*Inputs!$B$7*(1-Inputs!$F$7)*(ic*Inputs!$C$7+flat_fee-cost_acc-cost_wd*Inputs!$E$7-cost_fx*Inputs!$D$7) -> 328320 | D7: =12*Inputs!$B$8*(1-Inputs!$F$8)*(ic*Inputs!$C$8+flat_fee-cost_acc-cost_wd*Inputs!$E$8-cost_fx*Inputs!$D$8) -> 77328 | E7: =SUM(B7:D7) -> 770472 | F7: =E7-fixed -> 70472 | G7: =Inputs!$B$6*(1-Inputs!$F$6)+Inputs!$B$7*(1-Inputs!$F$7)+Inputs!$B$8*(1-Inputs!$F$8) -> 23400
A8: D · Basic + Travel only (no Plus plan) | B8: =12*Inputs!$B$6*(1-Inputs!$G$6)*(ic*Inputs!$C$6+fee_wd*Inputs!$E$6*(1-wd_red)+fee_fx*Inputs!$D$6-cost_acc-cost_wd*Inputs!$E$6*(1-wd_red)-cost_fx*Inputs!$D$6) -> 191520 | C8: =12*Inputs!$B$7*(1-Inputs!$G$7)*(ic*Inputs!$C$7+fee_wd*Inputs!$E$7*(1-wd_red)+fee_fx*Inputs!$D$7-cost_acc-cost_wd*Inputs!$E$7*(1-wd_red)-cost_fx*Inputs!$D$7) -> 391104 | D8: =Model!D18 -> 173520 | E8: =SUM(B8:D8) -> 756144 | F8: =E8-fixed -> 56144 | G8: =Inputs!$B$6*(1-Inputs!$G$6)+Inputs!$B$7*(1-Inputs!$G$7)+Model!D13 -> 37600
A9: E · Recommended: Basic + Plus + Travel (prices on Inputs) | B9: =Model!B18 -> 249696 | C9: =Model!C18 -> 452966.4 | D9: =Model!D18 -> 173520 | E9: =SUM(B9:D9) -> 876182.4 | F9: =E9-fixed -> 176182.4 | G9: =Model!E13 -> 37840
A11: Gain of the recommendation (handout 04, formula 1: contribution ÷ contribution of the alternative − 1)
A12: vs B · fees per use only | E12: =E9-E6 -> 195638.4 | F12: =E9/E6-1 -> 0.28747355
A13: vs C · one monthly fee | E13: =E9-E7 -> 105710.4 | F13: =E9/E7-1 -> 0.13720213
A14: vs D · Basic + Travel only | E14: =E9-E8 -> 120038.4 | F14: =E9/E8-1 -> 0.15875071
A16: One monthly fee at each level (same churn at every level — the survey gave no level):
A17: Flat fee 2.99 | B17: 2.99 | E17: =12*Inputs!$B$6*(1-Inputs!$F$6)*(ic*Inputs!$C$6+B17-cost_acc-cost_wd*Inputs!$E$6-cost_fx*Inputs!$D$6)+12*Inputs!$B$7*(1-Inputs!$F$7)*(ic*Inputs!$C$7+B17-cost_acc-cost_wd*Inputs!$E$7-cost_fx*Inputs!$D$7)+12*Inputs!$B$8*(1-Inputs!$F$8)*(ic*Inputs!$C$8+B17-cost_acc-cost_wd*Inputs!$E$8-cost_fx*Inputs!$D$8) -> 489672 | F17: =E17-fixed -> -210328
A18: Flat fee 3.99 | B18: 3.99 | E18: =12*Inputs!$B$6*(1-Inputs!$F$6)*(ic*Inputs!$C$6+B18-cost_acc-cost_wd*Inputs!$E$6-cost_fx*Inputs!$D$6)+12*Inputs!$B$7*(1-Inputs!$F$7)*(ic*Inputs!$C$7+B18-cost_acc-cost_wd*Inputs!$E$7-cost_fx*Inputs!$D$7)+12*Inputs!$B$8*(1-Inputs!$F$8)*(ic*Inputs!$C$8+B18-cost_acc-cost_wd*Inputs!$E$8-cost_fx*Inputs!$D$8) -> 770472 | F18: =E18-fixed -> 70472
A19: Flat fee 4.99 | B19: 4.99 | E19: =12*Inputs!$B$6*(1-Inputs!$F$6)*(ic*Inputs!$C$6+B19-cost_acc-cost_wd*Inputs!$E$6-cost_fx*Inputs!$D$6)+12*Inputs!$B$7*(1-Inputs!$F$7)*(ic*Inputs!$C$7+B19-cost_acc-cost_wd*Inputs!$E$7-cost_fx*Inputs!$D$7)+12*Inputs!$B$8*(1-Inputs!$F$8)*(ic*Inputs!$C$8+B19-cost_acc-cost_wd*Inputs!$E$8-cost_fx*Inputs!$D$8) -> 1051272 | F19: =E19-fixed -> 351272
A21: Note: at 4.99 the flat fee looks best only because the survey churn (55 / 25 / 10%) is held constant. The plan ladder says only 4% of students and 20% of employees would pay 4.99 even for a plan with extra features, so retaining 45% of students at a 4.99 mandatory fee is not credible. The honest comparison is at 2.99–3.99; even there the flat fee loses 41% of the customers (16,600) against 5% in the recommendation.

Sheet Price grid
A1: Contribution of each segment at each surveyed price point (per year)
A2: Segments are independent in the model, so the best price can be chosen segment by segment. 'No plan' = everyone on Basic.
A4: Segment / price | B4: Price | C4: Take-up | D4: Subscribers | E4: Stay on Basic | F4: Leave | G4: Plan contribution | H4: Basic contribution | I4: Total | J4: Best?
A5: Students
A6: No plan | C6: 0 | D6: 0 | E6: =Inputs!$B$6*(1-Inputs!$G$6) -> 22800 | F6: =Inputs!$B$6*Inputs!$G$6 -> 1200 | G6: 0 | H6: =12*E6*(ic*Inputs!$C$6+fee_wd*Inputs!$E$6*(1-wd_red)+fee_fx*Inputs!$D$6-cost_acc-cost_wd*Inputs!$E$6*(1-wd_red)-cost_fx*Inputs!$D$6) -> 191520 | I6: =G6+H6 -> 191520 | J6: =IF(I6=MAX(I$6:I$9),"← best","")
A7: Plus at price 1 | B7: =Inputs!$H$6 -> 2.99 | C7: =Inputs!$I$6 -> 0.15 | D7: =Inputs!$B$6*C7 -> 3600 | E7: =(Inputs!$B$6-D7)*(1-Inputs!$G$6*churn_nonbuyers) -> 19380 | F7: =Inputs!$B$6-D7-E7 -> 1020 | G7: =12*D7*(ic*Inputs!$C$6+B7+fee_fx*Inputs!$D$6-cost_acc-cost_wd*Inputs!$E$6*plus_wdf-cost_fx*Inputs!$D$6-feat_cost) -> 94608 | H7: =12*E7*(ic*Inputs!$C$6+fee_wd*Inputs!$E$6*(1-wd_red)+fee_fx*Inputs!$D$6-cost_acc-cost_wd*Inputs!$E$6*(1-wd_red)-cost_fx*Inputs!$D$6) -> 162792 | I7: =G7+H7 -> 257400 | J7: =IF(I7=MAX(I$6:I$9),"← best","") -> ← best
A8: Plus at price 2 | B8: =Inputs!$J$6 -> 3.99 | C8: =Inputs!$K$6 -> 0.08 | D8: =Inputs!$B$6*C8 -> 1920 | E8: =(Inputs!$B$6-D8)*(1-Inputs!$G$6*churn_nonbuyers) -> 20976 | F8: =Inputs!$B$6-D8-E8 -> 1104 | G8: =12*D8*(ic*Inputs!$C$6+B8+fee_fx*Inputs!$D$6-cost_acc-cost_wd*Inputs!$E$6*plus_wdf-cost_fx*Inputs!$D$6-feat_cost) -> 73497.6 | H8: =12*E8*(ic*Inputs!$C$6+fee_wd*Inputs!$E$6*(1-wd_red)+fee_fx*Inputs!$D$6-cost_acc-cost_wd*Inputs!$E$6*(1-wd_red)-cost_fx*Inputs!$D$6) -> 176198.4 | I8: =G8+H8 -> 249696 | J8: =IF(I8=MAX(I$6:I$9),"← best","")
A9: Plus at price 3 | B9: =Inputs!$L$6 -> 4.99 | C9: =Inputs!$M$6 -> 0.04 | D9: =Inputs!$B$6*C9 -> 960 | E9: =(Inputs!$B$6-D9)*(1-Inputs!$G$6*churn_nonbuyers) -> 21888 | F9: =Inputs!$B$6-D9-E9 -> 1152 | G9: =12*D9*(ic*Inputs!$C$6+B9+fee_fx*Inputs!$D$6-cost_acc-cost_wd*Inputs!$E$6*plus_wdf-cost_fx*Inputs!$D$6-feat_cost) -> 48268.8 | H9: =12*E9*(ic*Inputs!$C$6+fee_wd*Inputs!$E$6*(1-wd_red)+fee_fx*Inputs!$D$6-cost_acc-cost_wd*Inputs!$E$6*(1-wd_red)-cost_fx*Inputs!$D$6) -> 183859.2 | I9: =G9+H9 -> 232128 | J9: =IF(I9=MAX(I$6:I$9),"← best","")
A11: Employees
A12: No plan | C12: 0 | D12: 0 | E12: =Inputs!$B$7*(1-Inputs!$G$7) -> 11640 | F12: =Inputs!$B$7*Inputs!$G$7 -> 360 | G12: 0 | H12: =12*E12*(ic*Inputs!$C$7+fee_wd*Inputs!$E$7*(1-wd_red)+fee_fx*Inputs!$D$7-cost_acc-cost_wd*Inputs!$E$7*(1-wd_red)-cost_fx*Inputs!$D$7) -> 391104 | I12: =G12+H12 -> 391104 | J12: =IF(I12=MAX(I$12:I$15),"← best","")
A13: Plus at price 1 | B13: =Inputs!$H$7 -> 2.99 | C13: =Inputs!$I$7 -> 0.5 | D13: =Inputs!$B$7*C13 -> 6000 | E13: =(Inputs!$B$7-D13)*(1-Inputs!$G$7*churn_nonbuyers) -> 5820 | F13: =Inputs!$B$7-D13-E13 -> 180 | G13: =12*D13*(ic*Inputs!$C$7+B13+fee_fx*Inputs!$D$7-cost_acc-cost_wd*Inputs!$E$7*plus_wdf-cost_fx*Inputs!$D$7-feat_cost) -> 200880 | H13: =12*E13*(ic*Inputs!$C$7+fee_wd*Inputs!$E$7*(1-wd_red)+fee_fx*Inputs!$D$7-cost_acc-cost_wd*Inputs!$E$7*(1-wd_red)-cost_fx*Inputs!$D$7) -> 195552 | I13: =G13+H13 -> 396432 | J13: =IF(I13=MAX(I$12:I$15),"← best","")
A14: Plus at price 2 | B14: =Inputs!$J$7 -> 3.99 | C14: =Inputs!$K$7 -> 0.4 | D14: =Inputs!$B$7*C14 -> 4800 | E14: =(Inputs!$B$7-D14)*(1-Inputs!$G$7*churn_nonbuyers) -> 6984 | F14: =Inputs!$B$7-D14-E14 -> 216 | G14: =12*D14*(ic*Inputs!$C$7+B14+fee_fx*Inputs!$D$7-cost_acc-cost_wd*Inputs!$E$7*plus_wdf-cost_fx*Inputs!$D$7-feat_cost) -> 218304 | H14: =12*E14*(ic*Inputs!$C$7+fee_wd*Inputs!$E$7*(1-wd_red)+fee_fx*Inputs!$D$7-cost_acc-cost_wd*Inputs!$E$7*(1-wd_red)-cost_fx*Inputs!$D$7) -> 234662.4 | I14: =G14+H14 -> 452966.4 | J14: =IF(I14=MAX(I$12:I$15),"← best","") -> ← best
A15: Plus at price 3 | B15: =Inputs!$L$7 -> 4.99 | C15: =Inputs!$M$7 -> 0.2 | D15: =Inputs!$B$7*C15 -> 2400 | E15: =(Inputs!$B$7-D15)*(1-Inputs!$G$7*churn_nonbuyers) -> 9312 | F15: =Inputs!$B$7-D15-E15 -> 288 | G15: =12*D15*(ic*Inputs!$C$7+B15+fee_fx*Inputs!$D$7-cost_acc-cost_wd*Inputs!$E$7*plus_wdf-cost_fx*Inputs!$D$7-feat_cost) -> 137952 | H15: =12*E15*(ic*Inputs!$C$7+fee_wd*Inputs!$E$7*(1-wd_red)+fee_fx*Inputs!$D$7-cost_acc-cost_wd*Inputs!$E$7*(1-wd_red)-cost_fx*Inputs!$D$7) -> 312883.2 | I15: =G15+H15 -> 450835.2 | J15: =IF(I15=MAX(I$12:I$15),"← best","")
A17: Travellers
A18: No plan | C18: 0 | D18: 0 | E18: =Inputs!$B$8*(1-Inputs!$G$8) -> 1200 | F18: =Inputs!$B$8*Inputs!$G$8 -> 2800 | G18: 0 | H18: =12*E18*(ic*Inputs!$C$8+fee_wd*Inputs!$E$8*(1-wd_red)+fee_fx*Inputs!$D$8-cost_acc-cost_wd*Inputs!$E$8*(1-wd_red)-cost_fx*Inputs!$D$8) -> 97920 | I18: =G18+H18 -> 97920 | J18: =IF(I18=MAX(I$18:I$21),"← best","")
A19: Travel at price 1 | B19: =Inputs!$H$8 -> 5.99 | C19: =Inputs!$I$8 -> 0.8 | D19: =Inputs!$B$8*C19 -> 3200 | E19: =(Inputs!$B$8-D19)*(1-Inputs!$G$8*churn_nonbuyers) -> 240 | F19: =Inputs!$B$8-D19-E19 -> 560 | G19: =12*D19*(ic*Inputs!$C$8+B19-cost_acc-cost_wd*Inputs!$E$8-cost_fx*Inputs!$D$8-cost_ins) -> 126336 | H19: =12*E19*(ic*Inputs!$C$8+fee_wd*Inputs!$E$8*(1-wd_red)+fee_fx*Inputs!$D$8-cost_acc-cost_wd*Inputs!$E$8*(1-wd_red)-cost_fx*Inputs!$D$8) -> 19584 | I19: =G19+H19 -> 145920 | J19: =IF(I19=MAX(I$18:I$21),"← best","")
A20: Travel at price 2 | B20: =Inputs!$J$8 -> 6.99 | C20: =Inputs!$K$8 -> 0.7 | D20: =Inputs!$B$8*C20 -> 2800 | E20: =(Inputs!$B$8-D20)*(1-Inputs!$G$8*churn_nonbuyers) -> 360 | F20: =Inputs!$B$8-D20-E20 -> 840 | G20: =12*D20*(ic*Inputs!$C$8+B20-cost_acc-cost_wd*Inputs!$E$8-cost_fx*Inputs!$D$8-cost_ins) -> 144144 | H20: =12*E20*(ic*Inputs!$C$8+fee_wd*Inputs!$E$8*(1-wd_red)+fee_fx*Inputs!$D$8-cost_acc-cost_wd*Inputs!$E$8*(1-wd_red)-cost_fx*Inputs!$D$8) -> 29376 | I20: =G20+H20 -> 173520 | J20: =IF(I20=MAX(I$18:I$21),"← best","") -> ← best
A21: Travel at price 3 | B21: =Inputs!$L$8 -> 8.99 | C21: =Inputs!$M$8 -> 0.3 | D21: =Inputs!$B$8*C21 -> 1200 | E21: =(Inputs!$B$8-D21)*(1-Inputs!$G$8*churn_nonbuyers) -> 840 | F21: =Inputs!$B$8-D21-E21 -> 1960 | G21: =12*D21*(ic*Inputs!$C$8+B21-cost_acc-cost_wd*Inputs!$E$8-cost_fx*Inputs!$D$8-cost_ins) -> 90576 | H21: =12*E21*(ic*Inputs!$C$8+fee_wd*Inputs!$E$8*(1-wd_red)+fee_fx*Inputs!$D$8-cost_acc-cost_wd*Inputs!$E$8*(1-wd_red)-cost_fx*Inputs!$D$8) -> 68544 | I21: =G21+H21 -> 159120 | J21: =IF(I21=MAX(I$18:I$21),"← best","")
A23: Reading: for employees 3.99 beats 4.99 by less than 0.5%, but keeps twice the subscribers (4,800 vs 2,400) — the lower price is the robust choice. For students the plan adds little either way (2.99 is best by 7,700); for travellers 6.99 is clearly best, and 8.99 would win only if more than 37% took it (see Break-even).

Sheet Break-even
A1: Break-even — classic (handout 07, formula 3), breakeven sales change (formula 1), reactive breakeven (handout 08)
A3: Classic break-even against the fixed costs of 700,000
A4: Total contribution per year (recommended) | B4: =reco_total -> 876182.4
A5: Fixed costs | B5: =fixed -> 700000
A6: Profit | B6: =reco_profit -> 176182.4
A7: Customers retained | B7: =Model!E13 -> 37840
A8: Blended contribution per customer per month | B8: =B4/B7/12 -> 1.9295772
A9: Break-even customers at this blend | B9: =fixed/B8/12 -> 30231.148
A10: Contribution may fall by … before a loss | B10: =1-fixed/B4 -> 0.20107959
A11: Break-even in Plus subscribers if everything else stays (extra subscribers needed to close a gap of …) | B11: =MAX(0,-reco_profit) -> 0
A12: … = this many extra employee subscribers at the Plus margin | B12: =B11/12/'Segment economics'!H15 -> 0
A14: Breakeven sales change of a price move: −ΔP / (CM + ΔP) (positive = subscribers that must be won; negative = subscribers that may be lost)
A15: Move | B15: ΔP | C15: CM before | D15: Breakeven sales change | E15: Survey says
A16: Plus for employees: 3.99 → 2.99 | B16: -1 | C16: ='Segment economics'!H15 -> 3.79 | D16: =-B16/(C16+B16) -> 0.35842294 | E16: =Inputs!$I$7/Inputs!$K$7-1 -> 0.25
A17: Plus for employees: 3.99 → 4.99 | B17: 1 | C17: ='Segment economics'!H15 -> 3.79 | D17: =-B17/(C17+B17) -> -0.20876827 | E17: =Inputs!$M$7/Inputs!$K$7-1 -> -0.5
A18: Travel: 6.99 → 5.99 | B18: -1 | C18: ='Segment economics'!M15 -> 4.29 | D18: =-B18/(C18+B18) -> 0.30395137 | E18: =Inputs!$I$8/Inputs!$K$8-1 -> 0.14285714
A19: Travel: 6.99 → 8.99 | B19: 2 | C19: ='Segment economics'!M15 -> 4.29 | D19: =-B19/(C19+B19) -> -0.31796502 | E19: =Inputs!$M$8/Inputs!$K$8-1 -> -0.57142857
A20: Reading: a cut pays only if the survey gain exceeds the breakeven gain; an increase pays only if the survey loss is smaller than the allowed loss. All four moves fail, so 3.99 and 6.99 hold. (The formula ignores that non-buyers fall back to Basic; the full model on Price grid confirms the same ranking.)
A22: Travel at 8.99: the take-up at which 8.99 would beat 6.99 (full model, non-buyers fall back to Basic)
A23: Travellers' contribution per year at 6.99 | B23: =Model!D18 -> 173520
A24: Per traveller per month at 6.99 | B24: =B23/12/Inputs!$B$8 -> 3.615
A25: Contribution per subscriber at 8.99 | B25: =ic*Inputs!$C$8+Inputs!$L$8-cost_acc-cost_wd*Inputs!$E$8-cost_fx*Inputs!$D$8-cost_ins -> 6.29
A26: Contribution per non-buyer (stays on Basic × share who stay) | B26: =(1-Inputs!$G$8)*(ic*Inputs!$C$8+fee_wd*Inputs!$E$8*(1-wd_red)+fee_fx*Inputs!$D$8-cost_acc-cost_wd*Inputs!$E$8*(1-wd_red)-cost_fx*Inputs!$D$8) -> 2.04
A27: Take-up at 8.99 needed to match 6.99 | B27: =(B24-B26)/(B25-B26) -> 0.37058824
A28: Survey take-up at 8.99 | B28: =Inputs!$M$8 -> 0.3
A30: Reactive breakeven (handout 08): if Fluxa undercuts the Travel plan, when does matching pay?
A31: Our price cut to match (ΔP) | B31: 1
A32: Contribution per Travel subscriber (CM) | B32: ='Segment economics'!M15 -> 4.29
A33: Reactive breakeven = ΔP / CM: share of subscribers that must be at risk before matching pays | B33: =B31/B32 -> 0.23310023
A34: Cost of matching per year (all subscribers pay less) | B34: =12*B31*Model!D9 -> 33600
A35: Contribution lost if 10% of Travel subscribers left | B35: =0.1*Model!D9*12*B32 -> 14414.4
A37: Fallback-adjusted breakeven: a lost SUBSCRIBER is not a lost CUSTOMER — most fall back to Basic and keep paying per use
A38: The margin at stake when a subscriber is won or lost is the plan margin minus what the same customer would contribute on Basic (Basic margin × share who stay). This incremental margin goes into the formula −ΔP / (CM + ΔP).
A39: Move | B39: ΔP | C39: Plan CM | D39: Basic CM × share who stay | E39: Incremental CM | F39: Breakeven sales change | G39: Survey says | H39: Verdict
A40: Plus for employees: 3.99 → 2.99 | B40: -1 | C40: ='Segment economics'!H15 -> 3.79 | D40: ='Segment economics'!G15*(1-Inputs!$G$7*churn_nonbuyers) -> 2.716 | E40: =C40-D40 -> 1.074 | F40: =-B40/(E40+B40) -> 13.513514 | G40: =Inputs!$I$7/Inputs!$K$7-1 -> 0.25 | H40: =IF(G40>F40,"pays: move the price","fails: keep the price") -> fails: keep the price
A41: Plus for employees: 3.99 → 4.99 | B41: 1 | C41: ='Segment economics'!H15 -> 3.79 | D41: ='Segment economics'!G15*(1-Inputs!$G$7*churn_nonbuyers) -> 2.716 | E41: =C41-D41 -> 1.074 | F41: =-B41/(E41+B41) -> -0.48216008 | G41: =Inputs!$M$7/Inputs!$K$7-1 -> -0.5 | H41: =IF(G41>F41,"pays: move the price","fails: keep the price") -> fails: keep the price
A42: Travel: 6.99 → 5.99 | B42: -1 | C42: ='Segment economics'!M15 -> 4.29 | D42: ='Segment economics'!K15*(1-Inputs!$G$8*churn_nonbuyers) -> 2.04 | E42: =C42-D42 -> 2.25 | F42: =-B42/(E42+B42) -> 0.8 | G42: =Inputs!$I$8/Inputs!$K$8-1 -> 0.14285714 | H42: =IF(G42>F42,"pays: move the price","fails: keep the price") -> fails: keep the price
A43: Travel: 6.99 → 8.99 | B43: 2 | C43: ='Segment economics'!M15 -> 4.29 | D43: ='Segment economics'!K15*(1-Inputs!$G$8*churn_nonbuyers) -> 2.04 | E43: =C43-D43 -> 2.25 | F43: =-B43/(E43+B43) -> -0.47058824 | G43: =Inputs!$M$8/Inputs!$K$8-1 -> -0.57142857 | H43: =IF(G43>F43,"pays: move the price","fails: keep the price") -> fails: keep the price
A44: Reading: with the fall-back counted, a cut is hopeless (Plus at 2.99 would need +1,351% subscribers; Travel at 5.99 +80%, the survey offers +25% and +14%), and an increase may lose 48% (Plus) or 47% (Travel) of subscribers — the survey loses 50% and 57%. Plus at 4.99 fails by two points only: it is the closest call in the price list, which is why the lower price with twice the subscribers is preferred. The adjusted formula reproduces the full model (Price grid) exactly.
A46: The first price to test: Travel just under the reference value of 8.00
A47: Test price (not surveyed) | B47: 7.99
A48: Contribution per subscriber at the test price | B48: =ic*Inputs!$C$8+B47-cost_acc-cost_wd*Inputs!$E$8-cost_fx*Inputs!$D$8-cost_ins -> 5.29
A49: Per traveller per month at 6.99 (row 24) | B49: =B24 -> 3.615
A50: Contribution per non-buyer (row 26) | B50: =B26 -> 2.04
A51: Take-up needed at the test price to match 6.99 | B51: =(B49-B50)/(B48-B50) -> 0.48461538
A52: Take-up if demand were linear between the surveyed 6.99 and 8.99 | B52: =Inputs!$K$8+(B47-Inputs!$J$8)/(Inputs!$L$8-Inputs!$J$8)*(Inputs!$M$8-Inputs!$K$8) -> 0.5
A53: Reading: 7.99 pays if at least 48.5% of travellers take it; a straight line between the survey points gives 50%. Too close to decide on paper — hence a controlled price test on new Travel subscribers in 2027 (handout 07: price experiments, incremental implementation), not a change to the launch price.
A55: The same test for students (Plus has ONE price for students and employees)
A56: Plus for students: 3.99 → 2.99 | B56: -1 | C56: ='Segment economics'!D15 -> 3.19 | D56: ='Segment economics'!C15*(1-Inputs!$G$6*churn_nonbuyers) -> 0.665 | E56: =C56-D56 -> 2.525 | F56: =-B56/(E56+B56) -> 0.6557377 | G56: =Inputs!$I$6/Inputs!$K$6-1 -> 0.875 | H56: =IF(G56>F56,"pays for this segment","fails") -> pays for this segment
A57: Plus for students: 3.99 → 4.99 | B57: 1 | C57: ='Segment economics'!D15 -> 3.19 | D57: ='Segment economics'!C15*(1-Inputs!$G$6*churn_nonbuyers) -> 0.665 | E57: =C57-D57 -> 2.525 | F57: =-B57/(E57+B57) -> -0.28368794 | G57: =Inputs!$M$6/Inputs!$K$6-1 -> -0.5 | H57: =IF(G57>F57,"pays for this segment","fails") -> fails
A58: Reading: for students alone a cut to 2.99 WOULD pay (+88% subscribers against +66% needed, about +7,700 a year). But Plus has one price: at 2.99 the employees lose 56,500, so the price list as a whole loses 48,800 (Sensitivity, 'Option · Plus at 2.99 for everyone'). A separate student price would need proof of status and is not used.

Sheet EVE
A1: Economic value estimation (handout 03; Nagle & Müller 2018, Ch. 2): reference value + differentiation value
A2: Reference value = price of the next-best alternative for the same usage. Differentiation value = what our offer adds (+) or lacks (−) against that alternative. Floor of the value-based range = reference value; ceiling = total economic value (handout 07).
A3: Traveller — typical month: 800 card payments, 400 of them in other currencies, 2 withdrawals abroad
A4: Fluxa without Premium: currency fee 1.0% × 400 | B4: =fluxa_fx*Inputs!$D$8 -> 4 | C4: Case fact (competitors).
A5: Fluxa without Premium: 2 withdrawals abroad × 2.00 | B5: =fluxa_wd*Inputs!$E$8 -> 4 | C5: Case fact.
A6: REFERENCE VALUE — next-best alternative for the same usage (Fluxa, no plan) | B6: =B4+B5 -> 8 | C6: Cheapest alternative: own Basic costs 9.00, Fluxa Premium 13.99, a bank 15–19 (rows 20–23).
A7: + Positive differentiation: travel insurance included (price if bought separately) | B7: =ins_sep -> 4 | C7: Case fact: 'about 4 a month'. Counts in full only for travellers who would buy insurance anyway.
A8: − Negative differentiation (nothing quantifiable on the case sheet) | B8: 0 | C8: Assumption: 0. Shared features (euro account, transfers, savings goals) are not differences and are not counted.
A9: TOTAL ECONOMIC VALUE — ceiling of the value-based range | B9: =B6+B7-B8 -> 12 | C9: The most a fully informed traveller would pay.
A10: Floor of the value-based range = reference value | B10: =B6 -> 8 | C10: Handout 07: below the reference value the firm gives away all differentiation value.
A11: 50:50 starting point for a new product (handout 07) | B11: =B6+(B9-B6)/2 -> 10 | C11: Floor plus half of the differentiation value.
A12: Travel price | B12: =pT -> 6.99 | C12: Decision (Inputs).
A13: Customer keeps: economic value − price | B13: =B9-B12 -> 5.01 | C13: Consumer surplus of an informed traveller who wants insurance.
A14: Price minus reference value (negative = priced below the value-based floor) | B14: =B12-B6 -> -1.01 | C14: At 6.99 the plan is 1.01 cheaper than the Fluxa bill before counting the insurance.
A15: Share of differentiation value captured = (price − reference) ÷ (EVC − reference) | B15: =(B12-B6)/(B9-B6) -> -0.2525 | C15: Negative: a penetration price in the sense of handout 07.
A16: Cost floor: variable cost of a Travel subscriber, net of interchange | B16: =cost_acc+cost_wd*Inputs!$E$8+cost_fx*Inputs!$D$8+cost_ins-ic*Inputs!$C$8 -> 2.7 | C16: Lowest price that still covers incremental cost.
A17: Survey: share who would pay the surveyed price just BELOW the reference value (6.99) | B17: =Inputs!$K$8 -> 0.7 | C17: Case fact.
A18: Survey: share who would pay the surveyed price just ABOVE the reference value (8.99) | B18: =Inputs!$M$8 -> 0.3 | C18: Case fact. The cliff 70% → 30% brackets the reference value of 8.00.
A19: Other alternatives, same usage, with separate insurance (for the comparison on the website)
A20: Fluxa without Premium + separate insurance | B20: =B6+ins_sep -> 12
A21: Fluxa Premium 9.99 + 2 withdrawals + insurance | B21: =fluxa_prem+fluxa_wd*Inputs!$E$8+ins_sep -> 17.99
A22: Bank, low: 2.5% × 400 + 2 × 1.00 + package 3.00 + insurance | B22: =bank_fx*Inputs!$D$8+bank_wd_lo*Inputs!$E$8+bank_pkg_lo+ins_sep -> 19
A23: Bank, high: 2.5% × 400 + 2 × 2.00 + package 5.00 + insurance | B23: =bank_fx*Inputs!$D$8+bank_wd_hi*Inputs!$E$8+bank_pkg_hi+ins_sep -> 23
A24: Own Basic account per use (9.00) + insurance | B24: =fee_wd*Inputs!$E$8+fee_fx*Inputs!$D$8+ins_sep -> 13
A26: Reading: the value-based range is 8.00–12.00 and the 50:50 point is 10.00, yet only 30% would pay 8.99. Stated willingness to pay centres on the reference value: 70% accept the surveyed price below 8.00, 30% the one above it. Most travellers therefore perceive little of the 4.00 insurance value. Travel at 6.99 is a deliberate penetration price below the value-based floor: it maximises contribution on the surveyed prices (Price grid), keeps 70% of the most valuable segment, and the conditions of handout 07 hold (high contribution margin; Novčić's 4,000 travellers are too few to provoke Fluxa). The gap between 6.99 and 12.00 is the job of value communication (handout 05), and 7.99 — just under the reference value — is the first price to test (Break-even, row 47).
A28: Young employee — Plus plan: typical month 900 card payments, 50 in other currencies, 2 withdrawals
A29: REFERENCE VALUE — what the employee pays on Basic for the withdrawals Plus includes: 2 × 1.50 | B29: =fee_wd*Inputs!$E$7 -> 3 | C29: Next-best alternative to Plus is staying on Basic.
A30: + Positive differentiation: shared accounts + virtual cards | B30: =Inputs!$L$7-B29 -> 1.99 | C30: Not quantifiable from the case. Proxy: the top fifth of employees would pay 4.99, so for them the features are worth at least this much.
A31: ECONOMIC VALUE for the upper fifth of employees (proxy ceiling) | B31: =B29+B30 -> 4.99 | C31: A survey-based proxy, not a calculated saving.
A32: Plus price | B32: =pE -> 3.99 | C32: Decision (Inputs).
A33: Share of differentiation value captured = (price − reference) ÷ (EVC − reference) | B33: =(B32-B29)/(B31-B29) -> 0.49748744 | C33: 50% = the 50:50 starting point of handout 07.
A34: Survey: share who would pay 2.99 (just below the reference value of 3.00) | B34: =Inputs!$I$7 -> 0.5 | C34: Case fact. Again the median sits at the reference value.
A35: Typical employee's bill on Plus at 2.99 incl. currency fee, vs on Basic | B35: =Inputs!$H$7+fee_fx*Inputs!$D$7 -> 3.74 | C35: 3.74 against 3.75 on Basic: at 2.99 Plus is only a cheaper way to pay for withdrawals (cannibalisation).
A37: Reading: Plus is priced 0.99 ABOVE its reference value, Travel 1.01 BELOW its reference value. The asymmetry follows from what a non-buyer does: an employee who does not buy Plus stays on Basic and still contributes 2.80 a month (97% stay), so a lost subscriber costs little and the firm can ask for a share of the differentiation value. A traveller who does not buy Travel leaves with 70% probability, so the plan is priced to retain.
A39: Student — why there is no monthly fee on the account
A40: Student at a bank: package 3–5 + 1 withdrawal (1–2) + 2.5% × 25, low | B40: =bank_pkg_lo+bank_wd_lo+bank_fx*Inputs!$D$6 -> 4.625
A41: Student at Fluxa: no fee + 1.0% × 25 (+ 2.00 only if the withdrawal is abroad) | B41: =fluxa_fx*Inputs!$D$6 -> 0.25
A42: Student on Novčić Basic: 1 × 1.50 + 1.5% × 25 | B42: =fee_wd*Inputs!$E$6+fee_fx*Inputs!$D$6 -> 1.875
A43: Students who would leave if the account had a monthly fee | B43: =Inputs!$F$6 -> 0.55
A44: Students who would pay 2.99 for Plus | B44: =Inputs!$I$6 -> 0.15
A46: Reading: the next-best alternative of a student costs close to nothing (Fluxa), so the reference value of the account itself is near zero and a monthly fee cannot be justified by value — the survey confirms it (55% would leave). Basic at 1.88 a month in per-use fees sits between Fluxa and a bank.

Sheet Arbitrage
A1: Do the fences hold? Monthly bill of a typical member of each segment under each offer
A2: A fence works when the customers meant to pay more cannot gain by taking the cheaper offer (handout 04). Here customers choose, so the check is: does each segment pay least on the offer meant for it?
A4: Segment | B4: Basic (per use) | C4: Plus (+ currency fee) | D4: Travel | E4: Cheapest | F4: Comment
A5: Students | B5: =fee_wd*Inputs!$E$6+fee_fx*Inputs!$D$6 -> 1.875 | C5: =pS+fee_fx*Inputs!$D$6+fee_wd*MAX(0,Inputs!$E$6-plus_cap) -> 4.365 | D5: =pT -> 6.99 | E5: =IF(MIN(B5:D5)=B5,"Basic",IF(MIN(B5:D5)=C5,"Plus","Travel")) -> Basic | F5: Basic is cheapest; Plus is bought for its features (15% at 2.99, 8% at 3.99), not to save fees.
A6: Employees | B6: =fee_wd*Inputs!$E$7+fee_fx*Inputs!$D$7 -> 3.75 | C6: =pE+fee_fx*Inputs!$D$7+fee_wd*MAX(0,Inputs!$E$7-plus_cap) -> 4.74 | D6: =pT -> 6.99 | E6: =IF(MIN(B6:D6)=B6,"Basic",IF(MIN(B6:D6)=C6,"Plus","Travel")) -> Basic | F6: Basic is cheapest by 0.99; Plus is bought for shared accounts and virtual cards. At 2.99 Plus would be cheaper than Basic → pure cannibalisation.
A7: Travellers | B7: =fee_wd*Inputs!$E$8+fee_fx*Inputs!$D$8 -> 9 | C7: =pE+fee_fx*Inputs!$D$8+fee_wd*MAX(0,Inputs!$E$8-plus_cap) -> 9.99 | D7: =pT -> 6.99 | E7: =IF(MIN(B7:D7)=B7,"Basic",IF(MIN(B7:D7)=C7,"Plus","Travel")) -> Travel | F7: Travel is cheapest by 2.01 and adds insurance worth about 4.00 — travellers self-select; nobody else gains from Travel.
A9: Ways around the fences and what they cost
A10: Traveller buys Travel only in travel months (monthly, cancel any time) | B10: Pays 6.99 only when abroad; Novčić's variable costs (currency 1.20, withdrawals 2.00, insurance 0.50) also fall in home months, so the loss is the 6.99 − 0.60 account cost in home months. Answer: an annual Travel option at 10 months' price (69.90) rewards commitment (handout 06: discounts for behaviour that saves the seller).
A11: Heavy cash user buys Plus for unlimited withdrawals | B11: Capped: 3 withdrawals included, then 1.50 each. A customer with 6 withdrawals pays 3.99 + 4.50 — the metric tracks cost to serve.
A12: Employee claims a student price (if pS < pE) | B12: Student verification (ISIC / enrolment) — buyer-identification fence. The gain from a separate student price is only about 7,700 a year, so one Plus price is the simpler default.
A13: Student stays on Basic and never withdraws cash | B13: Then the student contributes 0.20 a month (interchange 0.50 + currency fee 0.375 − 0.60 − 0.075): still positive. Basic needs no minimum.

Sheet Sensitivity
A1: Scenario engine — every row recomputes the whole model with its own parameters
A2: Parameter cells that show '=name' follow the Inputs sheet; typed values override for that row only. Add rows by copying one.
A4: Scenario | B4: Basic withdrawals avoided | C4: Plus withdrawal factor | D4: Plus feature cost | E4: Take-up × factor | F4: Per-use churn × factor | G4: Withdrawal cost | H4: Interchange | I4: Withdrawal fee | J4: Currency fee | K4: Plus price S | L4: Plus price E | M4: Travel price | N4: Stud take-up | O4: Stud c/plan | P4: Stud c/basic | Q4: Stud subs | R4: Stud on Basic | S4: Stud contribution | T4: Empl take-up | U4: Empl c/plan | V4: Empl c/basic | W4: Empl subs | X4: Empl on Basic | Y4: Empl contribution | Z4: Trav take-up | AA4: Trav c/plan | AB4: Trav c/basic | AC4: Trav subs | AD4: Trav on Basic | AE4: Trav contribution | AF4: Contribution | AG4: Profit | AH4: Retained
A5: Base case (= Model sheet) | B5: =wd_red -> 0 | C5: =plus_wdf -> 1 | D5: =feat_cost -> 0 | E5: 1 | F5: 1 | G5: =cost_wd -> 1 | H5: =ic -> 0.002 | I5: =fee_wd -> 1.5 | J5: =fee_fx -> 0.015 | K5: =pS -> 3.99 | L5: =pE -> 3.99 | M5: =pT -> 6.99 | N5: =IF($K5="",0,MIN(1,$E5*IF($K5=Inputs!$H$6,Inputs!$I$6,IF($K5=Inputs!$J$6,Inputs!$K$6,IF($K5=Inputs!$L$6,Inputs!$M$6,NA()))))) -> 0.08 | O5: =$H5*Inputs!$C$6+$K5+$J5*Inputs!$D$6-cost_acc-$G5*Inputs!$E$6*$C5-cost_fx*Inputs!$D$6-$D5 -> 3.19 | P5: =$H5*Inputs!$C$6+$I5*Inputs!$E$6*(1-$B5)+$J5*Inputs!$D$6-cost_acc-$G5*Inputs!$E$6*(1-$B5)-cost_fx*Inputs!$D$6 -> 0.7 | Q5: =Inputs!$B$6*N5 -> 1920 | R5: =(Inputs!$B$6-Q5)*(1-MIN(1,Inputs!$G$6*$F5)*churn_nonbuyers) -> 20976 | S5: =12*(Q5*O5+R5*P5) -> 249696 | T5: =IF($L5="",0,MIN(1,$E5*IF($L5=Inputs!$H$7,Inputs!$I$7,IF($L5=Inputs!$J$7,Inputs!$K$7,IF($L5=Inputs!$L$7,Inputs!$M$7,NA()))))) -> 0.4 | U5: =$H5*Inputs!$C$7+$L5+$J5*Inputs!$D$7-cost_acc-$G5*Inputs!$E$7*$C5-cost_fx*Inputs!$D$7-$D5 -> 3.79 | V5: =$H5*Inputs!$C$7+$I5*Inputs!$E$7*(1-$B5)+$J5*Inputs!$D$7-cost_acc-$G5*Inputs!$E$7*(1-$B5)-cost_fx*Inputs!$D$7 -> 2.8 | W5: =Inputs!$B$7*T5 -> 4800 | X5: =(Inputs!$B$7-W5)*(1-MIN(1,Inputs!$G$7*$F5)*churn_nonbuyers) -> 6984 | Y5: =12*(W5*U5+X5*V5) -> 452966.4 | Z5: =IF($M5="",0,MIN(1,$E5*IF($M5=Inputs!$H$8,Inputs!$I$8,IF($M5=Inputs!$J$8,Inputs!$K$8,IF($M5=Inputs!$L$8,Inputs!$M$8,NA()))))) -> 0.7 | AA5: =$H5*Inputs!$C$8+$M5-cost_acc-$G5*Inputs!$E$8-cost_fx*Inputs!$D$8-cost_ins -> 4.29 | AB5: =$H5*Inputs!$C$8+$I5*Inputs!$E$8*(1-$B5)+$J5*Inputs!$D$8-cost_acc-$G5*Inputs!$E$8*(1-$B5)-cost_fx*Inputs!$D$8 -> 6.8 | AC5: =Inputs!$B$8*Z5 -> 2800 | AD5: =(Inputs!$B$8-AC5)*(1-MIN(1,Inputs!$G$8*$F5)*churn_nonbuyers) -> 360 | AE5: =12*(AC5*AA5+AD5*AB5) -> 173520 | AF5: =S5+Y5+AE5 -> 876182.4 | AG5: =AF5-fixed -> 176182.4 | AH5: =Q5+R5+W5+X5+AC5+AD5 -> 37840
A6: Basic customers make 25% fewer withdrawals | B6: 0.25 | C6: =plus_wdf -> 1 | D6: =feat_cost -> 0 | E6: 1 | F6: 1 | G6: =cost_wd -> 1 | H6: =ic -> 0.002 | I6: =fee_wd -> 1.5 | J6: =fee_fx -> 0.015 | K6: =pS -> 3.99 | L6: =pE -> 3.99 | M6: =pT -> 6.99 | N6: =IF($K6="",0,MIN(1,$E6*IF($K6=Inputs!$H$6,Inputs!$I$6,IF($K6=Inputs!$J$6,Inputs!$K$6,IF($K6=Inputs!$L$6,Inputs!$M$6,NA()))))) -> 0.08 | O6: =$H6*Inputs!$C$6+$K6+$J6*Inputs!$D$6-cost_acc-$G6*Inputs!$E$6*$C6-cost_fx*Inputs!$D$6-$D6 -> 3.19 | P6: =$H6*Inputs!$C$6+$I6*Inputs!$E$6*(1-$B6)+$J6*Inputs!$D$6-cost_acc-$G6*Inputs!$E$6*(1-$B6)-cost_fx*Inputs!$D$6 -> 0.575 | Q6: =Inputs!$B$6*N6 -> 1920 | R6: =(Inputs!$B$6-Q6)*(1-MIN(1,Inputs!$G$6*$F6)*churn_nonbuyers) -> 20976 | S6: =12*(Q6*O6+R6*P6) -> 218232 | T6: =IF($L6="",0,MIN(1,$E6*IF($L6=Inputs!$H$7,Inputs!$I$7,IF($L6=Inputs!$J$7,Inputs!$K$7,IF($L6=Inputs!$L$7,Inputs!$M$7,NA()))))) -> 0.4 | U6: =$H6*Inputs!$C$7+$L6+$J6*Inputs!$D$7-cost_acc-$G6*Inputs!$E$7*$C6-cost_fx*Inputs!$D$7-$D6 -> 3.79 | V6: =$H6*Inputs!$C$7+$I6*Inputs!$E$7*(1-$B6)+$J6*Inputs!$D$7-cost_acc-$G6*Inputs!$E$7*(1-$B6)-cost_fx*Inputs!$D$7 -> 2.55 | W6: =Inputs!$B$7*T6 -> 4800 | X6: =(Inputs!$B$7-W6)*(1-MIN(1,Inputs!$G$7*$F6)*churn_nonbuyers) -> 6984 | Y6: =12*(W6*U6+X6*V6) -> 432014.4 | Z6: =IF($M6="",0,MIN(1,$E6*IF($M6=Inputs!$H$8,Inputs!$I$8,IF($M6=Inputs!$J$8,Inputs!$K$8,IF($M6=Inputs!$L$8,Inputs!$M$8,NA()))))) -> 0.7 | AA6: =$H6*Inputs!$C$8+$M6-cost_acc-$G6*Inputs!$E$8-cost_fx*Inputs!$D$8-cost_ins -> 4.29 | AB6: =$H6*Inputs!$C$8+$I6*Inputs!$E$8*(1-$B6)+$J6*Inputs!$D$8-cost_acc-$G6*Inputs!$E$8*(1-$B6)-cost_fx*Inputs!$D$8 -> 6.55 | AC6: =Inputs!$B$8*Z6 -> 2800 | AD6: =(Inputs!$B$8-AC6)*(1-MIN(1,Inputs!$G$8*$F6)*churn_nonbuyers) -> 360 | AE6: =12*(AC6*AA6+AD6*AB6) -> 172440 | AF6: =S6+Y6+AE6 -> 822686.4 | AG6: =AF6-fixed -> 122686.4 | AH6: =Q6+R6+W6+X6+AC6+AD6 -> 37840
A7: Basic customers make 50% fewer withdrawals | B7: 0.5 | C7: =plus_wdf -> 1 | D7: =feat_cost -> 0 | E7: 1 | F7: 1 | G7: =cost_wd -> 1 | H7: =ic -> 0.002 | I7: =fee_wd -> 1.5 | J7: =fee_fx -> 0.015 | K7: =pS -> 3.99 | L7: =pE -> 3.99 | M7: =pT -> 6.99 | N7: =IF($K7="",0,MIN(1,$E7*IF($K7=Inputs!$H$6,Inputs!$I$6,IF($K7=Inputs!$J$6,Inputs!$K$6,IF($K7=Inputs!$L$6,Inputs!$M$6,NA()))))) -> 0.08 | O7: =$H7*Inputs!$C$6+$K7+$J7*Inputs!$D$6-cost_acc-$G7*Inputs!$E$6*$C7-cost_fx*Inputs!$D$6-$D7 -> 3.19 | P7: =$H7*Inputs!$C$6+$I7*Inputs!$E$6*(1-$B7)+$J7*Inputs!$D$6-cost_acc-$G7*Inputs!$E$6*(1-$B7)-cost_fx*Inputs!$D$6 -> 0.45 | Q7: =Inputs!$B$6*N7 -> 1920 | R7: =(Inputs!$B$6-Q7)*(1-MIN(1,Inputs!$G$6*$F7)*churn_nonbuyers) -> 20976 | S7: =12*(Q7*O7+R7*P7) -> 186768 | T7: =IF($L7="",0,MIN(1,$E7*IF($L7=Inputs!$H$7,Inputs!$I$7,IF($L7=Inputs!$J$7,Inputs!$K$7,IF($L7=Inputs!$L$7,Inputs!$M$7,NA()))))) -> 0.4 | U7: =$H7*Inputs!$C$7+$L7+$J7*Inputs!$D$7-cost_acc-$G7*Inputs!$E$7*$C7-cost_fx*Inputs!$D$7-$D7 -> 3.79 | V7: =$H7*Inputs!$C$7+$I7*Inputs!$E$7*(1-$B7)+$J7*Inputs!$D$7-cost_acc-$G7*Inputs!$E$7*(1-$B7)-cost_fx*Inputs!$D$7 -> 2.3 | W7: =Inputs!$B$7*T7 -> 4800 | X7: =(Inputs!$B$7-W7)*(1-MIN(1,Inputs!$G$7*$F7)*churn_nonbuyers) -> 6984 | Y7: =12*(W7*U7+X7*V7) -> 411062.4 | Z7: =IF($M7="",0,MIN(1,$E7*IF($M7=Inputs!$H$8,Inputs!$I$8,IF($M7=Inputs!$J$8,Inputs!$K$8,IF($M7=Inputs!$L$8,Inputs!$M$8,NA()))))) -> 0.7 | AA7: =$H7*Inputs!$C$8+$M7-cost_acc-$G7*Inputs!$E$8-cost_fx*Inputs!$D$8-cost_ins -> 4.29 | AB7: =$H7*Inputs!$C$8+$I7*Inputs!$E$8*(1-$B7)+$J7*Inputs!$D$8-cost_acc-$G7*Inputs!$E$8*(1-$B7)-cost_fx*Inputs!$D$8 -> 6.3 | AC7: =Inputs!$B$8*Z7 -> 2800 | AD7: =(Inputs!$B$8-AC7)*(1-MIN(1,Inputs!$G$8*$F7)*churn_nonbuyers) -> 360 | AE7: =12*(AC7*AA7+AD7*AB7) -> 171360 | AF7: =S7+Y7+AE7 -> 769190.4 | AG7: =AF7-fixed -> 69190.4 | AH7: =Q7+R7+W7+X7+AC7+AD7 -> 37840
A8: Basic customers make 75% fewer withdrawals | B8: 0.75 | C8: =plus_wdf -> 1 | D8: =feat_cost -> 0 | E8: 1 | F8: 1 | G8: =cost_wd -> 1 | H8: =ic -> 0.002 | I8: =fee_wd -> 1.5 | J8: =fee_fx -> 0.015 | K8: =pS -> 3.99 | L8: =pE -> 3.99 | M8: =pT -> 6.99 | N8: =IF($K8="",0,MIN(1,$E8*IF($K8=Inputs!$H$6,Inputs!$I$6,IF($K8=Inputs!$J$6,Inputs!$K$6,IF($K8=Inputs!$L$6,Inputs!$M$6,NA()))))) -> 0.08 | O8: =$H8*Inputs!$C$6+$K8+$J8*Inputs!$D$6-cost_acc-$G8*Inputs!$E$6*$C8-cost_fx*Inputs!$D$6-$D8 -> 3.19 | P8: =$H8*Inputs!$C$6+$I8*Inputs!$E$6*(1-$B8)+$J8*Inputs!$D$6-cost_acc-$G8*Inputs!$E$6*(1-$B8)-cost_fx*Inputs!$D$6 -> 0.325 | Q8: =Inputs!$B$6*N8 -> 1920 | R8: =(Inputs!$B$6-Q8)*(1-MIN(1,Inputs!$G$6*$F8)*churn_nonbuyers) -> 20976 | S8: =12*(Q8*O8+R8*P8) -> 155304 | T8: =IF($L8="",0,MIN(1,$E8*IF($L8=Inputs!$H$7,Inputs!$I$7,IF($L8=Inputs!$J$7,Inputs!$K$7,IF($L8=Inputs!$L$7,Inputs!$M$7,NA()))))) -> 0.4 | U8: =$H8*Inputs!$C$7+$L8+$J8*Inputs!$D$7-cost_acc-$G8*Inputs!$E$7*$C8-cost_fx*Inputs!$D$7-$D8 -> 3.79 | V8: =$H8*Inputs!$C$7+$I8*Inputs!$E$7*(1-$B8)+$J8*Inputs!$D$7-cost_acc-$G8*Inputs!$E$7*(1-$B8)-cost_fx*Inputs!$D$7 -> 2.05 | W8: =Inputs!$B$7*T8 -> 4800 | X8: =(Inputs!$B$7-W8)*(1-MIN(1,Inputs!$G$7*$F8)*churn_nonbuyers) -> 6984 | Y8: =12*(W8*U8+X8*V8) -> 390110.4 | Z8: =IF($M8="",0,MIN(1,$E8*IF($M8=Inputs!$H$8,Inputs!$I$8,IF($M8=Inputs!$J$8,Inputs!$K$8,IF($M8=Inputs!$L$8,Inputs!$M$8,NA()))))) -> 0.7 | AA8: =$H8*Inputs!$C$8+$M8-cost_acc-$G8*Inputs!$E$8-cost_fx*Inputs!$D$8-cost_ins -> 4.29 | AB8: =$H8*Inputs!$C$8+$I8*Inputs!$E$8*(1-$B8)+$J8*Inputs!$D$8-cost_acc-$G8*Inputs!$E$8*(1-$B8)-cost_fx*Inputs!$D$8 -> 6.05 | AC8: =Inputs!$B$8*Z8 -> 2800 | AD8: =(Inputs!$B$8-AC8)*(1-MIN(1,Inputs!$G$8*$F8)*churn_nonbuyers) -> 360 | AE8: =12*(AC8*AA8+AD8*AB8) -> 170280 | AF8: =S8+Y8+AE8 -> 715694.4 | AG8: =AF8-fixed -> 15694.4 | AH8: =Q8+R8+W8+X8+AC8+AD8 -> 37840
A9: Plus subscribers withdraw 1.5× (no cap enforced) | B9: =wd_red -> 0 | C9: 1.5 | D9: =feat_cost -> 0 | E9: 1 | F9: 1 | G9: =cost_wd -> 1 | H9: =ic -> 0.002 | I9: =fee_wd -> 1.5 | J9: =fee_fx -> 0.015 | K9: =pS -> 3.99 | L9: =pE -> 3.99 | M9: =pT -> 6.99 | N9: =IF($K9="",0,MIN(1,$E9*IF($K9=Inputs!$H$6,Inputs!$I$6,IF($K9=Inputs!$J$6,Inputs!$K$6,IF($K9=Inputs!$L$6,Inputs!$M$6,NA()))))) -> 0.08 | O9: =$H9*Inputs!$C$6+$K9+$J9*Inputs!$D$6-cost_acc-$G9*Inputs!$E$6*$C9-cost_fx*Inputs!$D$6-$D9 -> 2.69 | P9: =$H9*Inputs!$C$6+$I9*Inputs!$E$6*(1-$B9)+$J9*Inputs!$D$6-cost_acc-$G9*Inputs!$E$6*(1-$B9)-cost_fx*Inputs!$D$6 -> 0.7 | Q9: =Inputs!$B$6*N9 -> 1920 | R9: =(Inputs!$B$6-Q9)*(1-MIN(1,Inputs!$G$6*$F9)*churn_nonbuyers) -> 20976 | S9: =12*(Q9*O9+R9*P9) -> 238176 | T9: =IF($L9="",0,MIN(1,$E9*IF($L9=Inputs!$H$7,Inputs!$I$7,IF($L9=Inputs!$J$7,Inputs!$K$7,IF($L9=Inputs!$L$7,Inputs!$M$7,NA()))))) -> 0.4 | U9: =$H9*Inputs!$C$7+$L9+$J9*Inputs!$D$7-cost_acc-$G9*Inputs!$E$7*$C9-cost_fx*Inputs!$D$7-$D9 -> 2.79 | V9: =$H9*Inputs!$C$7+$I9*Inputs!$E$7*(1-$B9)+$J9*Inputs!$D$7-cost_acc-$G9*Inputs!$E$7*(1-$B9)-cost_fx*Inputs!$D$7 -> 2.8 | W9: =Inputs!$B$7*T9 -> 4800 | X9: =(Inputs!$B$7-W9)*(1-MIN(1,Inputs!$G$7*$F9)*churn_nonbuyers) -> 6984 | Y9: =12*(W9*U9+X9*V9) -> 395366.4 | Z9: =IF($M9="",0,MIN(1,$E9*IF($M9=Inputs!$H$8,Inputs!$I$8,IF($M9=Inputs!$J$8,Inputs!$K$8,IF($M9=Inputs!$L$8,Inputs!$M$8,NA()))))) -> 0.7 | AA9: =$H9*Inputs!$C$8+$M9-cost_acc-$G9*Inputs!$E$8-cost_fx*Inputs!$D$8-cost_ins -> 4.29 | AB9: =$H9*Inputs!$C$8+$I9*Inputs!$E$8*(1-$B9)+$J9*Inputs!$D$8-cost_acc-$G9*Inputs!$E$8*(1-$B9)-cost_fx*Inputs!$D$8 -> 6.8 | AC9: =Inputs!$B$8*Z9 -> 2800 | AD9: =(Inputs!$B$8-AC9)*(1-MIN(1,Inputs!$G$8*$F9)*churn_nonbuyers) -> 360 | AE9: =12*(AC9*AA9+AD9*AB9) -> 173520 | AF9: =S9+Y9+AE9 -> 807062.4 | AG9: =AF9-fixed -> 107062.4 | AH9: =Q9+R9+W9+X9+AC9+AD9 -> 37840
A10: Plus subscribers withdraw 2× (no cap enforced) | B10: =wd_red -> 0 | C10: 2 | D10: =feat_cost -> 0 | E10: 1 | F10: 1 | G10: =cost_wd -> 1 | H10: =ic -> 0.002 | I10: =fee_wd -> 1.5 | J10: =fee_fx -> 0.015 | K10: =pS -> 3.99 | L10: =pE -> 3.99 | M10: =pT -> 6.99 | N10: =IF($K10="",0,MIN(1,$E10*IF($K10=Inputs!$H$6,Inputs!$I$6,IF($K10=Inputs!$J$6,Inputs!$K$6,IF($K10=Inputs!$L$6,Inputs!$M$6,NA()))))) -> 0.08 | O10: =$H10*Inputs!$C$6+$K10+$J10*Inputs!$D$6-cost_acc-$G10*Inputs!$E$6*$C10-cost_fx*Inputs!$D$6-$D10 -> 2.19 | P10: =$H10*Inputs!$C$6+$I10*Inputs!$E$6*(1-$B10)+$J10*Inputs!$D$6-cost_acc-$G10*Inputs!$E$6*(1-$B10)-cost_fx*Inputs!$D$6 -> 0.7 | Q10: =Inputs!$B$6*N10 -> 1920 | R10: =(Inputs!$B$6-Q10)*(1-MIN(1,Inputs!$G$6*$F10)*churn_nonbuyers) -> 20976 | S10: =12*(Q10*O10+R10*P10) -> 226656 | T10: =IF($L10="",0,MIN(1,$E10*IF($L10=Inputs!$H$7,Inputs!$I$7,IF($L10=Inputs!$J$7,Inputs!$K$7,IF($L10=Inputs!$L$7,Inputs!$M$7,NA()))))) -> 0.4 | U10: =$H10*Inputs!$C$7+$L10+$J10*Inputs!$D$7-cost_acc-$G10*Inputs!$E$7*$C10-cost_fx*Inputs!$D$7-$D10 -> 1.79 | V10: =$H10*Inputs!$C$7+$I10*Inputs!$E$7*(1-$B10)+$J10*Inputs!$D$7-cost_acc-$G10*Inputs!$E$7*(1-$B10)-cost_fx*Inputs!$D$7 -> 2.8 | W10: =Inputs!$B$7*T10 -> 4800 | X10: =(Inputs!$B$7-W10)*(1-MIN(1,Inputs!$G$7*$F10)*churn_nonbuyers) -> 6984 | Y10: =12*(W10*U10+X10*V10) -> 337766.4 | Z10: =IF($M10="",0,MIN(1,$E10*IF($M10=Inputs!$H$8,Inputs!$I$8,IF($M10=Inputs!$J$8,Inputs!$K$8,IF($M10=Inputs!$L$8,Inputs!$M$8,NA()))))) -> 0.7 | AA10: =$H10*Inputs!$C$8+$M10-cost_acc-$G10*Inputs!$E$8-cost_fx*Inputs!$D$8-cost_ins -> 4.29 | AB10: =$H10*Inputs!$C$8+$I10*Inputs!$E$8*(1-$B10)+$J10*Inputs!$D$8-cost_acc-$G10*Inputs!$E$8*(1-$B10)-cost_fx*Inputs!$D$8 -> 6.8 | AC10: =Inputs!$B$8*Z10 -> 2800 | AD10: =(Inputs!$B$8-AC10)*(1-MIN(1,Inputs!$G$8*$F10)*churn_nonbuyers) -> 360 | AE10: =12*(AC10*AA10+AD10*AB10) -> 173520 | AF10: =S10+Y10+AE10 -> 737942.4 | AG10: =AF10-fixed -> 37942.4 | AH10: =Q10+R10+W10+X10+AC10+AD10 -> 37840
A11: Plus features cost 0.25 per subscriber per month | B11: =wd_red -> 0 | C11: =plus_wdf -> 1 | D11: 0.25 | E11: 1 | F11: 1 | G11: =cost_wd -> 1 | H11: =ic -> 0.002 | I11: =fee_wd -> 1.5 | J11: =fee_fx -> 0.015 | K11: =pS -> 3.99 | L11: =pE -> 3.99 | M11: =pT -> 6.99 | N11: =IF($K11="",0,MIN(1,$E11*IF($K11=Inputs!$H$6,Inputs!$I$6,IF($K11=Inputs!$J$6,Inputs!$K$6,IF($K11=Inputs!$L$6,Inputs!$M$6,NA()))))) -> 0.08 | O11: =$H11*Inputs!$C$6+$K11+$J11*Inputs!$D$6-cost_acc-$G11*Inputs!$E$6*$C11-cost_fx*Inputs!$D$6-$D11 -> 2.94 | P11: =$H11*Inputs!$C$6+$I11*Inputs!$E$6*(1-$B11)+$J11*Inputs!$D$6-cost_acc-$G11*Inputs!$E$6*(1-$B11)-cost_fx*Inputs!$D$6 -> 0.7 | Q11: =Inputs!$B$6*N11 -> 1920 | R11: =(Inputs!$B$6-Q11)*(1-MIN(1,Inputs!$G$6*$F11)*churn_nonbuyers) -> 20976 | S11: =12*(Q11*O11+R11*P11) -> 243936 | T11: =IF($L11="",0,MIN(1,$E11*IF($L11=Inputs!$H$7,Inputs!$I$7,IF($L11=Inputs!$J$7,Inputs!$K$7,IF($L11=Inputs!$L$7,Inputs!$M$7,NA()))))) -> 0.4 | U11: =$H11*Inputs!$C$7+$L11+$J11*Inputs!$D$7-cost_acc-$G11*Inputs!$E$7*$C11-cost_fx*Inputs!$D$7-$D11 -> 3.54 | V11: =$H11*Inputs!$C$7+$I11*Inputs!$E$7*(1-$B11)+$J11*Inputs!$D$7-cost_acc-$G11*Inputs!$E$7*(1-$B11)-cost_fx*Inputs!$D$7 -> 2.8 | W11: =Inputs!$B$7*T11 -> 4800 | X11: =(Inputs!$B$7-W11)*(1-MIN(1,Inputs!$G$7*$F11)*churn_nonbuyers) -> 6984 | Y11: =12*(W11*U11+X11*V11) -> 438566.4 | Z11: =IF($M11="",0,MIN(1,$E11*IF($M11=Inputs!$H$8,Inputs!$I$8,IF($M11=Inputs!$J$8,Inputs!$K$8,IF($M11=Inputs!$L$8,Inputs!$M$8,NA()))))) -> 0.7 | AA11: =$H11*Inputs!$C$8+$M11-cost_acc-$G11*Inputs!$E$8-cost_fx*Inputs!$D$8-cost_ins -> 4.29 | AB11: =$H11*Inputs!$C$8+$I11*Inputs!$E$8*(1-$B11)+$J11*Inputs!$D$8-cost_acc-$G11*Inputs!$E$8*(1-$B11)-cost_fx*Inputs!$D$8 -> 6.8 | AC11: =Inputs!$B$8*Z11 -> 2800 | AD11: =(Inputs!$B$8-AC11)*(1-MIN(1,Inputs!$G$8*$F11)*churn_nonbuyers) -> 360 | AE11: =12*(AC11*AA11+AD11*AB11) -> 173520 | AF11: =S11+Y11+AE11 -> 856022.4 | AG11: =AF11-fixed -> 156022.4 | AH11: =Q11+R11+W11+X11+AC11+AD11 -> 37840
A12: Plus features cost 0.50 per subscriber per month | B12: =wd_red -> 0 | C12: =plus_wdf -> 1 | D12: 0.5 | E12: 1 | F12: 1 | G12: =cost_wd -> 1 | H12: =ic -> 0.002 | I12: =fee_wd -> 1.5 | J12: =fee_fx -> 0.015 | K12: =pS -> 3.99 | L12: =pE -> 3.99 | M12: =pT -> 6.99 | N12: =IF($K12="",0,MIN(1,$E12*IF($K12=Inputs!$H$6,Inputs!$I$6,IF($K12=Inputs!$J$6,Inputs!$K$6,IF($K12=Inputs!$L$6,Inputs!$M$6,NA()))))) -> 0.08 | O12: =$H12*Inputs!$C$6+$K12+$J12*Inputs!$D$6-cost_acc-$G12*Inputs!$E$6*$C12-cost_fx*Inputs!$D$6-$D12 -> 2.69 | P12: =$H12*Inputs!$C$6+$I12*Inputs!$E$6*(1-$B12)+$J12*Inputs!$D$6-cost_acc-$G12*Inputs!$E$6*(1-$B12)-cost_fx*Inputs!$D$6 -> 0.7 | Q12: =Inputs!$B$6*N12 -> 1920 | R12: =(Inputs!$B$6-Q12)*(1-MIN(1,Inputs!$G$6*$F12)*churn_nonbuyers) -> 20976 | S12: =12*(Q12*O12+R12*P12) -> 238176 | T12: =IF($L12="",0,MIN(1,$E12*IF($L12=Inputs!$H$7,Inputs!$I$7,IF($L12=Inputs!$J$7,Inputs!$K$7,IF($L12=Inputs!$L$7,Inputs!$M$7,NA()))))) -> 0.4 | U12: =$H12*Inputs!$C$7+$L12+$J12*Inputs!$D$7-cost_acc-$G12*Inputs!$E$7*$C12-cost_fx*Inputs!$D$7-$D12 -> 3.29 | V12: =$H12*Inputs!$C$7+$I12*Inputs!$E$7*(1-$B12)+$J12*Inputs!$D$7-cost_acc-$G12*Inputs!$E$7*(1-$B12)-cost_fx*Inputs!$D$7 -> 2.8 | W12: =Inputs!$B$7*T12 -> 4800 | X12: =(Inputs!$B$7-W12)*(1-MIN(1,Inputs!$G$7*$F12)*churn_nonbuyers) -> 6984 | Y12: =12*(W12*U12+X12*V12) -> 424166.4 | Z12: =IF($M12="",0,MIN(1,$E12*IF($M12=Inputs!$H$8,Inputs!$I$8,IF($M12=Inputs!$J$8,Inputs!$K$8,IF($M12=Inputs!$L$8,Inputs!$M$8,NA()))))) -> 0.7 | AA12: =$H12*Inputs!$C$8+$M12-cost_acc-$G12*Inputs!$E$8-cost_fx*Inputs!$D$8-cost_ins -> 4.29 | AB12: =$H12*Inputs!$C$8+$I12*Inputs!$E$8*(1-$B12)+$J12*Inputs!$D$8-cost_acc-$G12*Inputs!$E$8*(1-$B12)-cost_fx*Inputs!$D$8 -> 6.8 | AC12: =Inputs!$B$8*Z12 -> 2800 | AD12: =(Inputs!$B$8-AC12)*(1-MIN(1,Inputs!$G$8*$F12)*churn_nonbuyers) -> 360 | AE12: =12*(AC12*AA12+AD12*AB12) -> 173520 | AF12: =S12+Y12+AE12 -> 835862.4 | AG12: =AF12-fixed -> 135862.4 | AH12: =Q12+R12+W12+X12+AC12+AD12 -> 37840
A13: Plan take-up 20% below the survey | B13: =wd_red -> 0 | C13: =plus_wdf -> 1 | D13: =feat_cost -> 0 | E13: 0.8 | F13: 1 | G13: =cost_wd -> 1 | H13: =ic -> 0.002 | I13: =fee_wd -> 1.5 | J13: =fee_fx -> 0.015 | K13: =pS -> 3.99 | L13: =pE -> 3.99 | M13: =pT -> 6.99 | N13: =IF($K13="",0,MIN(1,$E13*IF($K13=Inputs!$H$6,Inputs!$I$6,IF($K13=Inputs!$J$6,Inputs!$K$6,IF($K13=Inputs!$L$6,Inputs!$M$6,NA()))))) -> 0.064 | O13: =$H13*Inputs!$C$6+$K13+$J13*Inputs!$D$6-cost_acc-$G13*Inputs!$E$6*$C13-cost_fx*Inputs!$D$6-$D13 -> 3.19 | P13: =$H13*Inputs!$C$6+$I13*Inputs!$E$6*(1-$B13)+$J13*Inputs!$D$6-cost_acc-$G13*Inputs!$E$6*(1-$B13)-cost_fx*Inputs!$D$6 -> 0.7 | Q13: =Inputs!$B$6*N13 -> 1536 | R13: =(Inputs!$B$6-Q13)*(1-MIN(1,Inputs!$G$6*$F13)*churn_nonbuyers) -> 21340.8 | S13: =12*(Q13*O13+R13*P13) -> 238060.8 | T13: =IF($L13="",0,MIN(1,$E13*IF($L13=Inputs!$H$7,Inputs!$I$7,IF($L13=Inputs!$J$7,Inputs!$K$7,IF($L13=Inputs!$L$7,Inputs!$M$7,NA()))))) -> 0.32 | U13: =$H13*Inputs!$C$7+$L13+$J13*Inputs!$D$7-cost_acc-$G13*Inputs!$E$7*$C13-cost_fx*Inputs!$D$7-$D13 -> 3.79 | V13: =$H13*Inputs!$C$7+$I13*Inputs!$E$7*(1-$B13)+$J13*Inputs!$D$7-cost_acc-$G13*Inputs!$E$7*(1-$B13)-cost_fx*Inputs!$D$7 -> 2.8 | W13: =Inputs!$B$7*T13 -> 3840 | X13: =(Inputs!$B$7-W13)*(1-MIN(1,Inputs!$G$7*$F13)*churn_nonbuyers) -> 7915.2 | Y13: =12*(W13*U13+X13*V13) -> 440593.92 | Z13: =IF($M13="",0,MIN(1,$E13*IF($M13=Inputs!$H$8,Inputs!$I$8,IF($M13=Inputs!$J$8,Inputs!$K$8,IF($M13=Inputs!$L$8,Inputs!$M$8,NA()))))) -> 0.56 | AA13: =$H13*Inputs!$C$8+$M13-cost_acc-$G13*Inputs!$E$8-cost_fx*Inputs!$D$8-cost_ins -> 4.29 | AB13: =$H13*Inputs!$C$8+$I13*Inputs!$E$8*(1-$B13)+$J13*Inputs!$D$8-cost_acc-$G13*Inputs!$E$8*(1-$B13)-cost_fx*Inputs!$D$8 -> 6.8 | AC13: =Inputs!$B$8*Z13 -> 2240 | AD13: =(Inputs!$B$8-AC13)*(1-MIN(1,Inputs!$G$8*$F13)*churn_nonbuyers) -> 528 | AE13: =12*(AC13*AA13+AD13*AB13) -> 158400 | AF13: =S13+Y13+AE13 -> 837054.72 | AG13: =AF13-fixed -> 137054.72 | AH13: =Q13+R13+W13+X13+AC13+AD13 -> 37400
A14: Plan take-up 20% above the survey | B14: =wd_red -> 0 | C14: =plus_wdf -> 1 | D14: =feat_cost -> 0 | E14: 1.2 | F14: 1 | G14: =cost_wd -> 1 | H14: =ic -> 0.002 | I14: =fee_wd -> 1.5 | J14: =fee_fx -> 0.015 | K14: =pS -> 3.99 | L14: =pE -> 3.99 | M14: =pT -> 6.99 | N14: =IF($K14="",0,MIN(1,$E14*IF($K14=Inputs!$H$6,Inputs!$I$6,IF($K14=Inputs!$J$6,Inputs!$K$6,IF($K14=Inputs!$L$6,Inputs!$M$6,NA()))))) -> 0.096 | O14: =$H14*Inputs!$C$6+$K14+$J14*Inputs!$D$6-cost_acc-$G14*Inputs!$E$6*$C14-cost_fx*Inputs!$D$6-$D14 -> 3.19 | P14: =$H14*Inputs!$C$6+$I14*Inputs!$E$6*(1-$B14)+$J14*Inputs!$D$6-cost_acc-$G14*Inputs!$E$6*(1-$B14)-cost_fx*Inputs!$D$6 -> 0.7 | Q14: =Inputs!$B$6*N14 -> 2304 | R14: =(Inputs!$B$6-Q14)*(1-MIN(1,Inputs!$G$6*$F14)*churn_nonbuyers) -> 20611.2 | S14: =12*(Q14*O14+R14*P14) -> 261331.2 | T14: =IF($L14="",0,MIN(1,$E14*IF($L14=Inputs!$H$7,Inputs!$I$7,IF($L14=Inputs!$J$7,Inputs!$K$7,IF($L14=Inputs!$L$7,Inputs!$M$7,NA()))))) -> 0.48 | U14: =$H14*Inputs!$C$7+$L14+$J14*Inputs!$D$7-cost_acc-$G14*Inputs!$E$7*$C14-cost_fx*Inputs!$D$7-$D14 -> 3.79 | V14: =$H14*Inputs!$C$7+$I14*Inputs!$E$7*(1-$B14)+$J14*Inputs!$D$7-cost_acc-$G14*Inputs!$E$7*(1-$B14)-cost_fx*Inputs!$D$7 -> 2.8 | W14: =Inputs!$B$7*T14 -> 5760 | X14: =(Inputs!$B$7-W14)*(1-MIN(1,Inputs!$G$7*$F14)*churn_nonbuyers) -> 6052.8 | Y14: =12*(W14*U14+X14*V14) -> 465338.88 | Z14: =IF($M14="",0,MIN(1,$E14*IF($M14=Inputs!$H$8,Inputs!$I$8,IF($M14=Inputs!$J$8,Inputs!$K$8,IF($M14=Inputs!$L$8,Inputs!$M$8,NA()))))) -> 0.84 | AA14: =$H14*Inputs!$C$8+$M14-cost_acc-$G14*Inputs!$E$8-cost_fx*Inputs!$D$8-cost_ins -> 4.29 | AB14: =$H14*Inputs!$C$8+$I14*Inputs!$E$8*(1-$B14)+$J14*Inputs!$D$8-cost_acc-$G14*Inputs!$E$8*(1-$B14)-cost_fx*Inputs!$D$8 -> 6.8 | AC14: =Inputs!$B$8*Z14 -> 3360 | AD14: =(Inputs!$B$8-AC14)*(1-MIN(1,Inputs!$G$8*$F14)*churn_nonbuyers) -> 192 | AE14: =12*(AC14*AA14+AD14*AB14) -> 188640 | AF14: =S14+Y14+AE14 -> 915310.08 | AG14: =AF14-fixed -> 215310.08 | AH14: =Q14+R14+W14+X14+AC14+AD14 -> 38280
A15: Per-use churn twice the survey | B15: =wd_red -> 0 | C15: =plus_wdf -> 1 | D15: =feat_cost -> 0 | E15: 1 | F15: 2 | G15: =cost_wd -> 1 | H15: =ic -> 0.002 | I15: =fee_wd -> 1.5 | J15: =fee_fx -> 0.015 | K15: =pS -> 3.99 | L15: =pE -> 3.99 | M15: =pT -> 6.99 | N15: =IF($K15="",0,MIN(1,$E15*IF($K15=Inputs!$H$6,Inputs!$I$6,IF($K15=Inputs!$J$6,Inputs!$K$6,IF($K15=Inputs!$L$6,Inputs!$M$6,NA()))))) -> 0.08 | O15: =$H15*Inputs!$C$6+$K15+$J15*Inputs!$D$6-cost_acc-$G15*Inputs!$E$6*$C15-cost_fx*Inputs!$D$6-$D15 -> 3.19 | P15: =$H15*Inputs!$C$6+$I15*Inputs!$E$6*(1-$B15)+$J15*Inputs!$D$6-cost_acc-$G15*Inputs!$E$6*(1-$B15)-cost_fx*Inputs!$D$6 -> 0.7 | Q15: =Inputs!$B$6*N15 -> 1920 | R15: =(Inputs!$B$6-Q15)*(1-MIN(1,Inputs!$G$6*$F15)*churn_nonbuyers) -> 19872 | S15: =12*(Q15*O15+R15*P15) -> 240422.4 | T15: =IF($L15="",0,MIN(1,$E15*IF($L15=Inputs!$H$7,Inputs!$I$7,IF($L15=Inputs!$J$7,Inputs!$K$7,IF($L15=Inputs!$L$7,Inputs!$M$7,NA()))))) -> 0.4 | U15: =$H15*Inputs!$C$7+$L15+$J15*Inputs!$D$7-cost_acc-$G15*Inputs!$E$7*$C15-cost_fx*Inputs!$D$7-$D15 -> 3.79 | V15: =$H15*Inputs!$C$7+$I15*Inputs!$E$7*(1-$B15)+$J15*Inputs!$D$7-cost_acc-$G15*Inputs!$E$7*(1-$B15)-cost_fx*Inputs!$D$7 -> 2.8 | W15: =Inputs!$B$7*T15 -> 4800 | X15: =(Inputs!$B$7-W15)*(1-MIN(1,Inputs!$G$7*$F15)*churn_nonbuyers) -> 6768 | Y15: =12*(W15*U15+X15*V15) -> 445708.8 | Z15: =IF($M15="",0,MIN(1,$E15*IF($M15=Inputs!$H$8,Inputs!$I$8,IF($M15=Inputs!$J$8,Inputs!$K$8,IF($M15=Inputs!$L$8,Inputs!$M$8,NA()))))) -> 0.7 | AA15: =$H15*Inputs!$C$8+$M15-cost_acc-$G15*Inputs!$E$8-cost_fx*Inputs!$D$8-cost_ins -> 4.29 | AB15: =$H15*Inputs!$C$8+$I15*Inputs!$E$8*(1-$B15)+$J15*Inputs!$D$8-cost_acc-$G15*Inputs!$E$8*(1-$B15)-cost_fx*Inputs!$D$8 -> 6.8 | AC15: =Inputs!$B$8*Z15 -> 2800 | AD15: =(Inputs!$B$8-AC15)*(1-MIN(1,Inputs!$G$8*$F15)*churn_nonbuyers) -> 0 | AE15: =12*(AC15*AA15+AD15*AB15) -> 144144 | AF15: =S15+Y15+AE15 -> 830275.2 | AG15: =AF15-fixed -> 130275.2 | AH15: =Q15+R15+W15+X15+AC15+AD15 -> 36160
A16: Per-use churn half the survey | B16: =wd_red -> 0 | C16: =plus_wdf -> 1 | D16: =feat_cost -> 0 | E16: 1 | F16: 0.5 | G16: =cost_wd -> 1 | H16: =ic -> 0.002 | I16: =fee_wd -> 1.5 | J16: =fee_fx -> 0.015 | K16: =pS -> 3.99 | L16: =pE -> 3.99 | M16: =pT -> 6.99 | N16: =IF($K16="",0,MIN(1,$E16*IF($K16=Inputs!$H$6,Inputs!$I$6,IF($K16=Inputs!$J$6,Inputs!$K$6,IF($K16=Inputs!$L$6,Inputs!$M$6,NA()))))) -> 0.08 | O16: =$H16*Inputs!$C$6+$K16+$J16*Inputs!$D$6-cost_acc-$G16*Inputs!$E$6*$C16-cost_fx*Inputs!$D$6-$D16 -> 3.19 | P16: =$H16*Inputs!$C$6+$I16*Inputs!$E$6*(1-$B16)+$J16*Inputs!$D$6-cost_acc-$G16*Inputs!$E$6*(1-$B16)-cost_fx*Inputs!$D$6 -> 0.7 | Q16: =Inputs!$B$6*N16 -> 1920 | R16: =(Inputs!$B$6-Q16)*(1-MIN(1,Inputs!$G$6*$F16)*churn_nonbuyers) -> 21528 | S16: =12*(Q16*O16+R16*P16) -> 254332.8 | T16: =IF($L16="",0,MIN(1,$E16*IF($L16=Inputs!$H$7,Inputs!$I$7,IF($L16=Inputs!$J$7,Inputs!$K$7,IF($L16=Inputs!$L$7,Inputs!$M$7,NA()))))) -> 0.4 | U16: =$H16*Inputs!$C$7+$L16+$J16*Inputs!$D$7-cost_acc-$G16*Inputs!$E$7*$C16-cost_fx*Inputs!$D$7-$D16 -> 3.79 | V16: =$H16*Inputs!$C$7+$I16*Inputs!$E$7*(1-$B16)+$J16*Inputs!$D$7-cost_acc-$G16*Inputs!$E$7*(1-$B16)-cost_fx*Inputs!$D$7 -> 2.8 | W16: =Inputs!$B$7*T16 -> 4800 | X16: =(Inputs!$B$7-W16)*(1-MIN(1,Inputs!$G$7*$F16)*churn_nonbuyers) -> 7092 | Y16: =12*(W16*U16+X16*V16) -> 456595.2 | Z16: =IF($M16="",0,MIN(1,$E16*IF($M16=Inputs!$H$8,Inputs!$I$8,IF($M16=Inputs!$J$8,Inputs!$K$8,IF($M16=Inputs!$L$8,Inputs!$M$8,NA()))))) -> 0.7 | AA16: =$H16*Inputs!$C$8+$M16-cost_acc-$G16*Inputs!$E$8-cost_fx*Inputs!$D$8-cost_ins -> 4.29 | AB16: =$H16*Inputs!$C$8+$I16*Inputs!$E$8*(1-$B16)+$J16*Inputs!$D$8-cost_acc-$G16*Inputs!$E$8*(1-$B16)-cost_fx*Inputs!$D$8 -> 6.8 | AC16: =Inputs!$B$8*Z16 -> 2800 | AD16: =(Inputs!$B$8-AC16)*(1-MIN(1,Inputs!$G$8*$F16)*churn_nonbuyers) -> 780 | AE16: =12*(AC16*AA16+AD16*AB16) -> 207792 | AF16: =S16+Y16+AE16 -> 918720 | AG16: =AF16-fixed -> 218720 | AH16: =Q16+R16+W16+X16+AC16+AD16 -> 38920
A17: WHAT IF · withdrawal cost rises to 1.50, fees unchanged | B17: =wd_red -> 0 | C17: =plus_wdf -> 1 | D17: =feat_cost -> 0 | E17: 1 | F17: 1 | G17: 1.5 | H17: =ic -> 0.002 | I17: =fee_wd -> 1.5 | J17: =fee_fx -> 0.015 | K17: =pS -> 3.99 | L17: =pE -> 3.99 | M17: =pT -> 6.99 | N17: =IF($K17="",0,MIN(1,$E17*IF($K17=Inputs!$H$6,Inputs!$I$6,IF($K17=Inputs!$J$6,Inputs!$K$6,IF($K17=Inputs!$L$6,Inputs!$M$6,NA()))))) -> 0.08 | O17: =$H17*Inputs!$C$6+$K17+$J17*Inputs!$D$6-cost_acc-$G17*Inputs!$E$6*$C17-cost_fx*Inputs!$D$6-$D17 -> 2.69 | P17: =$H17*Inputs!$C$6+$I17*Inputs!$E$6*(1-$B17)+$J17*Inputs!$D$6-cost_acc-$G17*Inputs!$E$6*(1-$B17)-cost_fx*Inputs!$D$6 -> 0.2 | Q17: =Inputs!$B$6*N17 -> 1920 | R17: =(Inputs!$B$6-Q17)*(1-MIN(1,Inputs!$G$6*$F17)*churn_nonbuyers) -> 20976 | S17: =12*(Q17*O17+R17*P17) -> 112320 | T17: =IF($L17="",0,MIN(1,$E17*IF($L17=Inputs!$H$7,Inputs!$I$7,IF($L17=Inputs!$J$7,Inputs!$K$7,IF($L17=Inputs!$L$7,Inputs!$M$7,NA()))))) -> 0.4 | U17: =$H17*Inputs!$C$7+$L17+$J17*Inputs!$D$7-cost_acc-$G17*Inputs!$E$7*$C17-cost_fx*Inputs!$D$7-$D17 -> 2.79 | V17: =$H17*Inputs!$C$7+$I17*Inputs!$E$7*(1-$B17)+$J17*Inputs!$D$7-cost_acc-$G17*Inputs!$E$7*(1-$B17)-cost_fx*Inputs!$D$7 -> 1.8 | W17: =Inputs!$B$7*T17 -> 4800 | X17: =(Inputs!$B$7-W17)*(1-MIN(1,Inputs!$G$7*$F17)*churn_nonbuyers) -> 6984 | Y17: =12*(W17*U17+X17*V17) -> 311558.4 | Z17: =IF($M17="",0,MIN(1,$E17*IF($M17=Inputs!$H$8,Inputs!$I$8,IF($M17=Inputs!$J$8,Inputs!$K$8,IF($M17=Inputs!$L$8,Inputs!$M$8,NA()))))) -> 0.7 | AA17: =$H17*Inputs!$C$8+$M17-cost_acc-$G17*Inputs!$E$8-cost_fx*Inputs!$D$8-cost_ins -> 3.29 | AB17: =$H17*Inputs!$C$8+$I17*Inputs!$E$8*(1-$B17)+$J17*Inputs!$D$8-cost_acc-$G17*Inputs!$E$8*(1-$B17)-cost_fx*Inputs!$D$8 -> 5.8 | AC17: =Inputs!$B$8*Z17 -> 2800 | AD17: =(Inputs!$B$8-AC17)*(1-MIN(1,Inputs!$G$8*$F17)*churn_nonbuyers) -> 360 | AE17: =12*(AC17*AA17+AD17*AB17) -> 135600 | AF17: =S17+Y17+AE17 -> 559478.4 | AG17: =AF17-fixed -> -140521.6 | AH17: =Q17+R17+W17+X17+AC17+AD17 -> 37840
A18: WHAT IF · withdrawal cost 1.50 and fee raised to 2.00 (= Fluxa abroad) | B18: =wd_red -> 0 | C18: =plus_wdf -> 1 | D18: =feat_cost -> 0 | E18: 1 | F18: 1 | G18: 1.5 | H18: =ic -> 0.002 | I18: 2 | J18: =fee_fx -> 0.015 | K18: =pS -> 3.99 | L18: =pE -> 3.99 | M18: =pT -> 6.99 | N18: =IF($K18="",0,MIN(1,$E18*IF($K18=Inputs!$H$6,Inputs!$I$6,IF($K18=Inputs!$J$6,Inputs!$K$6,IF($K18=Inputs!$L$6,Inputs!$M$6,NA()))))) -> 0.08 | O18: =$H18*Inputs!$C$6+$K18+$J18*Inputs!$D$6-cost_acc-$G18*Inputs!$E$6*$C18-cost_fx*Inputs!$D$6-$D18 -> 2.69 | P18: =$H18*Inputs!$C$6+$I18*Inputs!$E$6*(1-$B18)+$J18*Inputs!$D$6-cost_acc-$G18*Inputs!$E$6*(1-$B18)-cost_fx*Inputs!$D$6 -> 0.7 | Q18: =Inputs!$B$6*N18 -> 1920 | R18: =(Inputs!$B$6-Q18)*(1-MIN(1,Inputs!$G$6*$F18)*churn_nonbuyers) -> 20976 | S18: =12*(Q18*O18+R18*P18) -> 238176 | T18: =IF($L18="",0,MIN(1,$E18*IF($L18=Inputs!$H$7,Inputs!$I$7,IF($L18=Inputs!$J$7,Inputs!$K$7,IF($L18=Inputs!$L$7,Inputs!$M$7,NA()))))) -> 0.4 | U18: =$H18*Inputs!$C$7+$L18+$J18*Inputs!$D$7-cost_acc-$G18*Inputs!$E$7*$C18-cost_fx*Inputs!$D$7-$D18 -> 2.79 | V18: =$H18*Inputs!$C$7+$I18*Inputs!$E$7*(1-$B18)+$J18*Inputs!$D$7-cost_acc-$G18*Inputs!$E$7*(1-$B18)-cost_fx*Inputs!$D$7 -> 2.8 | W18: =Inputs!$B$7*T18 -> 4800 | X18: =(Inputs!$B$7-W18)*(1-MIN(1,Inputs!$G$7*$F18)*churn_nonbuyers) -> 6984 | Y18: =12*(W18*U18+X18*V18) -> 395366.4 | Z18: =IF($M18="",0,MIN(1,$E18*IF($M18=Inputs!$H$8,Inputs!$I$8,IF($M18=Inputs!$J$8,Inputs!$K$8,IF($M18=Inputs!$L$8,Inputs!$M$8,NA()))))) -> 0.7 | AA18: =$H18*Inputs!$C$8+$M18-cost_acc-$G18*Inputs!$E$8-cost_fx*Inputs!$D$8-cost_ins -> 3.29 | AB18: =$H18*Inputs!$C$8+$I18*Inputs!$E$8*(1-$B18)+$J18*Inputs!$D$8-cost_acc-$G18*Inputs!$E$8*(1-$B18)-cost_fx*Inputs!$D$8 -> 6.8 | AC18: =Inputs!$B$8*Z18 -> 2800 | AD18: =(Inputs!$B$8-AC18)*(1-MIN(1,Inputs!$G$8*$F18)*churn_nonbuyers) -> 360 | AE18: =12*(AC18*AA18+AD18*AB18) -> 139920 | AF18: =S18+Y18+AE18 -> 773462.4 | AG18: =AF18-fixed -> 73462.4 | AH18: =Q18+R18+W18+X18+AC18+AD18 -> 37840
A19: WHAT IF · EU halves the interchange cap to 0.1% | B19: =wd_red -> 0 | C19: =plus_wdf -> 1 | D19: =feat_cost -> 0 | E19: 1 | F19: 1 | G19: =cost_wd -> 1 | H19: 0.001 | I19: =fee_wd -> 1.5 | J19: =fee_fx -> 0.015 | K19: =pS -> 3.99 | L19: =pE -> 3.99 | M19: =pT -> 6.99 | N19: =IF($K19="",0,MIN(1,$E19*IF($K19=Inputs!$H$6,Inputs!$I$6,IF($K19=Inputs!$J$6,Inputs!$K$6,IF($K19=Inputs!$L$6,Inputs!$M$6,NA()))))) -> 0.08 | O19: =$H19*Inputs!$C$6+$K19+$J19*Inputs!$D$6-cost_acc-$G19*Inputs!$E$6*$C19-cost_fx*Inputs!$D$6-$D19 -> 2.94 | P19: =$H19*Inputs!$C$6+$I19*Inputs!$E$6*(1-$B19)+$J19*Inputs!$D$6-cost_acc-$G19*Inputs!$E$6*(1-$B19)-cost_fx*Inputs!$D$6 -> 0.45 | Q19: =Inputs!$B$6*N19 -> 1920 | R19: =(Inputs!$B$6-Q19)*(1-MIN(1,Inputs!$G$6*$F19)*churn_nonbuyers) -> 20976 | S19: =12*(Q19*O19+R19*P19) -> 181008 | T19: =IF($L19="",0,MIN(1,$E19*IF($L19=Inputs!$H$7,Inputs!$I$7,IF($L19=Inputs!$J$7,Inputs!$K$7,IF($L19=Inputs!$L$7,Inputs!$M$7,NA()))))) -> 0.4 | U19: =$H19*Inputs!$C$7+$L19+$J19*Inputs!$D$7-cost_acc-$G19*Inputs!$E$7*$C19-cost_fx*Inputs!$D$7-$D19 -> 2.89 | V19: =$H19*Inputs!$C$7+$I19*Inputs!$E$7*(1-$B19)+$J19*Inputs!$D$7-cost_acc-$G19*Inputs!$E$7*(1-$B19)-cost_fx*Inputs!$D$7 -> 1.9 | W19: =Inputs!$B$7*T19 -> 4800 | X19: =(Inputs!$B$7-W19)*(1-MIN(1,Inputs!$G$7*$F19)*churn_nonbuyers) -> 6984 | Y19: =12*(W19*U19+X19*V19) -> 325699.2 | Z19: =IF($M19="",0,MIN(1,$E19*IF($M19=Inputs!$H$8,Inputs!$I$8,IF($M19=Inputs!$J$8,Inputs!$K$8,IF($M19=Inputs!$L$8,Inputs!$M$8,NA()))))) -> 0.7 | AA19: =$H19*Inputs!$C$8+$M19-cost_acc-$G19*Inputs!$E$8-cost_fx*Inputs!$D$8-cost_ins -> 3.49 | AB19: =$H19*Inputs!$C$8+$I19*Inputs!$E$8*(1-$B19)+$J19*Inputs!$D$8-cost_acc-$G19*Inputs!$E$8*(1-$B19)-cost_fx*Inputs!$D$8 -> 6 | AC19: =Inputs!$B$8*Z19 -> 2800 | AD19: =(Inputs!$B$8-AC19)*(1-MIN(1,Inputs!$G$8*$F19)*churn_nonbuyers) -> 360 | AE19: =12*(AC19*AA19+AD19*AB19) -> 143184 | AF19: =S19+Y19+AE19 -> 649891.2 | AG19: =AF19-fixed -> -50108.8 | AH19: =Q19+R19+W19+X19+AC19+AD19 -> 37840
A20: WHAT IF · interchange 0.1% and withdrawal fee raised to 2.00 | B20: =wd_red -> 0 | C20: =plus_wdf -> 1 | D20: =feat_cost -> 0 | E20: 1 | F20: 1 | G20: =cost_wd -> 1 | H20: 0.001 | I20: 2 | J20: =fee_fx -> 0.015 | K20: =pS -> 3.99 | L20: =pE -> 3.99 | M20: =pT -> 6.99 | N20: =IF($K20="",0,MIN(1,$E20*IF($K20=Inputs!$H$6,Inputs!$I$6,IF($K20=Inputs!$J$6,Inputs!$K$6,IF($K20=Inputs!$L$6,Inputs!$M$6,NA()))))) -> 0.08 | O20: =$H20*Inputs!$C$6+$K20+$J20*Inputs!$D$6-cost_acc-$G20*Inputs!$E$6*$C20-cost_fx*Inputs!$D$6-$D20 -> 2.94 | P20: =$H20*Inputs!$C$6+$I20*Inputs!$E$6*(1-$B20)+$J20*Inputs!$D$6-cost_acc-$G20*Inputs!$E$6*(1-$B20)-cost_fx*Inputs!$D$6 -> 0.95 | Q20: =Inputs!$B$6*N20 -> 1920 | R20: =(Inputs!$B$6-Q20)*(1-MIN(1,Inputs!$G$6*$F20)*churn_nonbuyers) -> 20976 | S20: =12*(Q20*O20+R20*P20) -> 306864 | T20: =IF($L20="",0,MIN(1,$E20*IF($L20=Inputs!$H$7,Inputs!$I$7,IF($L20=Inputs!$J$7,Inputs!$K$7,IF($L20=Inputs!$L$7,Inputs!$M$7,NA()))))) -> 0.4 | U20: =$H20*Inputs!$C$7+$L20+$J20*Inputs!$D$7-cost_acc-$G20*Inputs!$E$7*$C20-cost_fx*Inputs!$D$7-$D20 -> 2.89 | V20: =$H20*Inputs!$C$7+$I20*Inputs!$E$7*(1-$B20)+$J20*Inputs!$D$7-cost_acc-$G20*Inputs!$E$7*(1-$B20)-cost_fx*Inputs!$D$7 -> 2.9 | W20: =Inputs!$B$7*T20 -> 4800 | X20: =(Inputs!$B$7-W20)*(1-MIN(1,Inputs!$G$7*$F20)*churn_nonbuyers) -> 6984 | Y20: =12*(W20*U20+X20*V20) -> 409507.2 | Z20: =IF($M20="",0,MIN(1,$E20*IF($M20=Inputs!$H$8,Inputs!$I$8,IF($M20=Inputs!$J$8,Inputs!$K$8,IF($M20=Inputs!$L$8,Inputs!$M$8,NA()))))) -> 0.7 | AA20: =$H20*Inputs!$C$8+$M20-cost_acc-$G20*Inputs!$E$8-cost_fx*Inputs!$D$8-cost_ins -> 3.49 | AB20: =$H20*Inputs!$C$8+$I20*Inputs!$E$8*(1-$B20)+$J20*Inputs!$D$8-cost_acc-$G20*Inputs!$E$8*(1-$B20)-cost_fx*Inputs!$D$8 -> 7 | AC20: =Inputs!$B$8*Z20 -> 2800 | AD20: =(Inputs!$B$8-AC20)*(1-MIN(1,Inputs!$G$8*$F20)*churn_nonbuyers) -> 360 | AE20: =12*(AC20*AA20+AD20*AB20) -> 147504 | AF20: =S20+Y20+AE20 -> 863875.2 | AG20: =AF20-fixed -> 163875.2 | AH20: =Q20+R20+W20+X20+AC20+AD20 -> 37840
A21: WHAT IF · Fluxa undercuts: Travel cut to 5.99 | B21: =wd_red -> 0 | C21: =plus_wdf -> 1 | D21: =feat_cost -> 0 | E21: 1 | F21: 1 | G21: =cost_wd -> 1 | H21: =ic -> 0.002 | I21: =fee_wd -> 1.5 | J21: =fee_fx -> 0.015 | K21: =pS -> 3.99 | L21: =pE -> 3.99 | M21: 5.99 | N21: =IF($K21="",0,MIN(1,$E21*IF($K21=Inputs!$H$6,Inputs!$I$6,IF($K21=Inputs!$J$6,Inputs!$K$6,IF($K21=Inputs!$L$6,Inputs!$M$6,NA()))))) -> 0.08 | O21: =$H21*Inputs!$C$6+$K21+$J21*Inputs!$D$6-cost_acc-$G21*Inputs!$E$6*$C21-cost_fx*Inputs!$D$6-$D21 -> 3.19 | P21: =$H21*Inputs!$C$6+$I21*Inputs!$E$6*(1-$B21)+$J21*Inputs!$D$6-cost_acc-$G21*Inputs!$E$6*(1-$B21)-cost_fx*Inputs!$D$6 -> 0.7 | Q21: =Inputs!$B$6*N21 -> 1920 | R21: =(Inputs!$B$6-Q21)*(1-MIN(1,Inputs!$G$6*$F21)*churn_nonbuyers) -> 20976 | S21: =12*(Q21*O21+R21*P21) -> 249696 | T21: =IF($L21="",0,MIN(1,$E21*IF($L21=Inputs!$H$7,Inputs!$I$7,IF($L21=Inputs!$J$7,Inputs!$K$7,IF($L21=Inputs!$L$7,Inputs!$M$7,NA()))))) -> 0.4 | U21: =$H21*Inputs!$C$7+$L21+$J21*Inputs!$D$7-cost_acc-$G21*Inputs!$E$7*$C21-cost_fx*Inputs!$D$7-$D21 -> 3.79 | V21: =$H21*Inputs!$C$7+$I21*Inputs!$E$7*(1-$B21)+$J21*Inputs!$D$7-cost_acc-$G21*Inputs!$E$7*(1-$B21)-cost_fx*Inputs!$D$7 -> 2.8 | W21: =Inputs!$B$7*T21 -> 4800 | X21: =(Inputs!$B$7-W21)*(1-MIN(1,Inputs!$G$7*$F21)*churn_nonbuyers) -> 6984 | Y21: =12*(W21*U21+X21*V21) -> 452966.4 | Z21: =IF($M21="",0,MIN(1,$E21*IF($M21=Inputs!$H$8,Inputs!$I$8,IF($M21=Inputs!$J$8,Inputs!$K$8,IF($M21=Inputs!$L$8,Inputs!$M$8,NA()))))) -> 0.8 | AA21: =$H21*Inputs!$C$8+$M21-cost_acc-$G21*Inputs!$E$8-cost_fx*Inputs!$D$8-cost_ins -> 3.29 | AB21: =$H21*Inputs!$C$8+$I21*Inputs!$E$8*(1-$B21)+$J21*Inputs!$D$8-cost_acc-$G21*Inputs!$E$8*(1-$B21)-cost_fx*Inputs!$D$8 -> 6.8 | AC21: =Inputs!$B$8*Z21 -> 3200 | AD21: =(Inputs!$B$8-AC21)*(1-MIN(1,Inputs!$G$8*$F21)*churn_nonbuyers) -> 240 | AE21: =12*(AC21*AA21+AD21*AB21) -> 145920 | AF21: =S21+Y21+AE21 -> 848582.4 | AG21: =AF21-fixed -> 148582.4 | AH21: =Q21+R21+W21+X21+AC21+AD21 -> 38120
A22: Option · Plus Student 2.99 (student fence) | B22: =wd_red -> 0 | C22: =plus_wdf -> 1 | D22: =feat_cost -> 0 | E22: 1 | F22: 1 | G22: =cost_wd -> 1 | H22: =ic -> 0.002 | I22: =fee_wd -> 1.5 | J22: =fee_fx -> 0.015 | K22: 2.99 | L22: =pE -> 3.99 | M22: =pT -> 6.99 | N22: =IF($K22="",0,MIN(1,$E22*IF($K22=Inputs!$H$6,Inputs!$I$6,IF($K22=Inputs!$J$6,Inputs!$K$6,IF($K22=Inputs!$L$6,Inputs!$M$6,NA()))))) -> 0.15 | O22: =$H22*Inputs!$C$6+$K22+$J22*Inputs!$D$6-cost_acc-$G22*Inputs!$E$6*$C22-cost_fx*Inputs!$D$6-$D22 -> 2.19 | P22: =$H22*Inputs!$C$6+$I22*Inputs!$E$6*(1-$B22)+$J22*Inputs!$D$6-cost_acc-$G22*Inputs!$E$6*(1-$B22)-cost_fx*Inputs!$D$6 -> 0.7 | Q22: =Inputs!$B$6*N22 -> 3600 | R22: =(Inputs!$B$6-Q22)*(1-MIN(1,Inputs!$G$6*$F22)*churn_nonbuyers) -> 19380 | S22: =12*(Q22*O22+R22*P22) -> 257400 | T22: =IF($L22="",0,MIN(1,$E22*IF($L22=Inputs!$H$7,Inputs!$I$7,IF($L22=Inputs!$J$7,Inputs!$K$7,IF($L22=Inputs!$L$7,Inputs!$M$7,NA()))))) -> 0.4 | U22: =$H22*Inputs!$C$7+$L22+$J22*Inputs!$D$7-cost_acc-$G22*Inputs!$E$7*$C22-cost_fx*Inputs!$D$7-$D22 -> 3.79 | V22: =$H22*Inputs!$C$7+$I22*Inputs!$E$7*(1-$B22)+$J22*Inputs!$D$7-cost_acc-$G22*Inputs!$E$7*(1-$B22)-cost_fx*Inputs!$D$7 -> 2.8 | W22: =Inputs!$B$7*T22 -> 4800 | X22: =(Inputs!$B$7-W22)*(1-MIN(1,Inputs!$G$7*$F22)*churn_nonbuyers) -> 6984 | Y22: =12*(W22*U22+X22*V22) -> 452966.4 | Z22: =IF($M22="",0,MIN(1,$E22*IF($M22=Inputs!$H$8,Inputs!$I$8,IF($M22=Inputs!$J$8,Inputs!$K$8,IF($M22=Inputs!$L$8,Inputs!$M$8,NA()))))) -> 0.7 | AA22: =$H22*Inputs!$C$8+$M22-cost_acc-$G22*Inputs!$E$8-cost_fx*Inputs!$D$8-cost_ins -> 4.29 | AB22: =$H22*Inputs!$C$8+$I22*Inputs!$E$8*(1-$B22)+$J22*Inputs!$D$8-cost_acc-$G22*Inputs!$E$8*(1-$B22)-cost_fx*Inputs!$D$8 -> 6.8 | AC22: =Inputs!$B$8*Z22 -> 2800 | AD22: =(Inputs!$B$8-AC22)*(1-MIN(1,Inputs!$G$8*$F22)*churn_nonbuyers) -> 360 | AE22: =12*(AC22*AA22+AD22*AB22) -> 173520 | AF22: =S22+Y22+AE22 -> 883886.4 | AG22: =AF22-fixed -> 183886.4 | AH22: =Q22+R22+W22+X22+AC22+AD22 -> 37924
A23: Option · Plus at 4.99 for everyone | B23: =wd_red -> 0 | C23: =plus_wdf -> 1 | D23: =feat_cost -> 0 | E23: 1 | F23: 1 | G23: =cost_wd -> 1 | H23: =ic -> 0.002 | I23: =fee_wd -> 1.5 | J23: =fee_fx -> 0.015 | K23: 4.99 | L23: 4.99 | M23: =pT -> 6.99 | N23: =IF($K23="",0,MIN(1,$E23*IF($K23=Inputs!$H$6,Inputs!$I$6,IF($K23=Inputs!$J$6,Inputs!$K$6,IF($K23=Inputs!$L$6,Inputs!$M$6,NA()))))) -> 0.04 | O23: =$H23*Inputs!$C$6+$K23+$J23*Inputs!$D$6-cost_acc-$G23*Inputs!$E$6*$C23-cost_fx*Inputs!$D$6-$D23 -> 4.19 | P23: =$H23*Inputs!$C$6+$I23*Inputs!$E$6*(1-$B23)+$J23*Inputs!$D$6-cost_acc-$G23*Inputs!$E$6*(1-$B23)-cost_fx*Inputs!$D$6 -> 0.7 | Q23: =Inputs!$B$6*N23 -> 960 | R23: =(Inputs!$B$6-Q23)*(1-MIN(1,Inputs!$G$6*$F23)*churn_nonbuyers) -> 21888 | S23: =12*(Q23*O23+R23*P23) -> 232128 | T23: =IF($L23="",0,MIN(1,$E23*IF($L23=Inputs!$H$7,Inputs!$I$7,IF($L23=Inputs!$J$7,Inputs!$K$7,IF($L23=Inputs!$L$7,Inputs!$M$7,NA()))))) -> 0.2 | U23: =$H23*Inputs!$C$7+$L23+$J23*Inputs!$D$7-cost_acc-$G23*Inputs!$E$7*$C23-cost_fx*Inputs!$D$7-$D23 -> 4.79 | V23: =$H23*Inputs!$C$7+$I23*Inputs!$E$7*(1-$B23)+$J23*Inputs!$D$7-cost_acc-$G23*Inputs!$E$7*(1-$B23)-cost_fx*Inputs!$D$7 -> 2.8 | W23: =Inputs!$B$7*T23 -> 2400 | X23: =(Inputs!$B$7-W23)*(1-MIN(1,Inputs!$G$7*$F23)*churn_nonbuyers) -> 9312 | Y23: =12*(W23*U23+X23*V23) -> 450835.2 | Z23: =IF($M23="",0,MIN(1,$E23*IF($M23=Inputs!$H$8,Inputs!$I$8,IF($M23=Inputs!$J$8,Inputs!$K$8,IF($M23=Inputs!$L$8,Inputs!$M$8,NA()))))) -> 0.7 | AA23: =$H23*Inputs!$C$8+$M23-cost_acc-$G23*Inputs!$E$8-cost_fx*Inputs!$D$8-cost_ins -> 4.29 | AB23: =$H23*Inputs!$C$8+$I23*Inputs!$E$8*(1-$B23)+$J23*Inputs!$D$8-cost_acc-$G23*Inputs!$E$8*(1-$B23)-cost_fx*Inputs!$D$8 -> 6.8 | AC23: =Inputs!$B$8*Z23 -> 2800 | AD23: =(Inputs!$B$8-AC23)*(1-MIN(1,Inputs!$G$8*$F23)*churn_nonbuyers) -> 360 | AE23: =12*(AC23*AA23+AD23*AB23) -> 173520 | AF23: =S23+Y23+AE23 -> 856483.2 | AG23: =AF23-fixed -> 156483.2 | AH23: =Q23+R23+W23+X23+AC23+AD23 -> 37720
A24: Option · Travel at 8.99 | B24: =wd_red -> 0 | C24: =plus_wdf -> 1 | D24: =feat_cost -> 0 | E24: 1 | F24: 1 | G24: =cost_wd -> 1 | H24: =ic -> 0.002 | I24: =fee_wd -> 1.5 | J24: =fee_fx -> 0.015 | K24: =pS -> 3.99 | L24: =pE -> 3.99 | M24: 8.99 | N24: =IF($K24="",0,MIN(1,$E24*IF($K24=Inputs!$H$6,Inputs!$I$6,IF($K24=Inputs!$J$6,Inputs!$K$6,IF($K24=Inputs!$L$6,Inputs!$M$6,NA()))))) -> 0.08 | O24: =$H24*Inputs!$C$6+$K24+$J24*Inputs!$D$6-cost_acc-$G24*Inputs!$E$6*$C24-cost_fx*Inputs!$D$6-$D24 -> 3.19 | P24: =$H24*Inputs!$C$6+$I24*Inputs!$E$6*(1-$B24)+$J24*Inputs!$D$6-cost_acc-$G24*Inputs!$E$6*(1-$B24)-cost_fx*Inputs!$D$6 -> 0.7 | Q24: =Inputs!$B$6*N24 -> 1920 | R24: =(Inputs!$B$6-Q24)*(1-MIN(1,Inputs!$G$6*$F24)*churn_nonbuyers) -> 20976 | S24: =12*(Q24*O24+R24*P24) -> 249696 | T24: =IF($L24="",0,MIN(1,$E24*IF($L24=Inputs!$H$7,Inputs!$I$7,IF($L24=Inputs!$J$7,Inputs!$K$7,IF($L24=Inputs!$L$7,Inputs!$M$7,NA()))))) -> 0.4 | U24: =$H24*Inputs!$C$7+$L24+$J24*Inputs!$D$7-cost_acc-$G24*Inputs!$E$7*$C24-cost_fx*Inputs!$D$7-$D24 -> 3.79 | V24: =$H24*Inputs!$C$7+$I24*Inputs!$E$7*(1-$B24)+$J24*Inputs!$D$7-cost_acc-$G24*Inputs!$E$7*(1-$B24)-cost_fx*Inputs!$D$7 -> 2.8 | W24: =Inputs!$B$7*T24 -> 4800 | X24: =(Inputs!$B$7-W24)*(1-MIN(1,Inputs!$G$7*$F24)*churn_nonbuyers) -> 6984 | Y24: =12*(W24*U24+X24*V24) -> 452966.4 | Z24: =IF($M24="",0,MIN(1,$E24*IF($M24=Inputs!$H$8,Inputs!$I$8,IF($M24=Inputs!$J$8,Inputs!$K$8,IF($M24=Inputs!$L$8,Inputs!$M$8,NA()))))) -> 0.3 | AA24: =$H24*Inputs!$C$8+$M24-cost_acc-$G24*Inputs!$E$8-cost_fx*Inputs!$D$8-cost_ins -> 6.29 | AB24: =$H24*Inputs!$C$8+$I24*Inputs!$E$8*(1-$B24)+$J24*Inputs!$D$8-cost_acc-$G24*Inputs!$E$8*(1-$B24)-cost_fx*Inputs!$D$8 -> 6.8 | AC24: =Inputs!$B$8*Z24 -> 1200 | AD24: =(Inputs!$B$8-AC24)*(1-MIN(1,Inputs!$G$8*$F24)*churn_nonbuyers) -> 840 | AE24: =12*(AC24*AA24+AD24*AB24) -> 159120 | AF24: =S24+Y24+AE24 -> 861782.4 | AG24: =AF24-fixed -> 161782.4 | AH24: =Q24+R24+W24+X24+AC24+AD24 -> 36720
A25: Option · no Plus plan (Basic + Travel only) | B25: =wd_red -> 0 | C25: =plus_wdf -> 1 | D25: =feat_cost -> 0 | E25: 1 | F25: 1 | G25: =cost_wd -> 1 | H25: =ic -> 0.002 | I25: =fee_wd -> 1.5 | J25: =fee_fx -> 0.015 | M25: =pT -> 6.99 | N25: =IF($K25="",0,MIN(1,$E25*IF($K25=Inputs!$H$6,Inputs!$I$6,IF($K25=Inputs!$J$6,Inputs!$K$6,IF($K25=Inputs!$L$6,Inputs!$M$6,NA()))))) -> 0 | O25: =$H25*Inputs!$C$6+$K25+$J25*Inputs!$D$6-cost_acc-$G25*Inputs!$E$6*$C25-cost_fx*Inputs!$D$6-$D25 -> -0.8 | P25: =$H25*Inputs!$C$6+$I25*Inputs!$E$6*(1-$B25)+$J25*Inputs!$D$6-cost_acc-$G25*Inputs!$E$6*(1-$B25)-cost_fx*Inputs!$D$6 -> 0.7 | Q25: =Inputs!$B$6*N25 -> 0 | R25: =(Inputs!$B$6-Q25)*(1-MIN(1,Inputs!$G$6*$F25)*churn_nonbuyers) -> 22800 | S25: =12*(Q25*O25+R25*P25) -> 191520 | T25: =IF($L25="",0,MIN(1,$E25*IF($L25=Inputs!$H$7,Inputs!$I$7,IF($L25=Inputs!$J$7,Inputs!$K$7,IF($L25=Inputs!$L$7,Inputs!$M$7,NA()))))) -> 0 | U25: =$H25*Inputs!$C$7+$L25+$J25*Inputs!$D$7-cost_acc-$G25*Inputs!$E$7*$C25-cost_fx*Inputs!$D$7-$D25 -> -0.2 | V25: =$H25*Inputs!$C$7+$I25*Inputs!$E$7*(1-$B25)+$J25*Inputs!$D$7-cost_acc-$G25*Inputs!$E$7*(1-$B25)-cost_fx*Inputs!$D$7 -> 2.8 | W25: =Inputs!$B$7*T25 -> 0 | X25: =(Inputs!$B$7-W25)*(1-MIN(1,Inputs!$G$7*$F25)*churn_nonbuyers) -> 11640 | Y25: =12*(W25*U25+X25*V25) -> 391104 | Z25: =IF($M25="",0,MIN(1,$E25*IF($M25=Inputs!$H$8,Inputs!$I$8,IF($M25=Inputs!$J$8,Inputs!$K$8,IF($M25=Inputs!$L$8,Inputs!$M$8,NA()))))) -> 0.7 | AA25: =$H25*Inputs!$C$8+$M25-cost_acc-$G25*Inputs!$E$8-cost_fx*Inputs!$D$8-cost_ins -> 4.29 | AB25: =$H25*Inputs!$C$8+$I25*Inputs!$E$8*(1-$B25)+$J25*Inputs!$D$8-cost_acc-$G25*Inputs!$E$8*(1-$B25)-cost_fx*Inputs!$D$8 -> 6.8 | AC25: =Inputs!$B$8*Z25 -> 2800 | AD25: =(Inputs!$B$8-AC25)*(1-MIN(1,Inputs!$G$8*$F25)*churn_nonbuyers) -> 360 | AE25: =12*(AC25*AA25+AD25*AB25) -> 173520 | AF25: =S25+Y25+AE25 -> 756144 | AG25: =AF25-fixed -> 56144 | AH25: =Q25+R25+W25+X25+AC25+AD25 -> 37600
A26: Combined downside: 50% fewer withdrawals, take-up −20%, features 0.25 | B26: 0.5 | C26: =plus_wdf -> 1 | D26: 0.25 | E26: 0.8 | F26: 1 | G26: =cost_wd -> 1 | H26: =ic -> 0.002 | I26: =fee_wd -> 1.5 | J26: =fee_fx -> 0.015 | K26: =pS -> 3.99 | L26: =pE -> 3.99 | M26: =pT -> 6.99 | N26: =IF($K26="",0,MIN(1,$E26*IF($K26=Inputs!$H$6,Inputs!$I$6,IF($K26=Inputs!$J$6,Inputs!$K$6,IF($K26=Inputs!$L$6,Inputs!$M$6,NA()))))) -> 0.064 | O26: =$H26*Inputs!$C$6+$K26+$J26*Inputs!$D$6-cost_acc-$G26*Inputs!$E$6*$C26-cost_fx*Inputs!$D$6-$D26 -> 2.94 | P26: =$H26*Inputs!$C$6+$I26*Inputs!$E$6*(1-$B26)+$J26*Inputs!$D$6-cost_acc-$G26*Inputs!$E$6*(1-$B26)-cost_fx*Inputs!$D$6 -> 0.45 | Q26: =Inputs!$B$6*N26 -> 1536 | R26: =(Inputs!$B$6-Q26)*(1-MIN(1,Inputs!$G$6*$F26)*churn_nonbuyers) -> 21340.8 | S26: =12*(Q26*O26+R26*P26) -> 169430.4 | T26: =IF($L26="",0,MIN(1,$E26*IF($L26=Inputs!$H$7,Inputs!$I$7,IF($L26=Inputs!$J$7,Inputs!$K$7,IF($L26=Inputs!$L$7,Inputs!$M$7,NA()))))) -> 0.32 | U26: =$H26*Inputs!$C$7+$L26+$J26*Inputs!$D$7-cost_acc-$G26*Inputs!$E$7*$C26-cost_fx*Inputs!$D$7-$D26 -> 3.54 | V26: =$H26*Inputs!$C$7+$I26*Inputs!$E$7*(1-$B26)+$J26*Inputs!$D$7-cost_acc-$G26*Inputs!$E$7*(1-$B26)-cost_fx*Inputs!$D$7 -> 2.3 | W26: =Inputs!$B$7*T26 -> 3840 | X26: =(Inputs!$B$7-W26)*(1-MIN(1,Inputs!$G$7*$F26)*churn_nonbuyers) -> 7915.2 | Y26: =12*(W26*U26+X26*V26) -> 381582.72 | Z26: =IF($M26="",0,MIN(1,$E26*IF($M26=Inputs!$H$8,Inputs!$I$8,IF($M26=Inputs!$J$8,Inputs!$K$8,IF($M26=Inputs!$L$8,Inputs!$M$8,NA()))))) -> 0.56 | AA26: =$H26*Inputs!$C$8+$M26-cost_acc-$G26*Inputs!$E$8-cost_fx*Inputs!$D$8-cost_ins -> 4.29 | AB26: =$H26*Inputs!$C$8+$I26*Inputs!$E$8*(1-$B26)+$J26*Inputs!$D$8-cost_acc-$G26*Inputs!$E$8*(1-$B26)-cost_fx*Inputs!$D$8 -> 6.3 | AC26: =Inputs!$B$8*Z26 -> 2240 | AD26: =(Inputs!$B$8-AC26)*(1-MIN(1,Inputs!$G$8*$F26)*churn_nonbuyers) -> 528 | AE26: =12*(AC26*AA26+AD26*AB26) -> 155232 | AF26: =S26+Y26+AE26 -> 706245.12 | AG26: =AF26-fixed -> 6245.12 | AH26: =Q26+R26+W26+X26+AC26+AD26 -> 37400
A27: Option · Plus at 2.99 for everyone | B27: =wd_red -> 0 | C27: =plus_wdf -> 1 | D27: =feat_cost -> 0 | E27: 1 | F27: 1 | G27: =cost_wd -> 1 | H27: =ic -> 0.002 | I27: =fee_wd -> 1.5 | J27: =fee_fx -> 0.015 | K27: 2.99 | L27: 2.99 | M27: =pT -> 6.99 | N27: =IF($K27="",0,MIN(1,$E27*IF($K27=Inputs!$H$6,Inputs!$I$6,IF($K27=Inputs!$J$6,Inputs!$K$6,IF($K27=Inputs!$L$6,Inputs!$M$6,NA()))))) -> 0.15 | O27: =$H27*Inputs!$C$6+$K27+$J27*Inputs!$D$6-cost_acc-$G27*Inputs!$E$6*$C27-cost_fx*Inputs!$D$6-$D27 -> 2.19 | P27: =$H27*Inputs!$C$6+$I27*Inputs!$E$6*(1-$B27)+$J27*Inputs!$D$6-cost_acc-$G27*Inputs!$E$6*(1-$B27)-cost_fx*Inputs!$D$6 -> 0.7 | Q27: =Inputs!$B$6*N27 -> 3600 | R27: =(Inputs!$B$6-Q27)*(1-MIN(1,Inputs!$G$6*$F27)*churn_nonbuyers) -> 19380 | S27: =12*(Q27*O27+R27*P27) -> 257400 | T27: =IF($L27="",0,MIN(1,$E27*IF($L27=Inputs!$H$7,Inputs!$I$7,IF($L27=Inputs!$J$7,Inputs!$K$7,IF($L27=Inputs!$L$7,Inputs!$M$7,NA()))))) -> 0.5 | U27: =$H27*Inputs!$C$7+$L27+$J27*Inputs!$D$7-cost_acc-$G27*Inputs!$E$7*$C27-cost_fx*Inputs!$D$7-$D27 -> 2.79 | V27: =$H27*Inputs!$C$7+$I27*Inputs!$E$7*(1-$B27)+$J27*Inputs!$D$7-cost_acc-$G27*Inputs!$E$7*(1-$B27)-cost_fx*Inputs!$D$7 -> 2.8 | W27: =Inputs!$B$7*T27 -> 6000 | X27: =(Inputs!$B$7-W27)*(1-MIN(1,Inputs!$G$7*$F27)*churn_nonbuyers) -> 5820 | Y27: =12*(W27*U27+X27*V27) -> 396432 | Z27: =IF($M27="",0,MIN(1,$E27*IF($M27=Inputs!$H$8,Inputs!$I$8,IF($M27=Inputs!$J$8,Inputs!$K$8,IF($M27=Inputs!$L$8,Inputs!$M$8,NA()))))) -> 0.7 | AA27: =$H27*Inputs!$C$8+$M27-cost_acc-$G27*Inputs!$E$8-cost_fx*Inputs!$D$8-cost_ins -> 4.29 | AB27: =$H27*Inputs!$C$8+$I27*Inputs!$E$8*(1-$B27)+$J27*Inputs!$D$8-cost_acc-$G27*Inputs!$E$8*(1-$B27)-cost_fx*Inputs!$D$8 -> 6.8 | AC27: =Inputs!$B$8*Z27 -> 2800 | AD27: =(Inputs!$B$8-AC27)*(1-MIN(1,Inputs!$G$8*$F27)*churn_nonbuyers) -> 360 | AE27: =12*(AC27*AA27+AD27*AB27) -> 173520 | AF27: =S27+Y27+AE27 -> 827352 | AG27: =AF27-fixed -> 127352 | AH27: =Q27+R27+W27+X27+AC27+AD27 -> 37960
A29: Reading: the model is most sensitive to how customers react to the withdrawal fee (each avoided withdrawal costs 0.50 of margin) and to the two external what-ifs (withdrawal cost, interchange cap). Both external shocks are answered by a price move the structure allows: pass a higher withdrawal cost into the withdrawal fee, and raise the plan prices if the interchange cap falls.

Sheet Stress test
A1: Stress test — how far each assumption can move, what happens when the wrong customers buy Plus, and all five uncertainties at once
A2: A · switching values (profit = 0) · B · adverse selection in Plus · C · Monte Carlo simulation of the recommendation and three alternatives on the same random draws. Everything is a live formula; only the random inputs in block C are typed values (seeded, reproducible with novcic_model.py).
A4: A · Switching values: the value of each input at which the 2027 profit is exactly zero (one input at a time)
A5: Input | B5: Base value | C5: Tested value | D5: Profit at base | E5: Profit at tested | F5: Switching value | G5: Change vs base | J5: Reading
A6: Share of withdrawals Basic customers avoid | B6: 0 | C6: 0.5 | D6: =Sensitivity!AG5 -> 176182.4 | E6: =Sensitivity!AG7 -> 69190.4 | F6: =B6+(C6-B6)*D6/(D6-E6) -> 0.8233438 | G6: =IF(B6=0,F6,F6/B6-1) -> 0.8233438 | J6: Withdrawals on Basic may fall by this much before a loss. The largest behavioural unknown.
A7: Plan take-up relative to the survey | B7: 1 | C7: 0.8 | D7: =Sensitivity!AG5 -> 176182.4 | E7: =Sensitivity!AG13 -> 137054.72 | F7: =B7+(C7-B7)*D7/(D7-E7) -> 0.099448779 | G7: =IF(B7=0,F7,F7/B7-1) -> -0.90055122 | J7: Even with almost no plan buyers the per-use fees carry the company to break-even — but only just (B is −19,456).
A8: Withdrawals of a Plus subscriber ÷ segment average | B8: 1 | C8: 2 | D8: =Sensitivity!AG5 -> 176182.4 | E8: =Sensitivity!AG10 -> 37942.4 | F8: =B8+(C8-B8)*D8/(D8-E8) -> 2.2744676 | G8: =IF(B8=0,F8,F8/B8-1) -> 1.2744676 | J8: Above the cap of 3 (= 1.5× for employees) the 1.50 fee applies, so this cannot be reached with the cap in place.
A9: Cost of Plus features per subscriber per month | B9: 0 | C9: 0.5 | D9: =Sensitivity!AG5 -> 176182.4 | E9: =Sensitivity!AG12 -> 135862.4 | F9: =B9+(C9-B9)*D9/(D9-E9) -> 2.1848016 | G9: =IF(B9=0,F9,F9/B9-1) -> 2.1848016 | J9: More than half the Plus price: software features will not cost this.
A10: Cost per cash withdrawal | B10: 1 | C10: 1.5 | D10: =Sensitivity!AG5 -> 176182.4 | E10: =Sensitivity!AG17 -> -140521.6 | F10: =B10+(C10-B10)*D10/(D10-E10) -> 1.2781499 | G10: =IF(B10=0,F10,F10/B10-1) -> 0.27814994 | J10: THE TIGHTEST LIMIT: a 28% cost increase removes the profit if fees stay. Answer: pass it into the fee.
A11: Interchange (share of card payments) | B11: 0.002 | C11: 0.001 | D11: =Sensitivity!AG5 -> 176182.4 | E11: =Sensitivity!AG19 -> -50108.8 | F11: =B11+(C11-B11)*D11/(D11-E11) -> 0.001221435 | G11: =IF(B11=0,F11,F11/B11-1) -> -0.38928248 | J11: A cut of the cap from 0.2% to about 0.12% removes the profit if fees stay.
A12: Per-use churn relative to the survey | B12: 1 | C12: 2 | D12: =Sensitivity!AG5 -> 176182.4 | E12: =Sensitivity!AG15 -> 130275.2 | F12: 9.88 | J12: Typed from novcic_model.py (bisection): not linear, because the travellers' churn is capped at 100%. Churn would have to be ten times the survey.
A13: Profit is linear in each of the other inputs, so the switching value is found by linear extrapolation from two scenario rows of the Sensitivity sheet.
A15: B · Adverse selection: Plus is bought by the heaviest cash users (handout 04: a free service attracts its heaviest users)
A16: Total withdrawals per segment are held constant: if subscribers withdraw more than the average, the customers left on Basic withdraw less.
B17: Students | C17: Employees
A18: Withdrawals per month of a Plus subscriber (cap is 3) | B18: 2 | C18: 3
A19: Segment average (case) | B19: =Inputs!$E$6 -> 1 | C19: =Inputs!$E$7 -> 2
A20: Share who buy Plus (survey, at the Plus price) | B20: =IF(pS="",0,MIN(1,1*IF(pS=Inputs!$H$6,Inputs!$I$6,IF(pS=Inputs!$J$6,Inputs!$K$6,IF(pS=Inputs!$L$6,Inputs!$M$6,NA()))))) -> 0.08 | C20: =IF(pE="",0,MIN(1,1*IF(pE=Inputs!$H$7,Inputs!$I$7,IF(pE=Inputs!$J$7,Inputs!$K$7,IF(pE=Inputs!$L$7,Inputs!$M$7,NA()))))) -> 0.4
A21: Withdrawals per month of a customer left on Basic | B21: =(B19-B20*B18)/(1-B20) -> 0.91304348 | C21: =(C19-C20*C18)/(1-C20) -> 1.3333333
A22: Contribution per Plus subscriber per month | B22: =ic*Inputs!$C$6+pS+fee_fx*Inputs!$D$6-cost_acc-cost_wd*B18-cost_fx*Inputs!$D$6-feat_cost -> 2.19 | C22: =ic*Inputs!$C$7+pE+fee_fx*Inputs!$D$7-cost_acc-cost_wd*C18-cost_fx*Inputs!$D$7-feat_cost -> 2.79
A23: Contribution per Basic customer per month | B23: =ic*Inputs!$C$6+(fee_wd-cost_wd)*B21+fee_fx*Inputs!$D$6-cost_acc-cost_fx*Inputs!$D$6 -> 0.65652174 | C23: =ic*Inputs!$C$7+(fee_wd-cost_wd)*C21+fee_fx*Inputs!$D$7-cost_acc-cost_fx*Inputs!$D$7 -> 2.4666667
A24: Contribution per year | B24: =12*Inputs!$B$6*(B20*B22+(1-B20)*(1-Inputs!$G$6*churn_nonbuyers)*B23) -> 215712 | C24: =12*Inputs!$B$7*(C20*C22+(1-C20)*(1-Inputs!$G$7*churn_nonbuyers)*C23) -> 367430.4
A25: Profit with adverse selection (travellers as in the Model) | B25: =B24+C24+Model!D18-fixed -> 56662.4
A26: Profit in the base case | B26: =reco_profit -> 176182.4
A27: Cost of adverse selection | B27: =B25-B26 -> -119520
A28: Reading: if every Plus subscriber uses the full cap, profit falls by about two thirds but stays positive. Without the cap the exposure would be open-ended — this is the quantified reason for '3 withdrawals included' instead of the survey's 'free withdrawals'.
A30: C · Monte Carlo: five behavioural assumptions drawn together, 5,000 times (triangular distributions, seed 2027)
A31: Uncertain input | B31: Low | C31: Most likely | D31: High | F31: Why this range
A32: Share of Basic withdrawals avoided once a withdrawal costs 1.50 | B32: 0 | C32: 0.2 | D32: 0.6 | F32: People avoid fees they can see: cash-withdrawal fees reduce the number of withdrawals. The case gives no figure; up to 60% fewer is taken as the outer limit.
A33: Plan take-up relative to the stated survey share | B33: 0.6 | C33: 1 | D33: 1.2 | F33: Stated willingness to pay tends to overstate real purchases (hypothetical bias); the upside reflects that Plus becomes more attractive once withdrawals cost 1.50.
A34: Per-use churn relative to the survey | B34: 0.5 | C34: 1 | D34: 2 | F34: Survey intentions to leave: half to double.
A35: Withdrawals of a Plus subscriber relative to the segment average (cap 3) | B35: 1 | C35: 1.1 | D35: 1.5 | F35: Adverse selection up to the cap of 3 withdrawals (1.5 × the employee average).
A36: EUR per Plus subscriber per month for shared accounts and virtual cards | B36: 0 | C36: 0.1 | D36: 0.5 | F36: Shared accounts and virtual cards are software; a small issuing cost per virtual card is possible.
A37: The ranges are judgment, not case facts. Every range except the survey's own upside is skewed against the recommendation, so the base case is close to the best case of the simulation.
A39: Structure (profit after fixed costs) | B39: Mean | C39: 5th percentile | D39: 25th | E39: Median | F39: 75th | G39: 95th | H39: Probability of a loss | I39: Worst draw | J39: Base case (no uncertainty)
A40: E · Recommended: Basic + Plus + Travel | B40: =AVERAGE($J$66:$J$5065) -> 51007.901 | C40: =PERCENTILE($J$66:$J$5065,0.05) -> -27704.55 | D40: =PERCENTILE($J$66:$J$5065,0.25) -> 19954.343 | E40: =PERCENTILE($J$66:$J$5065,0.5) -> 52915.517 | F40: =PERCENTILE($J$66:$J$5065,0.75) -> 83908.163 | G40: =PERCENTILE($J$66:$J$5065,0.95) -> 122471.61 | H40: =COUNTIF($J$66:$J$5065,"<0")/COUNT($J$66:$J$5065) -> 0.1382 | I40: =MIN($J$66:$J$5065) -> -119634.54 | J40: =reco_profit -> 176182.4
A41: D · Basic + Travel only | B41: =AVERAGE($N$66:$N$5065) -> -37626.213 | C41: =PERCENTILE($N$66:$N$5065,0.05) -> -113519.94 | D41: =PERCENTILE($N$66:$N$5065,0.25) -> -67963.606 | E41: =PERCENTILE($N$66:$N$5065,0.5) -> -36172.581 | F41: =PERCENTILE($N$66:$N$5065,0.75) -> -4891.4206 | G41: =PERCENTILE($N$66:$N$5065,0.95) -> 33486.728 | H41: =COUNTIF($N$66:$N$5065,"<0")/COUNT($N$66:$N$5065) -> 0.7784 | I41: =MIN($N$66:$N$5065) -> -185130.16 | J41: =Alternatives!F8 -> 56144
A42: B · Fees per use only | B42: =AVERAGE($O$66:$O$5065) -> -128073.55 | C42: =PERCENTILE($O$66:$O$5065,0.05) -> -237382.73 | D42: =PERCENTILE($O$66:$O$5065,0.25) -> -181701 | E42: =PERCENTILE($O$66:$O$5065,0.5) -> -131324.35 | F42: =PERCENTILE($O$66:$O$5065,0.75) -> -75696.71 | G42: =PERCENTILE($O$66:$O$5065,0.95) -> -12651.037 | H42: =COUNTIF($O$66:$O$5065,"<0")/COUNT($O$66:$O$5065) -> 0.967 | I42: =MIN($O$66:$O$5065) -> -290759.47 | J42: =Alternatives!F6 -> -19456
A43: C · One monthly fee (Inputs), everything included | B43: =AVERAGE($P$66:$P$5065) -> -99969.034 | C43: =PERCENTILE($P$66:$P$5065,0.05) -> -401993.86 | D43: =PERCENTILE($P$66:$P$5065,0.25) -> -221260.82 | E43: =PERCENTILE($P$66:$P$5065,0.5) -> -86253.785 | F43: =PERCENTILE($P$66:$P$5065,0.75) -> 24251.26 | G43: =PERCENTILE($P$66:$P$5065,0.95) -> 154240.61 | H43: =COUNTIF($P$66:$P$5065,"<0")/COUNT($P$66:$P$5065) -> 0.6946 | I43: =MIN($P$66:$P$5065) -> -510437.81 | J43: =Alternatives!F7 -> 70472
A44: Share of draws in which the recommendation earns more than the one-fee alternative | B44: =SUMPRODUCT(--($J$66:$J$5065>$P$66:$P$5065))/COUNT($J$66:$J$5065) -> 0.8512
A45: For the one-fee alternative the churn factor scales the monthly-fee churn (55 / 25 / 10%, capped at 100%) and the Plus-use factor scales everybody's withdrawals, because they are then free for all.
A47: Distribution of the recommended structure's profit (number of draws per band)
A48: Band from | B48: to | C48: Draws | D48: Share
A49: -125000 | B49: -100000 | C49: =COUNTIFS($J$66:$J$5065,">="&A49,$J$66:$J$5065,"<"&B49) -> 4 | D49: =C49/COUNT($J$66:$J$5065) -> 0.0008 | G49: Survey share at the current plan price
A50: -100000 | B50: -75000 | C50: =COUNTIFS($J$66:$J$5065,">="&A50,$J$66:$J$5065,"<"&B50) -> 24 | D50: =C50/COUNT($J$66:$J$5065) -> 0.0048 | G50: Students | H50: =IF(pS="",0,MIN(1,1*IF(pS=Inputs!$H$6,Inputs!$I$6,IF(pS=Inputs!$J$6,Inputs!$K$6,IF(pS=Inputs!$L$6,Inputs!$M$6,NA()))))) -> 0.08
A51: -75000 | B51: -50000 | C51: =COUNTIFS($J$66:$J$5065,">="&A51,$J$66:$J$5065,"<"&B51) -> 67 | D51: =C51/COUNT($J$66:$J$5065) -> 0.0134 | G51: Employees | H51: =IF(pE="",0,MIN(1,1*IF(pE=Inputs!$H$7,Inputs!$I$7,IF(pE=Inputs!$J$7,Inputs!$K$7,IF(pE=Inputs!$L$7,Inputs!$M$7,NA()))))) -> 0.4
A52: -50000 | B52: -25000 | C52: =COUNTIFS($J$66:$J$5065,">="&A52,$J$66:$J$5065,"<"&B52) -> 178 | D52: =C52/COUNT($J$66:$J$5065) -> 0.0356 | G52: Travellers | H52: =IF(pT="",0,MIN(1,1*IF(pT=Inputs!$H$8,Inputs!$I$8,IF(pT=Inputs!$J$8,Inputs!$K$8,IF(pT=Inputs!$L$8,Inputs!$M$8,NA()))))) -> 0.7
A53: -25000 | B53: 0 | C53: =COUNTIFS($J$66:$J$5065,">="&A53,$J$66:$J$5065,"<"&B53) -> 418 | D53: =C53/COUNT($J$66:$J$5065) -> 0.0836
A54: 0 | B54: 25000 | C54: =COUNTIFS($J$66:$J$5065,">="&A54,$J$66:$J$5065,"<"&B54) -> 715 | D54: =C54/COUNT($J$66:$J$5065) -> 0.143
A55: 25000 | B55: 50000 | C55: =COUNTIFS($J$66:$J$5065,">="&A55,$J$66:$J$5065,"<"&B55) -> 972 | D55: =C55/COUNT($J$66:$J$5065) -> 0.1944
A56: 50000 | B56: 75000 | C56: =COUNTIFS($J$66:$J$5065,">="&A56,$J$66:$J$5065,"<"&B56) -> 1040 | D56: =C56/COUNT($J$66:$J$5065) -> 0.208
A57: 75000 | B57: 100000 | C57: =COUNTIFS($J$66:$J$5065,">="&A57,$J$66:$J$5065,"<"&B57) -> 855 | D57: =C57/COUNT($J$66:$J$5065) -> 0.171
A58: 100000 | B58: 125000 | C58: =COUNTIFS($J$66:$J$5065,">="&A58,$J$66:$J$5065,"<"&B58) -> 512 | D58: =C58/COUNT($J$66:$J$5065) -> 0.1024
A59: 125000 | B59: 150000 | C59: =COUNTIFS($J$66:$J$5065,">="&A59,$J$66:$J$5065,"<"&B59) -> 179 | D59: =C59/COUNT($J$66:$J$5065) -> 0.0358
A60: 150000 | B60: 175000 | C60: =COUNTIFS($J$66:$J$5065,">="&A60,$J$66:$J$5065,"<"&B60) -> 35 | D60: =C60/COUNT($J$66:$J$5065) -> 0.007
A61: 175000 | B61: 200000 | C61: =COUNTIFS($J$66:$J$5065,">="&A61,$J$66:$J$5065,"<"&B61) -> 1 | D61: =C61/COUNT($J$66:$J$5065) -> 0.0002
A65: Draw | B65: Withdrawals avoided | C65: Take-up × factor | D65: Churn × factor | E65: Plus use × factor | F65: Plus feature cost | G65: Students (E) | H65: Employees (E) | I65: Travellers (E) | J65: PROFIT E · recommended | K65: Students, no plan | L65: Employees, no plan | M65: Travellers, no plan | N65: PROFIT D · Basic + Travel | O65: PROFIT B · per use only | P65: PROFIT C · one fee
A66: 1 | B66: 0.114017 | C66: 0.933725 | D66: 0.600863 | E66: 1.131892 | F66: 0.155351 | G66: =12*Inputs!$B$6*(MIN(1,$H$50*$C66)*(ic*Inputs!$C$6+pS+fee_fx*Inputs!$D$6-cost_acc-cost_wd*Inputs!$E$6*$E66-cost_fx*Inputs!$D$6-$F66)+(1-MIN(1,$H$50*$C66))*(1-MIN(1,Inputs!$G$6*$D66)*churn_nonbuyers)*(ic*Inputs!$C$6+fee_wd*Inputs!$E$6*(1-$B66)+fee_fx*Inputs!$D$6-cost_acc-cost_wd*Inputs!$E$6*(1-$B66)-cost_fx*Inputs!$D$6)) -> 228648.08 | H66: =12*Inputs!$B$7*(MIN(1,$H$51*$C66)*(ic*Inputs!$C$7+pE+fee_fx*Inputs!$D$7-cost_acc-cost_wd*Inputs!$E$7*$E66-cost_fx*Inputs!$D$7-$F66)+(1-MIN(1,$H$51*$C66))*(1-MIN(1,Inputs!$G$7*$D66)*churn_nonbuyers)*(ic*Inputs!$C$7+fee_wd*Inputs!$E$7*(1-$B66)+fee_fx*Inputs!$D$7-cost_acc-cost_wd*Inputs!$E$7*(1-$B66)-cost_fx*Inputs!$D$7)) -> 419248.18 | I66: =12*Inputs!$B$8*(MIN(1,$H$52*$C66)*(ic*Inputs!$C$8+pT-cost_acc-cost_wd*Inputs!$E$8-cost_fx*Inputs!$D$8-cost_ins)+(1-MIN(1,$H$52*$C66))*(1-MIN(1,Inputs!$G$8*$D66)*churn_nonbuyers)*(ic*Inputs!$C$8+fee_wd*Inputs!$E$8*(1-$B66)+fee_fx*Inputs!$D$8-cost_acc-cost_wd*Inputs!$E$8*(1-$B66)-cost_fx*Inputs!$D$8)) -> 199000.43 | J66: =G66+H66+I66-fixed -> 146896.69 | K66: =12*Inputs!$B$6*(1-MIN(1,Inputs!$G$6*$D66)*churn_nonbuyers)*(ic*Inputs!$C$6+fee_wd*Inputs!$E$6*(1-$B66)+fee_fx*Inputs!$D$6-cost_acc-cost_wd*Inputs!$E$6*(1-$B66)-cost_fx*Inputs!$D$6) -> 179618.11 | L66: =12*Inputs!$B$7*(1-MIN(1,Inputs!$G$7*$D66)*churn_nonbuyers)*(ic*Inputs!$C$7+fee_wd*Inputs!$E$7*(1-$B66)+fee_fx*Inputs!$D$7-cost_acc-cost_wd*Inputs!$E$7*(1-$B66)-cost_fx*Inputs!$D$7) -> 379809.47 | M66: =12*Inputs!$B$8*(1-MIN(1,Inputs!$G$8*$D66)*churn_nonbuyers)*(ic*Inputs!$C$8+fee_wd*Inputs!$E$8*(1-$B66)+fee_fx*Inputs!$D$8-cost_acc-cost_wd*Inputs!$E$8*(1-$B66)-cost_fx*Inputs!$D$8) -> 185943.89 | N66: =K66+L66+I66-fixed -> 58428.012 | O66: =K66+L66+M66-fixed -> 45371.48 | P66: =12*Inputs!$B$6*(1-MIN(1,Inputs!$F$6*$D66))*(ic*Inputs!$C$6+flat_fee-cost_acc-cost_wd*Inputs!$E$6*$E66-cost_fx*Inputs!$D$6)+12*Inputs!$B$7*(1-MIN(1,Inputs!$F$7*$D66))*(ic*Inputs!$C$7+flat_fee-cost_acc-cost_wd*Inputs!$E$7*$E66-cost_fx*Inputs!$D$7)+12*Inputs!$B$8*(1-MIN(1,Inputs!$F$8*$D66))*(ic*Inputs!$C$8+flat_fee-cost_acc-cost_wd*Inputs!$E$8*$E66-cost_fx*Inputs!$D$8)-fixed -> 225944.87
A67: 2 | B67: 0.448487 | C67: 0.809855 | D67: 0.86749 | E67: 1.215513 | F67: 0.119653 | G67: =12*Inputs!$B$6*(MIN(1,$H$50*$C67)*(ic*Inputs!$C$6+pS+fee_fx*Inputs!$D$6-cost_acc-cost_wd*Inputs!$E$6*$E67-cost_fx*Inputs!$D$6-$F67)+(1-MIN(1,$H$50*$C67))*(1-MIN(1,Inputs!$G$6*$D67)*churn_nonbuyers)*(ic*Inputs!$C$6+fee_wd*Inputs!$E$6*(1-$B67)+fee_fx*Inputs!$D$6-cost_acc-cost_wd*Inputs!$E$6*(1-$B67)-cost_fx*Inputs!$D$6)) -> 175851.18 | H67: =12*Inputs!$B$7*(MIN(1,$H$51*$C67)*(ic*Inputs!$C$7+pE+fee_fx*Inputs!$D$7-cost_acc-cost_wd*Inputs!$E$7*$E67-cost_fx*Inputs!$D$7-$F67)+(1-MIN(1,$H$51*$C67))*(1-MIN(1,Inputs!$G$7*$D67)*churn_nonbuyers)*(ic*Inputs!$C$7+fee_wd*Inputs!$E$7*(1-$B67)+fee_fx*Inputs!$D$7-cost_acc-cost_wd*Inputs!$E$7*(1-$B67)-cost_fx*Inputs!$D$7)) -> 374074.31 | I67: =12*Inputs!$B$8*(MIN(1,$H$52*$C67)*(ic*Inputs!$C$8+pT-cost_acc-cost_wd*Inputs!$E$8-cost_fx*Inputs!$D$8-cost_ins)+(1-MIN(1,$H$52*$C67))*(1-MIN(1,Inputs!$G$8*$D67)*churn_nonbuyers)*(ic*Inputs!$C$8+fee_wd*Inputs!$E$8*(1-$B67)+fee_fx*Inputs!$D$8-cost_acc-cost_wd*Inputs!$E$8*(1-$B67)-cost_fx*Inputs!$D$8)) -> 168595.68 | J67: =G67+H67+I67-fixed -> 18521.179 | K67: =12*Inputs!$B$6*(1-MIN(1,Inputs!$G$6*$D67)*churn_nonbuyers)*(ic*Inputs!$C$6+fee_wd*Inputs!$E$6*(1-$B67)+fee_fx*Inputs!$D$6-cost_acc-cost_wd*Inputs!$E$6*(1-$B67)-cost_fx*Inputs!$D$6) -> 131074.79 | L67: =12*Inputs!$B$7*(1-MIN(1,Inputs!$G$7*$D67)*churn_nonbuyers)*(ic*Inputs!$C$7+fee_wd*Inputs!$E$7*(1-$B67)+fee_fx*Inputs!$D$7-cost_acc-cost_wd*Inputs!$E$7*(1-$B67)-cost_fx*Inputs!$D$7) -> 329805.44 | M67: =12*Inputs!$B$8*(1-MIN(1,Inputs!$G$8*$D67)*churn_nonbuyers)*(ic*Inputs!$C$8+fee_wd*Inputs!$E$8*(1-$B67)+fee_fx*Inputs!$D$8-cost_acc-cost_wd*Inputs!$E$8*(1-$B67)-cost_fx*Inputs!$D$8) -> 119740.86 | N67: =K67+L67+I67-fixed -> -70524.082 | O67: =K67+L67+M67-fixed -> -119378.91 | P67: =12*Inputs!$B$6*(1-MIN(1,Inputs!$F$6*$D67))*(ic*Inputs!$C$6+flat_fee-cost_acc-cost_wd*Inputs!$E$6*$E67-cost_fx*Inputs!$D$6)+12*Inputs!$B$7*(1-MIN(1,Inputs!$F$7*$D67))*(ic*Inputs!$C$7+flat_fee-cost_acc-cost_wd*Inputs!$E$7*$E67-cost_fx*Inputs!$D$7)+12*Inputs!$B$8*(1-MIN(1,Inputs!$F$8*$D67))*(ic*Inputs!$C$8+flat_fee-cost_acc-cost_wd*Inputs!$E$8*$E67-cost_fx*Inputs!$D$8)-fixed -> 45242.653
A68: 3 | B68: 0.325822 | C68: 0.735606 | D68: 1.286088 | E68: 1.126413 | F68: 0.113919 | G68: =12*Inputs!$B$6*(MIN(1,$H$50*$C68)*(ic*Inputs!$C$6+pS+fee_fx*Inputs!$D$6-cost_acc-cost_wd*Inputs!$E$6*$E68-cost_fx*Inputs!$D$6-$F68)+(1-MIN(1,$H$50*$C68))*(1-MIN(1,Inputs!$G$6*$D68)*churn_nonbuyers)*(ic*Inputs!$C$6+fee_wd*Inputs!$E$6*(1-$B68)+fee_fx*Inputs!$D$6-cost_acc-cost_wd*Inputs!$E$6*(1-$B68)-cost_fx*Inputs!$D$6)) -> 186209.53 | H68: =12*Inputs!$B$7*(MIN(1,$H$51*$C68)*(ic*Inputs!$C$7+pE+fee_fx*Inputs!$D$7-cost_acc-cost_wd*Inputs!$E$7*$E68-cost_fx*Inputs!$D$7-$F68)+(1-MIN(1,$H$51*$C68))*(1-MIN(1,Inputs!$G$7*$D68)*churn_nonbuyers)*(ic*Inputs!$C$7+fee_wd*Inputs!$E$7*(1-$B68)+fee_fx*Inputs!$D$7-cost_acc-cost_wd*Inputs!$E$7*(1-$B68)-cost_fx*Inputs!$D$7)) -> 386793.34 | I68: =12*Inputs!$B$8*(MIN(1,$H$52*$C68)*(ic*Inputs!$C$8+pT-cost_acc-cost_wd*Inputs!$E$8-cost_fx*Inputs!$D$8-cost_ins)+(1-MIN(1,$H$52*$C68))*(1-MIN(1,Inputs!$G$8*$D68)*churn_nonbuyers)*(ic*Inputs!$C$8+fee_wd*Inputs!$E$8*(1-$B68)+fee_fx*Inputs!$D$8-cost_acc-cost_wd*Inputs!$E$8*(1-$B68)-cost_fx*Inputs!$D$8)) -> 121068 | J68: =G68+H68+I68-fixed -> -5929.1288 | K68: =12*Inputs!$B$6*(1-MIN(1,Inputs!$G$6*$D68)*churn_nonbuyers)*(ic*Inputs!$C$6+fee_wd*Inputs!$E$6*(1-$B68)+fee_fx*Inputs!$D$6-cost_acc-cost_wd*Inputs!$E$6*(1-$B68)-cost_fx*Inputs!$D$6) -> 144734.92 | L68: =12*Inputs!$B$7*(1-MIN(1,Inputs!$G$7*$D68)*churn_nonbuyers)*(ic*Inputs!$C$7+fee_wd*Inputs!$E$7*(1-$B68)+fee_fx*Inputs!$D$7-cost_acc-cost_wd*Inputs!$E$7*(1-$B68)-cost_fx*Inputs!$D$7) -> 342535.35 | M68: =12*Inputs!$B$8*(1-MIN(1,Inputs!$G$8*$D68)*churn_nonbuyers)*(ic*Inputs!$C$8+fee_wd*Inputs!$E$8*(1-$B68)+fee_fx*Inputs!$D$8-cost_acc-cost_wd*Inputs!$E$8*(1-$B68)-cost_fx*Inputs!$D$8) -> 30994.759 | N68: =K68+L68+I68-fixed -> -91661.732 | O68: =K68+L68+M68-fixed -> -181734.97 | P68: =12*Inputs!$B$6*(1-MIN(1,Inputs!$F$6*$D68))*(ic*Inputs!$C$6+flat_fee-cost_acc-cost_wd*Inputs!$E$6*$E68-cost_fx*Inputs!$D$6)+12*Inputs!$B$7*(1-MIN(1,Inputs!$F$7*$D68))*(ic*Inputs!$C$7+flat_fee-cost_acc-cost_wd*Inputs!$E$7*$E68-cost_fx*Inputs!$D$7)+12*Inputs!$B$8*(1-MIN(1,Inputs!$F$8*$D68))*(ic*Inputs!$C$8+flat_fee-cost_acc-cost_wd*Inputs!$E$8*$E68-cost_fx*Inputs!$D$8)-fixed -> -136791.79
A69: 4 | B69: 0.355688 | C69: 1.112472 | D69: 1.537557 | E69: 1.160969 | F69: 0.107187 | G69: =12*Inputs!$B$6*(MIN(1,$H$50*$C69)*(ic*Inputs!$C$6+pS+fee_fx*Inputs!$D$6-cost_acc-cost_wd*Inputs!$E$6*$E69-cost_fx*Inputs!$D$6-$F69)+(1-MIN(1,$H$50*$C69))*(1-MIN(1,Inputs!$G$6*$D69)*churn_nonbuyers)*(ic*Inputs!$C$6+fee_wd*Inputs!$E$6*(1-$B69)+fee_fx*Inputs!$D$6-cost_acc-cost_wd*Inputs!$E$6*(1-$B69)-cost_fx*Inputs!$D$6)) -> 201356.12 | H69: =12*Inputs!$B$7*(MIN(1,$H$51*$C69)*(ic*Inputs!$C$7+pE+fee_fx*Inputs!$D$7-cost_acc-cost_wd*Inputs!$E$7*$E69-cost_fx*Inputs!$D$7-$F69)+(1-MIN(1,$H$51*$C69))*(1-MIN(1,Inputs!$G$7*$D69)*churn_nonbuyers)*(ic*Inputs!$C$7+fee_wd*Inputs!$E$7*(1-$B69)+fee_fx*Inputs!$D$7-cost_acc-cost_wd*Inputs!$E$7*(1-$B69)-cost_fx*Inputs!$D$7)) -> 401701.8 | I69: =12*Inputs!$B$8*(MIN(1,$H$52*$C69)*(ic*Inputs!$C$8+pT-cost_acc-cost_wd*Inputs!$E$8-cost_fx*Inputs!$D$8-cost_ins)+(1-MIN(1,$H$52*$C69))*(1-MIN(1,Inputs!$G$8*$D69)*churn_nonbuyers)*(ic*Inputs!$C$8+fee_wd*Inputs!$E$8*(1-$B69)+fee_fx*Inputs!$D$8-cost_acc-cost_wd*Inputs!$E$8*(1-$B69)-cost_fx*Inputs!$D$8)) -> 160356.16 | J69: =G69+H69+I69-fixed -> 63414.083 | K69: =12*Inputs!$B$6*(1-MIN(1,Inputs!$G$6*$D69)*churn_nonbuyers)*(ic*Inputs!$C$6+fee_wd*Inputs!$E$6*(1-$B69)+fee_fx*Inputs!$D$6-cost_acc-cost_wd*Inputs!$E$6*(1-$B69)-cost_fx*Inputs!$D$6) -> 138819.97 | L69: =12*Inputs!$B$7*(1-MIN(1,Inputs!$G$7*$D69)*churn_nonbuyers)*(ic*Inputs!$C$7+fee_wd*Inputs!$E$7*(1-$B69)+fee_fx*Inputs!$D$7-cost_acc-cost_wd*Inputs!$E$7*(1-$B69)-cost_fx*Inputs!$D$7) -> 335745.21 | M69: =12*Inputs!$B$8*(1-MIN(1,Inputs!$G$8*$D69)*churn_nonbuyers)*(ic*Inputs!$C$8+fee_wd*Inputs!$E$8*(1-$B69)+fee_fx*Inputs!$D$8-cost_acc-cost_wd*Inputs!$E$8*(1-$B69)-cost_fx*Inputs!$D$8) -> 0 | N69: =K69+L69+I69-fixed -> -65078.665 | O69: =K69+L69+M69-fixed -> -225434.83 | P69: =12*Inputs!$B$6*(1-MIN(1,Inputs!$F$6*$D69))*(ic*Inputs!$C$6+flat_fee-cost_acc-cost_wd*Inputs!$E$6*$E69-cost_fx*Inputs!$D$6)+12*Inputs!$B$7*(1-MIN(1,Inputs!$F$7*$D69))*(ic*Inputs!$C$7+flat_fee-cost_acc-cost_wd*Inputs!$E$7*$E69-cost_fx*Inputs!$D$7)+12*Inputs!$B$8*(1-MIN(1,Inputs!$F$8*$D69))*(ic*Inputs!$C$8+flat_fee-cost_acc-cost_wd*Inputs!$E$8*$E69-cost_fx*Inputs!$D$8)-fixed -> -281442.85
A70: 5 | B70: 0.347367 | C70: 0.884644 | D70: 1.009641 | E70: 1.1049 | F70: 0.169502 | G70: =12*Inputs!$B$6*(MIN(1,$H$50*$C70)*(ic*Inputs!$C$6+pS+fee_fx*Inputs!$D$6-cost_acc-cost_wd*Inputs!$E$6*$E70-cost_fx*Inputs!$D$6-$F70)+(1-MIN(1,$H$50*$C70))*(1-MIN(1,Inputs!$G$6*$D70)*churn_nonbuyers)*(ic*Inputs!$C$6+fee_wd*Inputs!$E$6*(1-$B70)+fee_fx*Inputs!$D$6-cost_acc-cost_wd*Inputs!$E$6*(1-$B70)-cost_fx*Inputs!$D$6)) -> 193167.48 | H70: =12*Inputs!$B$7*(MIN(1,$H$51*$C70)*(ic*Inputs!$C$7+pE+fee_fx*Inputs!$D$7-cost_acc-cost_wd*Inputs!$E$7*$E70-cost_fx*Inputs!$D$7-$F70)+(1-MIN(1,$H$51*$C70))*(1-MIN(1,Inputs!$G$7*$D70)*churn_nonbuyers)*(ic*Inputs!$C$7+fee_wd*Inputs!$E$7*(1-$B70)+fee_fx*Inputs!$D$7-cost_acc-cost_wd*Inputs!$E$7*(1-$B70)-cost_fx*Inputs!$D$7)) -> 395085.7 | I70: =12*Inputs!$B$8*(MIN(1,$H$52*$C70)*(ic*Inputs!$C$8+pT-cost_acc-cost_wd*Inputs!$E$8-cost_fx*Inputs!$D$8-cost_ins)+(1-MIN(1,$H$52*$C70))*(1-MIN(1,Inputs!$G$8*$D70)*churn_nonbuyers)*(ic*Inputs!$C$8+fee_wd*Inputs!$E$8*(1-$B70)+fee_fx*Inputs!$D$8-cost_acc-cost_wd*Inputs!$E$8*(1-$B70)-cost_fx*Inputs!$D$8)) -> 162098.69 | J70: =G70+H70+I70-fixed -> 50351.868 | K70: =12*Inputs!$B$6*(1-MIN(1,Inputs!$G$6*$D70)*churn_nonbuyers)*(ic*Inputs!$C$6+fee_wd*Inputs!$E$6*(1-$B70)+fee_fx*Inputs!$D$6-cost_acc-cost_wd*Inputs!$E$6*(1-$B70)-cost_fx*Inputs!$D$6) -> 143927.13 | L70: =12*Inputs!$B$7*(1-MIN(1,Inputs!$G$7*$D70)*churn_nonbuyers)*(ic*Inputs!$C$7+fee_wd*Inputs!$E$7*(1-$B70)+fee_fx*Inputs!$D$7-cost_acc-cost_wd*Inputs!$E$7*(1-$B70)-cost_fx*Inputs!$D$7) -> 342481.63 | M70: =12*Inputs!$B$8*(1-MIN(1,Inputs!$G$8*$D70)*churn_nonbuyers)*(ic*Inputs!$C$8+fee_wd*Inputs!$E$8*(1-$B70)+fee_fx*Inputs!$D$8-cost_acc-cost_wd*Inputs!$E$8*(1-$B70)-cost_fx*Inputs!$D$8) -> 90827.665 | N70: =K70+L70+I70-fixed -> -51492.561 | O70: =K70+L70+M70-fixed -> -122763.58 | P70: =12*Inputs!$B$6*(1-MIN(1,Inputs!$F$6*$D70))*(ic*Inputs!$C$6+flat_fee-cost_acc-cost_wd*Inputs!$E$6*$E70-cost_fx*Inputs!$D$6)+12*Inputs!$B$7*(1-MIN(1,Inputs!$F$7*$D70))*(ic*Inputs!$C$7+flat_fee-cost_acc-cost_wd*Inputs!$E$7*$E70-cost_fx*Inputs!$D$7)+12*Inputs!$B$8*(1-MIN(1,Inputs!$F$8*$D70))*(ic*Inputs!$C$8+flat_fee-cost_acc-cost_wd*Inputs!$E$8*$E70-cost_fx*Inputs!$D$8)-fixed -> 19961.092
A71: 6 | B71: 0.140291 | C71: 1.041769 | D71: 1.03088 | E71: 1.270524 | F71: 0.129913 | G71: =12*Inputs!$B$6*(MIN(1,$H$50*$C71)*(ic*Inputs!$C$6+pS+fee_fx*Inputs!$D$6-cost_acc-cost_wd*Inputs!$E$6*$E71-cost_fx*Inputs!$D$6-$F71)+(1-MIN(1,$H$50*$C71))*(1-MIN(1,Inputs!$G$6*$D71)*churn_nonbuyers)*(ic*Inputs!$C$6+fee_wd*Inputs!$E$6*(1-$B71)+fee_fx*Inputs!$D$6-cost_acc-cost_wd*Inputs!$E$6*(1-$B71)-cost_fx*Inputs!$D$6)) -> 224665.45 | H71: =12*Inputs!$B$7*(MIN(1,$H$51*$C71)*(ic*Inputs!$C$7+pE+fee_fx*Inputs!$D$7-cost_acc-cost_wd*Inputs!$E$7*$E71-cost_fx*Inputs!$D$7-$F71)+(1-MIN(1,$H$51*$C71))*(1-MIN(1,Inputs!$G$7*$D71)*churn_nonbuyers)*(ic*Inputs!$C$7+fee_wd*Inputs!$E$7*(1-$B71)+fee_fx*Inputs!$D$7-cost_acc-cost_wd*Inputs!$E$7*(1-$B71)-cost_fx*Inputs!$D$7)) -> 403651.65 | I71: =12*Inputs!$B$8*(MIN(1,$H$52*$C71)*(ic*Inputs!$C$8+pT-cost_acc-cost_wd*Inputs!$E$8-cost_fx*Inputs!$D$8-cost_ins)+(1-MIN(1,$H$52*$C71))*(1-MIN(1,Inputs!$G$8*$D71)*churn_nonbuyers)*(ic*Inputs!$C$8+fee_wd*Inputs!$E$8*(1-$B71)+fee_fx*Inputs!$D$8-cost_acc-cost_wd*Inputs!$E$8*(1-$B71)-cost_fx*Inputs!$D$8)) -> 174259.81 | J71: =G71+H71+I71-fixed -> 102576.91 | K71: =12*Inputs!$B$6*(1-MIN(1,Inputs!$G$6*$D71)*churn_nonbuyers)*(ic*Inputs!$C$6+fee_wd*Inputs!$E$6*(1-$B71)+fee_fx*Inputs!$D$6-cost_acc-cost_wd*Inputs!$E$6*(1-$B71)-cost_fx*Inputs!$D$6) -> 172048.11 | L71: =12*Inputs!$B$7*(1-MIN(1,Inputs!$G$7*$D71)*churn_nonbuyers)*(ic*Inputs!$C$7+fee_wd*Inputs!$E$7*(1-$B71)+fee_fx*Inputs!$D$7-cost_acc-cost_wd*Inputs!$E$7*(1-$B71)-cost_fx*Inputs!$D$7) -> 371153.34 | M71: =12*Inputs!$B$8*(1-MIN(1,Inputs!$G$8*$D71)*churn_nonbuyers)*(ic*Inputs!$C$8+fee_wd*Inputs!$E$8*(1-$B71)+fee_fx*Inputs!$D$8-cost_acc-cost_wd*Inputs!$E$8*(1-$B71)-cost_fx*Inputs!$D$8) -> 88989.909 | N71: =K71+L71+I71-fixed -> 17461.266 | O71: =K71+L71+M71-fixed -> -67808.635 | P71: =12*Inputs!$B$6*(1-MIN(1,Inputs!$F$6*$D71))*(ic*Inputs!$C$6+flat_fee-cost_acc-cost_wd*Inputs!$E$6*$E71-cost_fx*Inputs!$D$6)+12*Inputs!$B$7*(1-MIN(1,Inputs!$F$7*$D71))*(ic*Inputs!$C$7+flat_fee-cost_acc-cost_wd*Inputs!$E$7*$E71-cost_fx*Inputs!$D$7)+12*Inputs!$B$8*(1-MIN(1,Inputs!$F$8*$D71))*(ic*Inputs!$C$8+flat_fee-cost_acc-cost_wd*Inputs!$E$8*$E71-cost_fx*Inputs!$D$8)-fixed -> -61803.557
A72: 7 | B72: 0.405615 | C72: 1.03372 | D72: 1.57921 | E72: 1.332893 | F72: 0.055607 | G72: =12*Inputs!$B$6*(MIN(1,$H$50*$C72)*(ic*Inputs!$C$6+pS+fee_fx*Inputs!$D$6-cost_acc-cost_wd*Inputs!$E$6*$E72-cost_fx*Inputs!$D$6-$F72)+(1-MIN(1,$H$50*$C72))*(1-MIN(1,Inputs!$G$6*$D72)*churn_nonbuyers)*(ic*Inputs!$C$6+fee_wd*Inputs!$E$6*(1-$B72)+fee_fx*Inputs!$D$6-cost_acc-cost_wd*Inputs!$E$6*(1-$B72)-cost_fx*Inputs!$D$6)) -> 187701.47 | H72: =12*Inputs!$B$7*(MIN(1,$H$51*$C72)*(ic*Inputs!$C$7+pE+fee_fx*Inputs!$D$7-cost_acc-cost_wd*Inputs!$E$7*$E72-cost_fx*Inputs!$D$7-$F72)+(1-MIN(1,$H$51*$C72))*(1-MIN(1,Inputs!$G$7*$D72)*churn_nonbuyers)*(ic*Inputs!$C$7+fee_wd*Inputs!$E$7*(1-$B72)+fee_fx*Inputs!$D$7-cost_acc-cost_wd*Inputs!$E$7*(1-$B72)-cost_fx*Inputs!$D$7)) -> 375355.51 | I72: =12*Inputs!$B$8*(MIN(1,$H$52*$C72)*(ic*Inputs!$C$8+pT-cost_acc-cost_wd*Inputs!$E$8-cost_fx*Inputs!$D$8-cost_ins)+(1-MIN(1,$H$52*$C72))*(1-MIN(1,Inputs!$G$8*$D72)*churn_nonbuyers)*(ic*Inputs!$C$8+fee_wd*Inputs!$E$8*(1-$B72)+fee_fx*Inputs!$D$8-cost_acc-cost_wd*Inputs!$E$8*(1-$B72)-cost_fx*Inputs!$D$8)) -> 149004.54 | J72: =G72+H72+I72-fixed -> 12061.517 | K72: =12*Inputs!$B$6*(1-MIN(1,Inputs!$G$6*$D72)*churn_nonbuyers)*(ic*Inputs!$C$6+fee_wd*Inputs!$E$6*(1-$B72)+fee_fx*Inputs!$D$6-cost_acc-cost_wd*Inputs!$E$6*(1-$B72)-cost_fx*Inputs!$D$6) -> 131884.97 | L72: =12*Inputs!$B$7*(1-MIN(1,Inputs!$G$7*$D72)*churn_nonbuyers)*(ic*Inputs!$C$7+fee_wd*Inputs!$E$7*(1-$B72)+fee_fx*Inputs!$D$7-cost_acc-cost_wd*Inputs!$E$7*(1-$B72)-cost_fx*Inputs!$D$7) -> 328456.5 | M72: =12*Inputs!$B$8*(1-MIN(1,Inputs!$G$8*$D72)*churn_nonbuyers)*(ic*Inputs!$C$8+fee_wd*Inputs!$E$8*(1-$B72)+fee_fx*Inputs!$D$8-cost_acc-cost_wd*Inputs!$E$8*(1-$B72)-cost_fx*Inputs!$D$8) -> 0 | N72: =K72+L72+I72-fixed -> -90653.995 | O72: =K72+L72+M72-fixed -> -239658.53 | P72: =12*Inputs!$B$6*(1-MIN(1,Inputs!$F$6*$D72))*(ic*Inputs!$C$6+flat_fee-cost_acc-cost_wd*Inputs!$E$6*$E72-cost_fx*Inputs!$D$6)+12*Inputs!$B$7*(1-MIN(1,Inputs!$F$7*$D72))*(ic*Inputs!$C$7+flat_fee-cost_acc-cost_wd*Inputs!$E$7*$E72-cost_fx*Inputs!$D$7)+12*Inputs!$B$8*(1-MIN(1,Inputs!$F$8*$D72))*(ic*Inputs!$C$8+flat_fee-cost_acc-cost_wd*Inputs!$E$8*$E72-cost_fx*Inputs!$D$8)-fixed -> -353694.92
A73: 8 | B73: 0.245317 | C73: 0.955014 | D73: 0.952895 | E73: 1.477484 | F73: 0.157785 | G73: =12*Inputs!$B$6*(MIN(1,$H$50*$C73)*(ic*Inputs!$C$6+pS+fee_fx*Inputs!$D$6-cost_acc-cost_wd*Inputs!$E$6*$E73-cost_fx*Inputs!$D$6-$F73)+(1-MIN(1,$H$50*$C73))*(1-MIN(1,Inputs!$G$6*$D73)*churn_nonbuyers)*(ic*Inputs!$C$6+fee_wd*Inputs!$E$6*(1-$B73)+fee_fx*Inputs!$D$6-cost_acc-cost_wd*Inputs!$E$6*(1-$B73)-cost_fx*Inputs!$D$6)) -> 202467.04 | H73: =12*Inputs!$B$7*(MIN(1,$H$51*$C73)*(ic*Inputs!$C$7+pE+fee_fx*Inputs!$D$7-cost_acc-cost_wd*Inputs!$E$7*$E73-cost_fx*Inputs!$D$7-$F73)+(1-MIN(1,$H$51*$C73))*(1-MIN(1,Inputs!$G$7*$D73)*churn_nonbuyers)*(ic*Inputs!$C$7+fee_wd*Inputs!$E$7*(1-$B73)+fee_fx*Inputs!$D$7-cost_acc-cost_wd*Inputs!$E$7*(1-$B73)-cost_fx*Inputs!$D$7)) -> 368117.39 | I73: =12*Inputs!$B$8*(MIN(1,$H$52*$C73)*(ic*Inputs!$C$8+pT-cost_acc-cost_wd*Inputs!$E$8-cost_fx*Inputs!$D$8-cost_ins)+(1-MIN(1,$H$52*$C73))*(1-MIN(1,Inputs!$G$8*$D73)*churn_nonbuyers)*(ic*Inputs!$C$8+fee_wd*Inputs!$E$8*(1-$B73)+fee_fx*Inputs!$D$8-cost_acc-cost_wd*Inputs!$E$8*(1-$B73)-cost_fx*Inputs!$D$8)) -> 172387.02 | J73: =G73+H73+I73-fixed -> 42971.458 | K73: =12*Inputs!$B$6*(1-MIN(1,Inputs!$G$6*$D73)*churn_nonbuyers)*(ic*Inputs!$C$6+fee_wd*Inputs!$E$6*(1-$B73)+fee_fx*Inputs!$D$6-cost_acc-cost_wd*Inputs!$E$6*(1-$B73)-cost_fx*Inputs!$D$6) -> 158352.25 | L73: =12*Inputs!$B$7*(1-MIN(1,Inputs!$G$7*$D73)*churn_nonbuyers)*(ic*Inputs!$C$7+fee_wd*Inputs!$E$7*(1-$B73)+fee_fx*Inputs!$D$7-cost_acc-cost_wd*Inputs!$E$7*(1-$B73)-cost_fx*Inputs!$D$7) -> 357357.98 | M73: =12*Inputs!$B$8*(1-MIN(1,Inputs!$G$8*$D73)*churn_nonbuyers)*(ic*Inputs!$C$8+fee_wd*Inputs!$E$8*(1-$B73)+fee_fx*Inputs!$D$8-cost_acc-cost_wd*Inputs!$E$8*(1-$B73)-cost_fx*Inputs!$D$8) -> 104761.72 | N73: =K73+L73+I73-fixed -> -11902.745 | O73: =K73+L73+M73-fixed -> -79528.049 | P73: =12*Inputs!$B$6*(1-MIN(1,Inputs!$F$6*$D73))*(ic*Inputs!$C$6+flat_fee-cost_acc-cost_wd*Inputs!$E$6*$E73-cost_fx*Inputs!$D$6)+12*Inputs!$B$7*(1-MIN(1,Inputs!$F$7*$D73))*(ic*Inputs!$C$7+flat_fee-cost_acc-cost_wd*Inputs!$E$7*$E73-cost_fx*Inputs!$D$7)+12*Inputs!$B$8*(1-MIN(1,Inputs!$F$8*$D73))*(ic*Inputs!$C$8+flat_fee-cost_acc-cost_wd*Inputs!$E$8*$E73-cost_fx*Inputs!$D$8)-fixed -> -114635.31
A74: 9 | B74: 0.27801 | C74: 1.030064 | D74: 0.952372 | E74: 1.060118 | F74: 0.301506 | G74: =12*Inputs!$B$6*(MIN(1,$H$50*$C74)*(ic*Inputs!$C$6+pS+fee_fx*Inputs!$D$6-cost_acc-cost_wd*Inputs!$E$6*$E74-cost_fx*Inputs!$D$6-$F74)+(1-MIN(1,$H$50*$C74))*(1-MIN(1,Inputs!$G$6*$D74)*churn_nonbuyers)*(ic*Inputs!$C$6+fee_wd*Inputs!$E$6*(1-$B74)+fee_fx*Inputs!$D$6-cost_acc-cost_wd*Inputs!$E$6*(1-$B74)-cost_fx*Inputs!$D$6)) -> 208317.99 | H74: =12*Inputs!$B$7*(MIN(1,$H$51*$C74)*(ic*Inputs!$C$7+pE+fee_fx*Inputs!$D$7-cost_acc-cost_wd*Inputs!$E$7*$E74-cost_fx*Inputs!$D$7-$F74)+(1-MIN(1,$H$51*$C74))*(1-MIN(1,Inputs!$G$7*$D74)*churn_nonbuyers)*(ic*Inputs!$C$7+fee_wd*Inputs!$E$7*(1-$B74)+fee_fx*Inputs!$D$7-cost_acc-cost_wd*Inputs!$E$7*(1-$B74)-cost_fx*Inputs!$D$7)) -> 407276.19 | I74: =12*Inputs!$B$8*(MIN(1,$H$52*$C74)*(ic*Inputs!$C$8+pT-cost_acc-cost_wd*Inputs!$E$8-cost_fx*Inputs!$D$8-cost_ins)+(1-MIN(1,$H$52*$C74))*(1-MIN(1,Inputs!$G$8*$D74)*churn_nonbuyers)*(ic*Inputs!$C$8+fee_wd*Inputs!$E$8*(1-$B74)+fee_fx*Inputs!$D$8-cost_acc-cost_wd*Inputs!$E$8*(1-$B74)-cost_fx*Inputs!$D$8)) -> 177587.58 | J74: =G74+H74+I74-fixed -> 93181.765 | K74: =12*Inputs!$B$6*(1-MIN(1,Inputs!$G$6*$D74)*churn_nonbuyers)*(ic*Inputs!$C$6+fee_wd*Inputs!$E$6*(1-$B74)+fee_fx*Inputs!$D$6-cost_acc-cost_wd*Inputs!$E$6*(1-$B74)-cost_fx*Inputs!$D$6) -> 153872.99 | L74: =12*Inputs!$B$7*(1-MIN(1,Inputs!$G$7*$D74)*churn_nonbuyers)*(ic*Inputs!$C$7+fee_wd*Inputs!$E$7*(1-$B74)+fee_fx*Inputs!$D$7-cost_acc-cost_wd*Inputs!$E$7*(1-$B74)-cost_fx*Inputs!$D$7) -> 352790.47 | M74: =12*Inputs!$B$8*(1-MIN(1,Inputs!$G$8*$D74)*churn_nonbuyers)*(ic*Inputs!$C$8+fee_wd*Inputs!$E$8*(1-$B74)+fee_fx*Inputs!$D$8-cost_acc-cost_wd*Inputs!$E$8*(1-$B74)-cost_fx*Inputs!$D$8) -> 104353.8 | N74: =K74+L74+I74-fixed -> -15748.962 | O74: =K74+L74+M74-fixed -> -88982.741 | P74: =12*Inputs!$B$6*(1-MIN(1,Inputs!$F$6*$D74))*(ic*Inputs!$C$6+flat_fee-cost_acc-cost_wd*Inputs!$E$6*$E74-cost_fx*Inputs!$D$6)+12*Inputs!$B$7*(1-MIN(1,Inputs!$F$7*$D74))*(ic*Inputs!$C$7+flat_fee-cost_acc-cost_wd*Inputs!$E$7*$E74-cost_fx*Inputs!$D$7)+12*Inputs!$B$8*(1-MIN(1,Inputs!$F$8*$D74))*(ic*Inputs!$C$8+flat_fee-cost_acc-cost_wd*Inputs!$E$8*$E74-cost_fx*Inputs!$D$8)-fixed -> 70672.595
A75: 10 | B75: 0.294942 | C75: 1.025923 | D75: 1.136391 | E75: 1.058415 | F75: 0.107531 | G75: =12*Inputs!$B$6*(MIN(1,$H$50*$C75)*(ic*Inputs!$C$6+pS+fee_fx*Inputs!$D$6-cost_acc-cost_wd*Inputs!$E$6*$E75-cost_fx*Inputs!$D$6-$F75)+(1-MIN(1,$H$50*$C75))*(1-MIN(1,Inputs!$G$6*$D75)*churn_nonbuyers)*(ic*Inputs!$C$6+fee_wd*Inputs!$E$6*(1-$B75)+fee_fx*Inputs!$D$6-cost_acc-cost_wd*Inputs!$E$6*(1-$B75)-cost_fx*Inputs!$D$6)) -> 209248.92 | H75: =12*Inputs!$B$7*(MIN(1,$H$51*$C75)*(ic*Inputs!$C$7+pE+fee_fx*Inputs!$D$7-cost_acc-cost_wd*Inputs!$E$7*$E75-cost_fx*Inputs!$D$7-$F75)+(1-MIN(1,$H$51*$C75))*(1-MIN(1,Inputs!$G$7*$D75)*churn_nonbuyers)*(ic*Inputs!$C$7+fee_wd*Inputs!$E$7*(1-$B75)+fee_fx*Inputs!$D$7-cost_acc-cost_wd*Inputs!$E$7*(1-$B75)-cost_fx*Inputs!$D$7)) -> 416150.25 | I75: =12*Inputs!$B$8*(MIN(1,$H$52*$C75)*(ic*Inputs!$C$8+pT-cost_acc-cost_wd*Inputs!$E$8-cost_fx*Inputs!$D$8-cost_ins)+(1-MIN(1,$H$52*$C75))*(1-MIN(1,Inputs!$G$8*$D75)*churn_nonbuyers)*(ic*Inputs!$C$8+fee_wd*Inputs!$E$8*(1-$B75)+fee_fx*Inputs!$D$8-cost_acc-cost_wd*Inputs!$E$8*(1-$B75)-cost_fx*Inputs!$D$8)) -> 165880.36 | J75: =G75+H75+I75-fixed -> 91279.529 | K75: =12*Inputs!$B$6*(1-MIN(1,Inputs!$G$6*$D75)*churn_nonbuyers)*(ic*Inputs!$C$6+fee_wd*Inputs!$E$6*(1-$B75)+fee_fx*Inputs!$D$6-cost_acc-cost_wd*Inputs!$E$6*(1-$B75)-cost_fx*Inputs!$D$6) -> 150086.75 | L75: =12*Inputs!$B$7*(1-MIN(1,Inputs!$G$7*$D75)*churn_nonbuyers)*(ic*Inputs!$C$7+fee_wd*Inputs!$E$7*(1-$B75)+fee_fx*Inputs!$D$7-cost_acc-cost_wd*Inputs!$E$7*(1-$B75)-cost_fx*Inputs!$D$7) -> 348430.5 | M75: =12*Inputs!$B$8*(1-MIN(1,Inputs!$G$8*$D75)*churn_nonbuyers)*(ic*Inputs!$C$8+fee_wd*Inputs!$E$8*(1-$B75)+fee_fx*Inputs!$D$8-cost_acc-cost_wd*Inputs!$E$8*(1-$B75)-cost_fx*Inputs!$D$8) -> 63861.861 | N75: =K75+L75+I75-fixed -> -35602.391 | O75: =K75+L75+M75-fixed -> -137620.89 | P75: =12*Inputs!$B$6*(1-MIN(1,Inputs!$F$6*$D75))*(ic*Inputs!$C$6+flat_fee-cost_acc-cost_wd*Inputs!$E$6*$E75-cost_fx*Inputs!$D$6)+12*Inputs!$B$7*(1-MIN(1,Inputs!$F$7*$D75))*(ic*Inputs!$C$7+flat_fee-cost_acc-cost_wd*Inputs!$E$7*$E75-cost_fx*Inputs!$D$7)+12*Inputs!$B$8*(1-MIN(1,Inputs!$F$8*$D75))*(ic*Inputs!$C$8+flat_fee-cost_acc-cost_wd*Inputs!$E$8*$E75-cost_fx*Inputs!$D$8)-fixed -> -29765.837
A76: 11 | B76: 0.065083 | C76: 0.86965 | D76: 1.25525 | E76: 1.185991 | F76: 0.067116 | G76: =12*Inputs!$B$6*(MIN(1,$H$50*$C76)*(ic*Inputs!$C$6+pS+fee_fx*Inputs!$D$6-cost_acc-cost_wd*Inputs!$E$6*$E76-cost_fx*Inputs!$D$6-$F76)+(1-MIN(1,$H$50*$C76))*(1-MIN(1,Inputs!$G$6*$D76)*churn_nonbuyers)*(ic*Inputs!$C$6+fee_wd*Inputs!$E$6*(1-$B76)+fee_fx*Inputs!$D$6-cost_acc-cost_wd*Inputs!$E$6*(1-$B76)-cost_fx*Inputs!$D$6)) -> 226474.76 | H76: =12*Inputs!$B$7*(MIN(1,$H$51*$C76)*(ic*Inputs!$C$7+pE+fee_fx*Inputs!$D$7-cost_acc-cost_wd*Inputs!$E$7*$E76-cost_fx*Inputs!$D$7-$F76)+(1-MIN(1,$H$51*$C76))*(1-MIN(1,Inputs!$G$7*$D76)*churn_nonbuyers)*(ic*Inputs!$C$7+fee_wd*Inputs!$E$7*(1-$B76)+fee_fx*Inputs!$D$7-cost_acc-cost_wd*Inputs!$E$7*(1-$B76)-cost_fx*Inputs!$D$7)) -> 415012.26 | I76: =12*Inputs!$B$8*(MIN(1,$H$52*$C76)*(ic*Inputs!$C$8+pT-cost_acc-cost_wd*Inputs!$E$8-cost_fx*Inputs!$D$8-cost_ins)+(1-MIN(1,$H$52*$C76))*(1-MIN(1,Inputs!$G$8*$D76)*churn_nonbuyers)*(ic*Inputs!$C$8+fee_wd*Inputs!$E$8*(1-$B76)+fee_fx*Inputs!$D$8-cost_acc-cost_wd*Inputs!$E$8*(1-$B76)-cost_fx*Inputs!$D$8)) -> 140700.03 | J76: =G76+H76+I76-fixed -> 82187.048 | K76: =12*Inputs!$B$6*(1-MIN(1,Inputs!$G$6*$D76)*churn_nonbuyers)*(ic*Inputs!$C$6+fee_wd*Inputs!$E$6*(1-$B76)+fee_fx*Inputs!$D$6-cost_acc-cost_wd*Inputs!$E$6*(1-$B76)-cost_fx*Inputs!$D$6) -> 180163.34 | L76: =12*Inputs!$B$7*(1-MIN(1,Inputs!$G$7*$D76)*churn_nonbuyers)*(ic*Inputs!$C$7+fee_wd*Inputs!$E$7*(1-$B76)+fee_fx*Inputs!$D$7-cost_acc-cost_wd*Inputs!$E$7*(1-$B76)-cost_fx*Inputs!$D$7) -> 378997.47 | M76: =12*Inputs!$B$8*(1-MIN(1,Inputs!$G$8*$D76)*churn_nonbuyers)*(ic*Inputs!$C$8+fee_wd*Inputs!$E$8*(1-$B76)+fee_fx*Inputs!$D$8-cost_acc-cost_wd*Inputs!$E$8*(1-$B76)-cost_fx*Inputs!$D$8) -> 39221.463 | N76: =K76+L76+I76-fixed -> -139.16583 | O76: =K76+L76+M76-fixed -> -101617.73 | P76: =12*Inputs!$B$6*(1-MIN(1,Inputs!$F$6*$D76))*(ic*Inputs!$C$6+flat_fee-cost_acc-cost_wd*Inputs!$E$6*$E76-cost_fx*Inputs!$D$6)+12*Inputs!$B$7*(1-MIN(1,Inputs!$F$7*$D76))*(ic*Inputs!$C$7+flat_fee-cost_acc-cost_wd*Inputs!$E$7*$E76-cost_fx*Inputs!$D$7)+12*Inputs!$B$8*(1-MIN(1,Inputs!$F$8*$D76))*(ic*Inputs!$C$8+flat_fee-cost_acc-cost_wd*Inputs!$E$8*$E76-cost_fx*Inputs!$D$8)-fixed -> -142424.93
A77: 12 | B77: 0.058199 | C77: 0.987898 | D77: 1.235174 | E77: 1.135847 | F77: 0.026359 | G77: =12*Inputs!$B$6*(MIN(1,$H$50*$C77)*(ic*Inputs!$C$6+pS+fee_fx*Inputs!$D$6-cost_acc-cost_wd*Inputs!$E$6*$E77-cost_fx*Inputs!$D$6-$F77)+(1-MIN(1,$H$50*$C77))*(1-MIN(1,Inputs!$G$6*$D77)*churn_nonbuyers)*(ic*Inputs!$C$6+fee_wd*Inputs!$E$6*(1-$B77)+fee_fx*Inputs!$D$6-cost_acc-cost_wd*Inputs!$E$6*(1-$B77)-cost_fx*Inputs!$D$6)) -> 235875.11 | H77: =12*Inputs!$B$7*(MIN(1,$H$51*$C77)*(ic*Inputs!$C$7+pE+fee_fx*Inputs!$D$7-cost_acc-cost_wd*Inputs!$E$7*$E77-cost_fx*Inputs!$D$7-$F77)+(1-MIN(1,$H$51*$C77))*(1-MIN(1,Inputs!$G$7*$D77)*churn_nonbuyers)*(ic*Inputs!$C$7+fee_wd*Inputs!$E$7*(1-$B77)+fee_fx*Inputs!$D$7-cost_acc-cost_wd*Inputs!$E$7*(1-$B77)-cost_fx*Inputs!$D$7)) -> 428655.95 | I77: =12*Inputs!$B$8*(MIN(1,$H$52*$C77)*(ic*Inputs!$C$8+pT-cost_acc-cost_wd*Inputs!$E$8-cost_fx*Inputs!$D$8-cost_ins)+(1-MIN(1,$H$52*$C77))*(1-MIN(1,Inputs!$G$8*$D77)*churn_nonbuyers)*(ic*Inputs!$C$8+fee_wd*Inputs!$E$8*(1-$B77)+fee_fx*Inputs!$D$8-cost_acc-cost_wd*Inputs!$E$8*(1-$B77)-cost_fx*Inputs!$D$8)) -> 155913.47 | J77: =G77+H77+I77-fixed -> 120444.53 | K77: =12*Inputs!$B$6*(1-MIN(1,Inputs!$G$6*$D77)*churn_nonbuyers)*(ic*Inputs!$C$6+fee_wd*Inputs!$E$6*(1-$B77)+fee_fx*Inputs!$D$6-cost_acc-cost_wd*Inputs!$E$6*(1-$B77)-cost_fx*Inputs!$D$6) -> 181286.37 | L77: =12*Inputs!$B$7*(1-MIN(1,Inputs!$G$7*$D77)*churn_nonbuyers)*(ic*Inputs!$C$7+fee_wd*Inputs!$E$7*(1-$B77)+fee_fx*Inputs!$D$7-cost_acc-cost_wd*Inputs!$E$7*(1-$B77)-cost_fx*Inputs!$D$7) -> 380189.23 | M77: =12*Inputs!$B$8*(1-MIN(1,Inputs!$G$8*$D77)*churn_nonbuyers)*(ic*Inputs!$C$8+fee_wd*Inputs!$E$8*(1-$B77)+fee_fx*Inputs!$D$8-cost_acc-cost_wd*Inputs!$E$8*(1-$B77)-cost_fx*Inputs!$D$8) -> 43809.258 | N77: =K77+L77+I77-fixed -> 17389.067 | O77: =K77+L77+M77-fixed -> -94715.147 | P77: =12*Inputs!$B$6*(1-MIN(1,Inputs!$F$6*$D77))*(ic*Inputs!$C$6+flat_fee-cost_acc-cost_wd*Inputs!$E$6*$E77-cost_fx*Inputs!$D$6)+12*Inputs!$B$7*(1-MIN(1,Inputs!$F$7*$D77))*(ic*Inputs!$C$7+flat_fee-cost_acc-cost_wd*Inputs!$E$7*$E77-cost_fx*Inputs!$D$7)+12*Inputs!$B$8*(1-MIN(1,Inputs!$F$8*$D77))*(ic*Inputs!$C$8+flat_fee-cost_acc-cost_wd*Inputs!$E$8*$E77-cost_fx*Inputs!$D$8)-fixed -> -113167.66
... A5065: 5000 | B5065: 0.368468 | C5065: 0.837892 | D5065: 1.666491 | E5065: 1.225393 | F5065: 0.393797 | G5065: =12*Inputs!$B$6*(MIN(1,$H$50*$C5065)*(ic*Inputs!$C$6+pS+fee_fx*Inputs!$D$6-cost_acc-cost_wd*Inputs!$E$6*$E5065-cost_fx*Inputs!$D$6-$F5065)+(1-MIN(1,$H$50*$C5065))*(1-MIN(1,Inputs!$G$6*$D5065)*churn_nonbuyers)*(ic*Inputs!$C$6+fee_wd*Inputs!$E$6*(1-$B5065)+fee_fx*Inputs!$D$6-cost_acc-cost_wd*Inputs!$E$6*(1-$B5065)-cost_fx*Inputs!$D$6)) -> 176665.87 | H5065: =12*Inputs!$B$7*(MIN(1,$H$51*$C5065)*(ic*Inputs!$C$7+pE+fee_fx*Inputs!$D$7-cost_acc-cost_wd*Inputs!$E$7*$E5065-cost_fx*Inputs!$D$7-$F5065)+(1-MIN(1,$H$51*$C5065))*(1-MIN(1,Inputs!$G$7*$D5065)*churn_nonbuyers)*(ic*Inputs!$C$7+fee_wd*Inputs!$E$7*(1-$B5065)+fee_fx*Inputs!$D$7-cost_acc-cost_wd*Inputs!$E$7*(1-$B5065)-cost_fx*Inputs!$D$7)) -> 363303.82 | I5065: =12*Inputs!$B$8*(MIN(1,$H$52*$C5065)*(ic*Inputs!$C$8+pT-cost_acc-cost_wd*Inputs!$E$8-cost_fx*Inputs!$D$8-cost_ins)+(1-MIN(1,$H$52*$C5065))*(1-MIN(1,Inputs!$G$8*$D5065)*churn_nonbuyers)*(ic*Inputs!$C$8+fee_wd*Inputs!$E$8*(1-$B5065)+fee_fx*Inputs!$D$8-cost_acc-cost_wd*Inputs!$E$8*(1-$B5065)-cost_fx*Inputs!$D$8)) -> 120777.1 | J5065: =G5065+H5065+I5065-fixed -> -39253.205 | K5065: =12*Inputs!$B$6*(1-MIN(1,Inputs!$G$6*$D5065)*churn_nonbuyers)*(ic*Inputs!$C$6+fee_wd*Inputs!$E$6*(1-$B5065)+fee_fx*Inputs!$D$6-cost_acc-cost_wd*Inputs!$E$6*(1-$B5065)-cost_fx*Inputs!$D$6) -> 136163.53 | L5065: =12*Inputs!$B$7*(1-MIN(1,Inputs!$G$7*$D5065)*churn_nonbuyers)*(ic*Inputs!$C$7+fee_wd*Inputs!$E$7*(1-$B5065)+fee_fx*Inputs!$D$7-cost_acc-cost_wd*Inputs!$E$7*(1-$B5065)-cost_fx*Inputs!$D$7) -> 332635.42 | M5065: =12*Inputs!$B$8*(1-MIN(1,Inputs!$G$8*$D5065)*churn_nonbuyers)*(ic*Inputs!$C$8+fee_wd*Inputs!$E$8*(1-$B5065)+fee_fx*Inputs!$D$8-cost_acc-cost_wd*Inputs!$E$8*(1-$B5065)-cost_fx*Inputs!$D$8) -> 0 | N5065: =K5065+L5065+I5065-fixed -> -110423.94 | O5065: =K5065+L5065+M5065-fixed -> -231201.05 | P5065: =12*Inputs!$B$6*(1-MIN(1,Inputs!$F$6*$D5065))*(ic*Inputs!$C$6+flat_fee-cost_acc-cost_wd*Inputs!$E$6*$E5065-cost_fx*Inputs!$D$6)+12*Inputs!$B$7*(1-MIN(1,Inputs!$F$7*$D5065))*(ic*Inputs!$C$7+flat_fee-cost_acc-cost_wd*Inputs!$E$7*$E5065-cost_fx*Inputs!$D$7)+12*Inputs!$B$8*(1-MIN(1,Inputs!$F$8*$D5065))*(ic*Inputs!$C$8+flat_fee-cost_acc-cost_wd*Inputs!$E$8*$E5065-cost_fx*Inputs!$D$8)-fixed -> -366697.34

Sheet Assumptions
A1: Assumption register — everything that is not on the case sheet
A2: Each assumption has a base value (Inputs), a tested range (Sensitivity / Stress test) and a way to replace it with data after launch.
A4: # | B4: Assumption | C4: Base value | D4: Tested | E4: Profit at the tested value | F4: Switching value | G4: Why this base value · how to replace it with data
A5: 1 | B5: Per-use churn applies only to customers who actually pay per-use fees; plan buyers do not leave | C5: non-buyers only | D5: churn × 2 | E5: =Sensitivity!AG15 -> 130275.2 | F5: ='Stress test'!F12 -> 9.88 | G5: Wording of the case: '… of the travellers who pay these fees would leave'. Replace with observed churn by segment and plan status.
A6: 2 | B6: Nobody changes how often they withdraw cash once a withdrawal costs 1.50 | C6: 0% avoided | D6: 50% avoided | E6: =Sensitivity!AG7 -> 69190.4 | F6: ='Stress test'!F6 -> 0.8233438 | G6: The case gives usage before fees only. The least defensible assumption, hence the widest tested range. Replace with withdrawals per Basic customer in the first quarter.
A7: 3 | B7: Plus subscribers withdraw as often as the segment average | C7: 1.0 × | D7: 2.0 × | E7: =Sensitivity!AG10 -> 37942.4 | F7: ='Stress test'!F8 -> 2.2744676 | G7: Protected by the cap of 3 included withdrawals. Replace with withdrawals per Plus subscriber.
A8: 4 | B8: Shared accounts and virtual cards cost nothing extra per subscriber | C8: 0 | D8: 0.50 a month | E8: =Sensitivity!AG12 -> 135862.4 | F8: ='Stress test'!F9 -> 2.1848016 | G8: Software features; the case lists no cost. Replace with the processor's price per virtual card.
A9: 5 | B9: Plan take-up equals the survey share at the chosen price; no interpolation between surveyed prices | C9: 1.0 × | D9: 0.8 × | E9: =Sensitivity!AG13 -> 137054.72 | F9: ='Stress test'!F7 -> 0.099448779 | G9: Survey of 2,000 customers. Stated intentions usually overstate purchases; on the other hand the plan becomes more attractive once per-use fees exist. Replace with the attach rate.
A10: 6 | B10: The cap of 3 included withdrawals does not lower Plus take-up | C10: survey shares unchanged | D10: see take-up | G10: The survey asked about 'free cash withdrawals'; the cap is above typical use (1–2). Covered by the take-up range.
A11: 7 | B11: Travel includes the Plus features at no extra cost | C11: 0 | D11: as Plus features | G11: A clean ladder: each offer contains the one below.
A12: 8 | B12: Negative differentiation value of Travel against Fluxa is zero | C12: 0 | D12: — | G12: No drawback is quantifiable from the case. Does not enter the profit model; it only sets the stated ceiling of 12.00.
A13: 9 | B13: Interchange is earned on all card payments, including those in other currencies | C13: 0.2% of all | D13: 0.1% (cap halved) | E13: =Sensitivity!AG19 -> -50108.8 | F13: ='Stress test'!F11 -> 0.001221435 | G13: Wording of the case: 'of all card payments'.
A14: 10 | B14: Plus and Travel are paid in all twelve months, at the monthly price | C14: 12 monthly payments | D14: every Travel subscriber takes the yearly price of 69.90 | E14: =reco_profit-(12*pT-69.9)*Model!D9 -> 137038.4 | G14: The case describes a typical month only. The yearly Travel price gives away two months (13.98 per subscriber); a traveller who cancels in months at home pays less still. Replace with paid months per subscriber.
A15: 11 | B15: Plus subscribers do not leave, although they still pay the 1.5% currency fee | C15: 0 leave | D15: per-use churn applies to them too (240 customers) | E15: =reco_profit-12*(Model!B9*Inputs!$G$6*Model!B14+Model!C9*Inputs!$G$7*Model!C14) -> 165958.4 | G15: Someone who has just chosen a paid plan is unlikely to leave over 0.38–0.75 a month of currency fee. Small either way.
A16: 12 | B16: The Plus features inside Travel (shared accounts, virtual cards) add no value in the economic value estimate | C16: 0 | D16: — | G16: Conservative: the 12.00 for Travel counts only the insurance as differentiation. Does not enter the profit model.
A17: 13 | B17: The one-fee alternative includes everything (no per-use fees) and keeps the survey churn at every fee level | C17: fee 3.99 | D17: 2.99 / 4.99 | E17: =Alternatives!F17 -> -210328 | G17: The survey gave the churn for 'a monthly fee' without a level, so the alternative is credible only in the bank-package range of 3–5 (Alternatives, note).

Sheet Dashboard map
A1: Where every headline number on the website and the dashboard comes from
A2: Dashboard: https://axk2126.github.io/pricing-project/dashboard/ · the values below are live formulas pointing at the sheet that produces them.
A4: Number shown | B4: Value | C4: Produced in (sheet · cell) | D4: Dashboard page
A5: Contribution 2027, recommended price list | B5: =reco_total -> 876182.4 | C5: Model · E20 | D5: Overview · 3 Numbers
A6: Profit 2027 after fixed costs | B6: =reco_profit -> 176182.4 | C6: Model · E22 | D6: Overview · 3 Numbers
A7: Profit today (everything free) | B7: =Alternatives!F5 -> -1280800 | C7: Alternatives · F5 | D7: Overview
A8: Customers retained | B8: =Model!E13 -> 37840 | C8: Model · E13 | D8: Overview
A9: Customers retained, share | B9: =Model!E13/Inputs!$B$10 -> 0.946 | C9: Model · E23 | D9: Overview
A10: Plan subscribers | B10: =Model!E9 -> 9520 | C10: Model · E9 | D10: 3 Numbers
A11: Contribution: fees per use only (B) | B11: =Alternatives!E6 -> 680544 | C11: Alternatives · E6 | D11: Overview · 3 Numbers
A12: Contribution: one fee 3.99 (C) | B12: =Alternatives!E7 -> 770472 | C12: Alternatives · E7 | D12: Overview · 3 Numbers
A13: Contribution: Basic + Travel only (D) | B13: =Alternatives!E8 -> 756144 | C13: Alternatives · E8 | D13: 3 Numbers
A14: Gain over one fee | B14: =Alternatives!F13 -> 0.13720213 | C14: Alternatives · F13 | D14: Overview · 3 Numbers
A15: Customers lost by a monthly fee | B15: =Inputs!$B$10-Alternatives!G7 -> 16600 | C15: Alternatives · G7 | D15: 1 Customers
A16: Break-even customers | B16: ='Break-even'!B9 -> 30231.148 | C16: Break-even · B9 | D16: 3 Numbers
A17: Safety margin | B17: ='Break-even'!B10 -> 0.20107959 | C17: Break-even · B10 | D17: 3 Numbers
A18: Reference value of the Travel plan | B18: =EVE!B6 -> 8 | C18: EVE · B6 | D18: 1 Customers · 2 Pricing
A19: Total economic value of the Travel plan | B19: =EVE!B9 -> 12 | C19: EVE · B9 | D19: 1 Customers · 4 Presentation · website
A20: Incremental margin of a Plus subscriber | B20: ='Break-even'!E40 -> 1.074 | C20: Break-even · E40 | D20: 2 Pricing
A21: Incremental margin of a Travel subscriber | B21: ='Break-even'!E42 -> 2.25 | C21: Break-even · E42 | D21: 2 Pricing
A22: Take-up at which Travel 8.99 would match 6.99 | B22: ='Break-even'!B27 -> 0.37058824 | C22: Break-even · B27 | D22: 2 Pricing
A23: Take-up at which Travel 7.99 would match 6.99 | B23: ='Break-even'!B51 -> 0.48461538 | C23: Break-even · B51 | D23: 2 Pricing · KPIs and roll-out
A24: Typical traveller's bill on Basic / Plus / Travel | B24: =Arbitrage!B7 -> 9 | C24: Arbitrage · B7:D7 | D24: 2 Pricing · website calculator
A25: Profit with 50% fewer withdrawals | B25: =Sensitivity!AG7 -> 69190.4 | C25: Sensitivity | D25: Risk
A26: Profit: combined downside | B26: =Sensitivity!AG26 -> 6245.12 | C26: Sensitivity | D26: Risk
A27: Profit if the withdrawal cost rises to 1.50 | B27: =Sensitivity!AG17 -> -140521.6 | C27: Sensitivity | D27: Risk
A28: … and the fee follows to 2.00 | B28: =Sensitivity!AG18 -> 73462.4 | C28: Sensitivity | D28: Risk
A29: Profit if interchange is capped at 0.1% | B29: =Sensitivity!AG19 -> -50108.8 | C29: Sensitivity | D29: Risk
A30: Withdrawals avoided at which profit is zero | B30: ='Stress test'!F6 -> 0.8233438 | C30: Stress test · block A | D30: Risk
A31: Withdrawal cost at which profit is zero | B31: ='Stress test'!F10 -> 1.2781499 | C31: Stress test · block A | D31: Risk
A32: Profit with adverse selection in Plus | B32: ='Stress test'!B25 -> 56662.4 | C32: Stress test · B25 | D32: Risk
A33: Median simulated profit | B33: ='Stress test'!E40 -> 52915.517 | C33: Stress test · E40 | D33: Overview · Risk
A34: Probability of a loss, recommended | B34: ='Stress test'!H40 -> 0.1382 | C34: Stress test · H40 | D34: Overview · Risk
A35: Probability of a loss, one fee | B35: ='Stress test'!H43 -> 0.6946 | C35: Stress test · H43 | D35: Risk
A36: KPIs met | B36: =KPIs!E24 -> 17 | C36: KPIs · E24 | D36: KPIs and roll-out

Sheet Sources
A1: Sources — literature, EU rules, price lists (all checked on 05.10.2026)
A3: Type | B3: Reference | C3: Used for
A4: Literature | B4: Nagle, T. T., & Müller, G. (2018). The Strategy and Tactics of Pricing: A Guide to Growing More Profitably (6th ed.). Routledge. Ch. 2 Economic value; Ch. 3 Price and value communication; Ch. 4 Price structure; Ch. 6 Price level; Ch. 9 Financial analysis. | C4: Economic value, price structure, communication, price level, breakeven sales change.
A5: Literature | B5: Kaplan, R. S., & Norton, D. P. (1992). The balanced scorecard: Measures that drive performance. Harvard Business Review, 70(1), 71–79. | C5: Structure of the operating scorecard (KPIs, part 2).
A6: Literature | B6: Schmidt, J., & Bijmolt, T. H. A. (2020). Accurately measuring willingness to pay for consumer goods: A meta-analysis of the hypothetical bias. Journal of the Academy of Marketing Science, 48(3), 499–518. | C6: Stated willingness to pay exceeds real by 21% on average → take-up range in the stress test.
A7: Literature | B7: Magnac, T. (2017). ATM foreign fees and cash withdrawals. Journal of Banking & Finance, 78, 117–129. | C7: Customers withdraw less often once a withdrawal fee exists → direction of the withdrawal range (no figure taken from it).
A8: Course | B8: Price Management, ZSEM 2026/27: lecture handouts 3, 4, 5, 7; Case Book, case 05 (p. 7); Project Brief. | C8: Case facts, formulas, assignment.
A9: EU rule | B9: Regulation (EU) 2015/751, Art. 3(1): interchange fee for consumer debit card transactions at most 0.2%. | C9: Card income of 0.2% is a legal cap.
A10: EU rule | B10: Directive 2014/92/EU, Art. 4 (fee information document before the contract) and Art. 5 (statement of fees at least annually). | C10: Constraint: fee document and yearly statement.
A11: EU rule | B11: Regulation (EU) 2021/1230, Art. 4(1): currency conversion charges for card-based transactions as a percentage mark-up over the latest ECB reference rate, before the payment. (Replaces Regulation (EC) No 924/2009, repealed.) | C11: Constraint: currency fee format.
A12: EU rule | B12: Directive 2005/29/EC, Annex I, No 20: 'free' only if the consumer pays nothing beyond unavoidable costs. | C12: Constraint: Basic is never called free.
A13: EU rule | B13: Directive 2006/112/EC, Art. 135(1)(d): VAT exemption for transactions concerning accounts and payments. | C13: Price note on the website.
A14: EU rule | B14: Directive (EU) 2015/2366 (PSD2), Art. 62(4): no surcharges for consumer cards with regulated interchange. | C14: Background for gain–loss framing (handout 5).
... A18: Price list | B18: PBZ mladi: current account without fee for ages 18–25, offer to be contracted by 31.12.2026. pbz.hr/studenti/pbz-mladi.html. | C18: Benchmark only; context for the €0 account.

Sheet Check
A1: Check against the independent Python recomputation (novcic_model.py)
A2: Python values are typed in; differences should be 0 at the default inputs.
A4: Quantity | B4: Workbook (live) | C4: Python | D4: Difference
A5: Today: total contribution | B5: =Alternatives!E5 -> -580800 | C5: -580800 | D5: =B5-C5 -> 0
A6: Fees per use only: total contribution | B6: =Alternatives!E6 -> 680544 | C6: 680544 | D6: =B6-C6 -> 0
A7: One monthly fee 2.99: contribution | B7: =Alternatives!E17 -> 489672 | C7: 489672 | D7: =B7-C7 -> 0
A8: One monthly fee 3.99: contribution | B8: =Alternatives!E18 -> 770472 | C8: 770472 | D8: =B8-C8 -> 0
A9: One monthly fee 4.99: contribution | B9: =Alternatives!E19 -> 1051272 | C9: 1051272 | D9: =B9-C9 -> 0
A10: Basic + Travel only: contribution | B10: =Alternatives!E8 -> 756144 | C10: 756144 | D10: =B10-C10 -> 0
A11: Recommended: total contribution | B11: =reco_total -> 876182.4 | C11: 876182.4 | D11: =B11-C11 -> 0
A12: Recommended: profit | B12: =reco_profit -> 176182.4 | C12: 176182.4 | D12: =B12-C12 -> 0
A13: Recommended: customers retained | B13: =Model!E13 -> 37840 | C13: 37840 | D13: =B13-C13 -> 0
A14: Students at 2.99 / 3.99 / 4.99 (price grid) | B14: ='Price grid'!I7 -> 257400 | C14: 257400 | D14: =B14-C14 -> 0
B15: ='Price grid'!I8 -> 249696 | C15: 249696 | D15: =B15-C15 -> 0
B16: ='Price grid'!I9 -> 232128 | C16: 232128 | D16: =B16-C16 -> 0
A17: Employees at 2.99 / 3.99 / 4.99 | B17: ='Price grid'!I13 -> 396432 | C17: 396432 | D17: =B17-C17 -> 0
B18: ='Price grid'!I14 -> 452966.4 | C18: 452966.4 | D18: =B18-C18 -> 0
B19: ='Price grid'!I15 -> 450835.2 | C19: 450835.2 | D19: =B19-C19 -> 0
A20: Travellers at 5.99 / 6.99 / 8.99 | B20: ='Price grid'!I19 -> 145920 | C20: 145920 | D20: =B20-C20 -> 0
B21: ='Price grid'!I20 -> 173520 | C21: 173520 | D21: =B21-C21 -> 0
B22: ='Price grid'!I21 -> 159120 | C22: 159120 | D22: =B22-C22 -> 0
A23: Sensitivity: 50% fewer withdrawals → profit | B23: =Sensitivity!AG7 -> 69190.4 | C23: 69190.4 | D23: =B23-C23 -> 0
A24: Sensitivity: Plus features 0.50 → profit | B24: =Sensitivity!AG12 -> 135862.4 | C24: 135862.4 | D24: =B24-C24 -> 0
A25: Sensitivity: take-up −20% → profit | B25: =Sensitivity!AG13 -> 137054.72 | C25: 137054.72 | D25: =B25-C25 -> 0
A26: Sensitivity: churn doubles → profit | B26: =Sensitivity!AG15 -> 130275.2 | C26: 130275.2 | D26: =B26-C26 -> 0
A27: What-if: interchange 0.1% + fee 2.00 → contribution | B27: =Sensitivity!AF20 -> 863875.2 | C27: 863875.2 | D27: =B27-C27 -> 0
A28: Option: student fence → contribution | B28: =Sensitivity!AF22 -> 883886.4 | C28: 883886.4 | D28: =B28-C28 -> 0
A29: Option: Plus 4.99 → contribution | B29: =Sensitivity!AF23 -> 856483.2 | C29: 856483.2 | D29: =B29-C29 -> 0
A30: Adjusted breakeven: Plus 3.99 → 4.99 | B30: ='Break-even'!F41 -> -0.48216008 | C30: -0.48216 | D30: =B30-C30 -> -7.7145612e-08
A31: Adjusted breakeven: Travel 6.99 → 8.99 | B31: ='Break-even'!F43 -> -0.47058824 | C31: -0.470588 | D31: =B31-C31 -> -2.3529412e-07
A32: Take-up needed at Travel 7.99 | B32: ='Break-even'!B51 -> 0.48461538 | C32: 0.484615 | D32: =B32-C32 -> 3.8461538e-07
A33: Switching value: withdrawals avoided | B33: ='Stress test'!F6 -> 0.8233438 | C33: 0.823344 | D33: =B33-C33 -> -1.9859429e-07
A34: Switching value: plan take-up factor | B34: ='Stress test'!F7 -> 0.099448779 | C34: 0.099449 | D34: =B34-C34 -> -2.2102818e-07
A35: Switching value: cost per withdrawal | B35: ='Stress test'!F10 -> 1.2781499 | C35: 1.27815 | D35: =B35-C35 -> -5.5572396e-08
A36: Switching value: interchange | B36: ='Stress test'!F11 -> 0.001221435 | C36: 0.001221 | D36: =B36-C36 -> 4.3503592e-07
A37: Adverse selection in Plus → profit | B37: ='Stress test'!B25 -> 56662.4 | C37: 56662.4 | D37: =B37-C37 -> 0
A38: Bridge: leavers no longer served | B38: =Bridge!B10 -> 40204.8 | C38: 40204.8 | D38: =B38-C38 -> 0
A39: Monte Carlo, recommended: mean profit | B39: ='Stress test'!B40 -> 51007.901 | C39: 51007.901 | D39: =B39-C39 -> 2.4796464e-07
A40: Monte Carlo, recommended: 5th percentile | B40: ='Stress test'!C40 -> -27704.55 | C40: -27704.55 | D40: =B40-C40 -> -2.6063935e-07
A41: Monte Carlo, recommended: median | B41: ='Stress test'!E40 -> 52915.517 | C41: 52915.517 | D41: =B41-C41 -> -9.2462869e-08
A42: Monte Carlo, recommended: probability of a loss | B42: ='Stress test'!H40 -> 0.1382 | C42: 0.1382 | D42: =B42-C42 -> 0
A43: Monte Carlo, Basic + Travel: mean profit | B43: ='Stress test'!B41 -> -37626.213 | C43: -37626.213 | D43: =B43-C43 -> -1.5627302e-07
A44: Monte Carlo, per use only: mean profit | B44: ='Stress test'!B42 -> -128073.55 | C44: -128073.55 | D44: =B44-C44 -> -2.8101203e-07
A45: Monte Carlo, one fee: median | B45: ='Stress test'!E43 -> -86253.785 | C45: -86253.785 | D45: =B45-C45 -> -4.0000305e-07
A46: Monte Carlo, one fee: probability of a loss | B46: ='Stress test'!H43 -> 0.6946 | C46: 0.6946 | D46: =B46-C46 -> 0
A47: Share of draws: recommended beats one fee | B47: ='Stress test'!B44 -> 0.8512 | C47: 0.8512 | D47: =B47-C47 -> 0
A48: Option: Plus 2.99 for everyone → profit | B48: =Sensitivity!AG27 -> 127352 | C48: 127352 | D48: =B48-C48 -> 0
A49: Option: Travel 8.99 → profit | B49: =Sensitivity!AG24 -> 161782.4 | C49: 161782.4 | D49: =B49-C49 -> 0
A50: Adjusted breakeven, students: 3.99 → 2.99 | B50: ='Break-even'!F56 -> 0.6557377 | C50: 0.655738 | D50: =B50-C50 -> -2.9508197e-07
A52: Max absolute difference | D52: =MAX(ABS(MIN(D5:D50)),ABS(MAX(D5:D50))) -> 4.3503592e-07
